Workbook

Sheet Cover
A1: ASSOCIA BRANCH READINESS — INTEGRATED ASSESSMENT v3.0
A3: One document. Branch answers the question. Assessor marks PC / AC / FB. Output sheets auto-populate.
A5: Branch Name
A6: Assessment Date
A7: Assessor
A8: Source System
A10: CLASSIFICATION CODES
A11: PC | B11: Process Change | C11: TownSq supports this natively. Branch must adapt how they work. | E11: Change Plan sheet
A12: AC | B12: Adoption / Config | C12: TownSq supports this after configuration, data setup, or training. | E12: Onboarding List sheet
A13: FB | B13: Feature Backlog | C13: TownSq cannot support this today. Must be built or put on roadmap. | E13: Product Backlog sheet — assign P0–P3
A14: NA | B14: Not Applicable | C14: Branch does not use this capability. | E14: Excluded from score
A16: HOW TO USE
A17: Branch | B17: Send to branch ops lead 3 days before the discovery session. They type their answers in the yellow Answer column.
A18: Assessor | B18: During the 60-min session, read each answer and mark PC / AC / FB / NA in the Classification column.
A19: Auto | B19: The Change Plan, Onboarding List, and Product Backlog sheets auto-populate as you classify.
A20: FB only | B20: For Feature Backlog rows, also set the FB Priority (P0–P3) in column J.
A21: Output | B21: Review the three output sheets — share Change Plan with ops, Onboarding List with implementation, Backlog with product.

Sheet Assessment
A1: BRANCH ASSESSMENT — One row per dimension. Branch answers → Assessor classifies.
A2: BRANCH: Read the Discovery Question in column G and type your answer in column H (yellow). ASSESSOR: Read the branch's answer and mark column I as PC / AC / FB / NA. For FB items, also set FB Priority in column J. Output sheets auto-populate as you classify.
A3: ← READ ONLY — Do not edit columns A–F or K | H3: BRANCH FILLS THIS | I3: SME fills once — one-time exercise | L3: ASSESSOR NOTES
A4: Dom # | B4: Domain | C4: Cap # | D4: Capability | E4: Dimension | F4: Priority | G4: Discovery Question — what to ask the branch | H4: Branch Answer — describe your current process | I4: TownSq Capability — what TownSq supports today | J4: Classification PC / AC / FB / NA | K4: FB Priority (P0–P3 if FB) | L4: Assessor Notes | M4: AC# | N4: FB# | O4: PC# | P4: QID — Dom.Cap.Seq | Q4: UID — permanent key
A5: 1 | B5: Platform Foundation | C5: 1.1 | D5: General System Access | E5: Multi-system navigation | F5: P0 | G5: How many different systems does your branch log into daily? List them ALL by name. | I5: After config — TownSq Business (back-office) and TownSq Community (homeowner portal) are separate logins; WorkPoints+ is the accounting core. Managers must navigate two or three interfaces daily. ~ verify current SSO roadmap | M5: =IF($J5="AC",COUNTIF($J$5:$J5,"AC"),"") | N5: =IF($J5="FB",COUNTIF($J$5:$J5,"FB"),"") | O5: =IF($J5="PC",COUNTIF($J$5:$J5,"PC"),"") | P5: 1.1.1 | Q5: Q0001
A6: 1 | B6: Platform Foundation | C6: 1.1 | D6: General System Access | E6: User account management | F6: P0 | G6: Who manages user account creation, modification and removal today? What is the process when a new employee starts? | I6: After config — User accounts created and managed in TownSq admin console; new-user setup requires admin role. Process differs from legacy systems. ✓ | M6: =IF($J6="AC",COUNTIF($J$5:$J6,"AC"),"") | N6: =IF($J6="FB",COUNTIF($J$5:$J6,"FB"),"") | O6: =IF($J6="PC",COUNTIF($J$5:$J6,"PC"),"") | P6: 1.1.2 | Q6: Q0002
A7: 1 | B7: Platform Foundation | C7: 1.1 | D7: General System Access | E7: Password reset / access mgmt | F7: P0 | G7: What is the step-by-step process when a user is locked out or needs a password reset? | I7: Native — Standard email-based password reset and account recovery; no admin intervention needed for most resets. ✓ | M7: =IF($J7="AC",COUNTIF($J$5:$J7,"AC"),"") | N7: =IF($J7="FB",COUNTIF($J$5:$J7,"FB"),"") | O7: =IF($J7="PC",COUNTIF($J$5:$J7,"PC"),"") | P7: 1.1.3 | Q7: Q0003
A8: 1 | B8: Platform Foundation | C8: 1.1 | D8: General System Access | E8: Issue submission process | F8: P1 | G8: When you find a system bug or need to report a technical problem, what do you do? Who do you contact and how? | I8: After config — Support tickets submitted via TownSq Help Center portal or Associa internal ticketing; process needs to be configured and communicated to branches. ~ | M8: =IF($J8="AC",COUNTIF($J$5:$J8,"AC"),"") | N8: =IF($J8="FB",COUNTIF($J$5:$J8,"FB"),"") | O8: =IF($J8="PC",COUNTIF($J$5:$J8,"PC"),"") | P8: 1.1.4 | Q8: Q0004
A9: 1 | B9: Platform Foundation | C9: 1.2 | D9: User Security / Permissions | E9: Role-based access control | F9: P0 | G9: Who is responsible for managing user security and permissions? Can you restrict what different roles can see or do? | I9: After config — TownSq Business supports role-based permissions (Manager, Admin, Read-Only, Accounting, etc.). Roles assigned per user; granularity varies by module. ✓ | M9: =IF($J9="AC",COUNTIF($J$5:$J9,"AC"),"") | N9: =IF($J9="FB",COUNTIF($J$5:$J9,"FB"),"") | O9: =IF($J9="PC",COUNTIF($J$5:$J9,"PC"),"") | P9: 1.2.1 | Q9: Q0005
A10: 1 | B10: Platform Foundation | C10: 1.2 | D10: User Security / Permissions | E10: Board member access | F10: P0 | G10: Do any board members have direct login access to your systems today? If yes, what can they see or do? | I10: After config — Board members can be granted TownSq Community access to view financials, documents, and announcements. Access scoped to their association only. ✓ | M10: =IF($J10="AC",COUNTIF($J$5:$J10,"AC"),"") | N10: =IF($J10="FB",COUNTIF($J$5:$J10,"FB"),"") | O10: =IF($J10="PC",COUNTIF($J$5:$J10,"PC"),"") | P10: 1.2.2 | Q10: Q0006
A11: 1 | B11: Platform Foundation | C11: 1.2 | D11: User Security / Permissions | E11: Attorney / external access | F11: P1 | G11: Do any affiliated groups — attorneys, collections agencies — have direct access to your systems to manage delinquencies? | I11: Partial — External users (attorneys) can be given read-only Community access but there is no dedicated attorney/legal portal or collections-agency role. ! verify with TownSq product | M11: =IF($J11="AC",COUNTIF($J$5:$J11,"AC"),"") | N11: =IF($J11="FB",COUNTIF($J$5:$J11,"FB"),"") | O11: =IF($J11="PC",COUNTIF($J$5:$J11,"PC"),"") | P11: 1.2.3 | Q11: Q0007
A12: 1 | B12: Platform Foundation | C12: 1.2 | D12: User Security / Permissions | E12: LOA / temporary access mgmt | F12: P2 | G12: Do you have a policy for user access when someone is on extended leave? Describe what happens to their access. | I12: Not supported — No formal LOA workflow; disabling or restricting a user during leave requires manual admin action with no automated reinstatement. ~ | M12: =IF($J12="AC",COUNTIF($J$5:$J12,"AC"),"") | N12: =IF($J12="FB",COUNTIF($J$5:$J12,"FB"),"") | O12: =IF($J12="PC",COUNTIF($J$5:$J12,"PC"),"") | P12: 1.2.4 | Q12: Q0008
A13: 1 | B13: Platform Foundation | C13: 1.3 | D13: Data Management / Master Data | E13: Association record structure | F13: P0 | G13: Are your association IDs consistent (all letters, all numbers, or a mix)? Provide an example. How are they assigned? | I13: After config — Association records structured with a unique ID, legal name, unit count, management contract details. ID format must be standardised before import. ✓ | M13: =IF($J13="AC",COUNTIF($J$5:$J13,"AC"),"") | N13: =IF($J13="FB",COUNTIF($J$5:$J13,"FB"),"") | O13: =IF($J13="PC",COUNTIF($J$5:$J13,"PC"),"") | P13: 1.3.1 | Q13: Q0009
A14: 1 | B14: Platform Foundation | C14: 1.3 | D14: Data Management / Master Data | E14: Unit / lot data completeness | F14: P0 | G14: Do you have a complete list showing the number of units in each association? How current and reliable is that data? | I14: After config — Unit/lot records imported via data migration template; completeness of incoming data drives accuracy. Post-import validation step required. ✓ | M14: =IF($J14="AC",COUNTIF($J$5:$J14,"AC"),"") | N14: =IF($J14="FB",COUNTIF($J$5:$J14,"FB"),"") | O14: =IF($J14="PC",COUNTIF($J$5:$J14,"PC"),"") | P14: 1.3.2 | Q14: Q0010
A15: 1 | B15: Platform Foundation | C15: 1.3 | D15: Data Management / Master Data | E15: Tax ID / legal entity data | F15: P0 | G15: Can you provide a list of Tax IDs for all associations? Are associations listed by common name or legal name? | I15: After config — Tax ID field exists on the association record. Must be populated as part of onboarding; not auto-populated from any external source. ✓ | M15: =IF($J15="AC",COUNTIF($J$5:$J15,"AC"),"") | N15: =IF($J15="FB",COUNTIF($J$5:$J15,"FB"),"") | O15: =IF($J15="PC",COUNTIF($J$5:$J15,"PC"),"") | P15: 1.3.3 | Q15: Q0011
A16: 1 | B16: Platform Foundation | C16: 1.3 | D16: Data Management / Master Data | E16: Transition-in / out process | F16: P0 | G16: Walk through your step-by-step process for setting up a new client when they transition in. Who is involved and how long does it take? | I16: After config — No automated transition-in wizard; new association setup is a multi-step manual process (COA, bank accounts, owner import, billing setup). Guided by implementation checklist. ~ | M16: =IF($J16="AC",COUNTIF($J$5:$J16,"AC"),"") | N16: =IF($J16="FB",COUNTIF($J$5:$J16,"FB"),"") | O16: =IF($J16="PC",COUNTIF($J$5:$J16,"PC"),"") | P16: 1.3.4 | Q16: Q0012
... A92: 5 | B92: Operations & Tasks | C92: 5.6 | D92: Board Packets | E92: Digital distribution to board | F92: P1 | G92: How are packets delivered to board members today — email, portal, physical binder, or a combination? How far in advance? | I92: After config — Board packets distributed digitally to board members via TownSq portal or email. Board members notified on publication. ✓ | M92: =IF($J92="AC",COUNTIF($J$5:$J92,"AC"),"") | N92: =IF($J92="FB",COUNTIF($J$5:$J92,"FB"),"") | O92: =IF($J92="PC",COUNTIF($J$5:$J92,"PC"),"") | P92: 5.6.3 | Q92: Q0088
A93: 6 | B93: Financial Operations | C93: 6.1 | D93: Accounts Payable | E93: Invoice intake & routing | F93: P0 | G93: Walk through your AP process step by step — from invoice receipt to payment. Who touches it at each stage? | I93: After config — AP invoice entry and routing native in TownSq Business (WorkPoints+). Invoice workflow requires GL coding, association assignment, and approver configuration. ✓ | O93: =IF($J93="PC",COUNTIF($J$5:$J93,"PC"),"") | P93: 6.1.1 | Q93: Q0089
A94: 6 | B94: Financial Operations | C94: 6.1 | D94: Accounts Payable | E94: Approval / hold / reject workflow | F94: P0 | G94: Do you have dollar limits that require Board Member or Branch Executive approval before paying an invoice? What are the thresholds and who approves? | I94: After config — Dollar-threshold approval rules configurable in TownSq AP module. Board-approval routing and branch-exec approval rules set during onboarding. ✓ | O94: =IF($J94="PC",COUNTIF($J$5:$J94,"PC"),"") | P94: 6.1.2 | Q94: Q0090
A95: 6 | B95: Financial Operations | C95: 6.1 | D95: Accounts Payable | E95: ACH payment processing | F95: P0 | G95: Do you pay any vendors by ACH? If yes, how do you set up an ACH vendor and how are payments initiated? | I95: After config — ACH vendor payments supported in TownSq. Vendor must have ACH banking details on file; payment runs initiated from AP module. ✓ | O95: =IF($J95="PC",COUNTIF($J$5:$J95,"PC"),"") | P95: 6.1.3 | Q95: Q0091
A96: 6 | B96: Financial Operations | C96: 6.1 | D96: Accounts Payable | E96: Cash-poor / priority handling | F96: P1 | G96: If there is not enough money in an association's bank account to pay a vendor, what happens? Who decides what gets paid and in what order? | I96: Partial — No automated cash-poor / priority queue; assessor or manager manually reviews and holds or prioritises invoices in TownSq when funds are limited. ~ | O96: =IF($J96="PC",COUNTIF($J$5:$J96,"PC"),"") | P96: 6.1.4 | Q96: Q0092
A97: 6 | B97: Financial Operations | C97: 6.1 | D97: Accounts Payable | E97: Invoice history & notes | F97: P1 | G97: How do you view the payment history for a vendor or a specific invoice? Can you add notes or comments to an invoice record? | I97: Native — Full AP invoice history accessible by vendor, association, or date range in TownSq Business. Notes and attachments included. ✓ | O97: =IF($J97="PC",COUNTIF($J$5:$J97,"PC"),"") | P97: 6.1.5 | Q97: Q0093
A98: 6 | B98: Financial Operations | C98: 6.1 | D98: Accounts Payable | E98: Supporting document mgmt | F98: P1 | G98: How are supporting documents (contracts, POs, photos of work) attached to an invoice before it goes through approval? | I98: After config — Supporting documents (contracts, photos of work, purchase orders) attached to invoice records in TownSq before approval routing. ✓ | O98: =IF($J98="PC",COUNTIF($J$5:$J98,"PC"),"") | P98: 6.1.6 | Q98: Q0094
A99: 6 | B99: Financial Operations | C99: 6.1 | D99: Accounts Payable | E99: Duplicate Invoice Control | F99: P0 | G99: How do you detect and prevent duplicate vendor invoices across all entry channels before payment is released? | M99: =IF($J99="AC",COUNTIF($J$5:$J99,"AC"),"") | N99: =IF($J99="FB",COUNTIF($J$5:$J99,"FB"),"") | O99: =IF($J99="PC",COUNTIF($J$5:$J99,"PC"),"") | P99: 6.1.7 | Q99: Q0095
A100: 6 | B100: Financial Operations | C100: 6.1 | D100: Accounts Payable | E100: Vendor Mgmt | F100: P0 | G100: Who owns vendor master maintenance, and how are new vendor records, address changes, and bank detail changes validated before use? | M100: =IF($J100="AC",COUNTIF($J$5:$J100,"AC"),"") | N100: =IF($J100="FB",COUNTIF($J$5:$J100,"FB"),"") | O100: =IF($J100="PC",COUNTIF($J$5:$J100,"PC"),"") | P100: 6.1.8 | Q100: Q0096
A101: 6 | B101: Financial Operations | C101: 6.1 | D101: Accounts Payable | E101: Recurring Charges / Coding Defaults | F101: P0 | G101: Are recurring vendor charges pre-coded from templates/rules, and how are GL/property/class codes populated for new bills? | M101: =IF($J101="AC",COUNTIF($J$5:$J101,"AC"),"") | N101: =IF($J101="FB",COUNTIF($J$5:$J101,"FB"),"") | O101: =IF($J101="PC",COUNTIF($J$5:$J101,"PC"),"") | P101: 6.1.9 | Q101: Q0097
A102: 6 | B102: Financial Operations | C102: 6.1 | D102: Accounts Payable | E102: Contract Matching | F102: P0 | G102: Do you require purchase orders, contracts, or work-order references matched to invoices before approval? Where is that link maintained? | M102: =IF($J102="AC",COUNTIF($J$5:$J102,"AC"),"") | N102: =IF($J102="FB",COUNTIF($J$5:$J102,"FB"),"") | O102: =IF($J102="PC",COUNTIF($J$5:$J102,"PC"),"") | P102: 6.1.10 | Q102: Q0098
A103: 6 | B103: Financial Operations | C103: 6.1 | D103: Accounts Payable | E103: Fraud Controls | F103: P0 | G103: What controls/checks happen between the AP system, the bank, and fraud mitigation measures (e.g., Positive Pay) before money leaves the account? | M103: =IF($J103="AC",COUNTIF($J$5:$J103,"AC"),"") | N103: =IF($J103="FB",COUNTIF($J$5:$J103,"FB"),"") | O103: =IF($J103="PC",COUNTIF($J$5:$J103,"PC"),"") | P103: 6.1.11 | Q103: Q0099
A104: 6 | B104: Financial Operations | C104: 6.1 | D104: Accounts Payable | E104: Exception Handling | F104: P1 | G104: How are voided, stopped, or rejected AP payments traced to the original invoice and reflected in the GL & vendor history? | M104: =IF($J104="AC",COUNTIF($J$5:$J104,"AC"),"") | N104: =IF($J104="FB",COUNTIF($J$5:$J104,"FB"),"") | O104: =IF($J104="PC",COUNTIF($J$5:$J104,"PC"),"") | P104: 6.1.12 | Q104: Q0100
A105: 6 | B105: Financial Operations | C105: 6.1 | D105: Accounts Payable | E105: AP Visibility & Liability Aging | F105: P1 | G105: How do you review AP aging or open liabilities by association, vendor, or approver across the portfolio? | M105: =IF($J105="AC",COUNTIF($J$5:$J105,"AC"),"") | N105: =IF($J105="FB",COUNTIF($J$5:$J105,"FB"),"") | O105: =IF($J105="PC",COUNTIF($J$5:$J105,"PC"),"") | P105: 6.1.13 | Q105: Q0101
A106: 6 | B106: Financial Operations | C106: 6.1 | D106: Accounts Payable | E106: Systems Involved | F106: P0 | G106: Which systems receive AP invoice data after posting (e.g., reporting, document storage, ticketing)—is that sync automated or manual? | M106: =IF($J106="AC",COUNTIF($J$5:$J106,"AC"),"") | N106: =IF($J106="FB",COUNTIF($J$5:$J106,"FB"),"") | O106: =IF($J106="PC",COUNTIF($J$5:$J106,"PC"),"") | P106: 6.1.14 | Q106: Q0102
A107: 6 | B107: Financial Operations | C107: 6.1 | D107: Accounts Payable | E107: Fraud Controls | F107: P0 | G107: What controls are in place to verify the authenticity of vendor invoices and protect against business email compromise/phishing? | M107: =IF($J107="AC",COUNTIF($J$5:$J107,"AC"),"") | N107: =IF($J107="FB",COUNTIF($J$5:$J107,"FB"),"") | O107: =IF($J107="PC",COUNTIF($J$5:$J107,"PC"),"") | P107: 6.1.15 | Q107: Q0103
A108: 6 | B108: Financial Operations | C108: 6.1 | D108: Accounts Payable | E108: Backup Mgmt | F108: P3 | G108: In case of outage/ransomware, how quickly can AP processing resume, and are vendor records backed up offsite? | M108: =IF($J108="AC",COUNTIF($J$5:$J108,"AC"),"") | N108: =IF($J108="FB",COUNTIF($J$5:$J108,"FB"),"") | O108: =IF($J108="PC",COUNTIF($J$5:$J108,"PC"),"") | P108: 6.1.16 | Q108: Q0104
A109: 6 | B109: Financial Operations | C109: 6.1 | D109: Accounts Payable | E109: Regulatory & Compliance Updates | F109: P1 | G109: How does your AP system stay updated for 1099 reporting, IRS/state requirements, or other regulatory changes affecting vendor payments? | M109: =IF($J109="AC",COUNTIF($J$5:$J109,"AC"),"") | N109: =IF($J109="FB",COUNTIF($J$5:$J109,"FB"),"") | O109: =IF($J109="PC",COUNTIF($J$5:$J109,"PC"),"") | P109: 6.1.17 | Q109: Q0105
A110: 6 | B110: Financial Operations | C110: 6.1 | D110: Accounts Payable | E110: Systems Involved | F110: P0 | G110: Are paper invoices still received and, if so, what is the process for digitizing them and using them in existing systems? | M110: =IF($J110="AC",COUNTIF($J$5:$J110,"AC"),"") | N110: =IF($J110="FB",COUNTIF($J$5:$J110,"FB"),"") | O110: =IF($J110="PC",COUNTIF($J$5:$J110,"PC"),"") | P110: 6.1.18 | Q110: Q0106
... A121: 6 | B121: Financial Operations | C121: 6.1 | D121: Accounts Payable | E121: Fraud Controls | F121: P0 | G121: Have you detected or prevented vendor fraud attempts involving multiple HOAs, and how was this identified? | M121: =IF($J121="AC",COUNTIF($J$5:$J121,"AC"),"") | N121: =IF($J121="FB",COUNTIF($J$5:$J121,"FB"),"") | O121: =IF($J121="PC",COUNTIF($J$5:$J121,"PC"),"") | P121: 6.1.29 | Q121: Q0117
A122: 6 | B122: Financial Operations | C122: 6.2 | D122: Accounts Receivable | E122: Lockbox payment processing | F122: P0 | G122: Do you use lockbox processing for homeowner assessment payments? Which bank? What percentage of homeowners pay through the lockbox? | I122: After config — Lockbox payment file import supported in TownSq AR module. Bank sends file; TownSq processes and posts payments. Bank and file format must be configured. ✓ | O122: =IF($J122="PC",COUNTIF($J$5:$J122,"PC"),"") | P122: 6.2.1 | Q122: Q0118
A123: 6 | B123: Financial Operations | C123: 6.2 | D123: Accounts Receivable | E123: ACH / direct debit enrollment | F123: P0 | G123: Does your branch process direct debit (ACH pull) payments from owners? What day of the month are they pulled, and how do owners enroll? Does some one does it for you already or do we need to set it up in TSQB. | I123: There are two types of ACH payment models. One is homeowner-initiated payments through the portal using external providers, and the other is branch-initiated direct debit, where the branch collects bank information and executes a batch process to pull funds from homeowner accounts on a scheduled basis. This question is intended to determine whether the branch uses internal direct debit processing or relies on third-party providers. | O123: =IF($J123="PC",COUNTIF($J$5:$J123,"PC"),"") | P123: 6.2.2 | Q123: Q0119
A124: 6 | B124: Financial Operations | C124: 6.2 | D124: Accounts Receivable | E124: Special assessment processing | F124: P0 | G124: Do any associations currently have special assessments? Describe how those payments are collected, recorded, and tracked separately from regular dues. What method do you use - Lump sum, multi year payments (late fee schedule) | I124: Special assessments can be handled in multiple ways depending on association requirements. They may be collected as a one-time lump sum, structured as multi-year installment plans, or tracked in separate ledgers distinct from regular dues. In some cases, special assessments may also follow different delinquency rules. The purpose of this question is to understand the specific approach used so it can be properly configured during implementation. | O124: =IF($J124="PC",COUNTIF($J$5:$J124,"PC"),"") | P124: 6.2.3 | Q124: Q0120
A125: 6 | B125: Financial Operations | C125: 6.2 | D125: Accounts Receivable | E125: Payment exceptions handling | F125: P1 | G125: On average, how many lockbox exceptions does your branch handle each day? What types of exceptions occur most often and how are they resolved? | I125: After config — Lockbox exceptions handled manually in TownSq; exception report generated after each file load. Resolution process defined in onboarding. ✓ | O125: =IF($J125="PC",COUNTIF($J$5:$J125,"PC"),"") | P125: 6.2.4 | Q125: Q0121
A126: 6 | B126: Financial Operations | C126: 6.2 | D126: Accounts Receivable | E126: Refunds & adjustments | F126: P1 | G126: How do homeowners request refunds? Walk through the approval and posting process. Which GL code do you use? | I126: After config — Homeowner account adjustments, credits, and refunds posted in TownSq AR. Refunds processed as manual cheques or ACH reversals. ✓ | O126: =IF($J126="PC",COUNTIF($J$5:$J126,"PC"),"") | P126: 6.2.5 | Q126: Q0122
A127: 6 | B127: Financial Operations | C127: 6.2 | D127: Accounts Receivable | E127: Returned payment processing | F127: P1 | G127: How does the branch handle returned payments — NSF checks and returned ACH? Do homeowners pay additional fees beyond the bank charge? | I127: After config — Returned payment (NSF, returned ACH) processing native in TownSq. Returned-item fees configurable per association policy. ✓ | O127: =IF($J127="PC",COUNTIF($J$5:$J127,"PC"),"") | P127: 6.2.6 | Q127: Q0123
A128: 6 | B128: Financial Operations | C128: 6.2 | D128: Accounts Receivable | E128: Account Receivables Workflows & Process Flows | F128: P1 | G128: Walk me through the end-to-end AR lifecycle — from assessment generation (dues, special assessments, fines) through to cash application and reconciliation. | I128: After config RC: Charges are created via recurring charges or one-time charges (manual or import). Once posted to the unit ledger, cash is applied either automatically (based on configured priority rules like dues → assessments → penalties) or manually per unit. | O128: =IF($J128="PC",COUNTIF($J$5:$J128,"PC"),"") | P128: 6.2.7 | Q128: Q0124
A129: 6 | B129: Financial Operations | C129: 6.2 | D129: Accounts Receivable | E129: Core AR Systems & Platforms | F129: P1 | G129: Are AR functions managed within a single platform across all communities, or do you have multiple systems in use across different portfolios or regions? | I129: TBD — confirm with domain SME | M129: =IF($J129="AC",COUNTIF($J$5:$J129,"AC"),"") | N129: =IF($J129="FB",COUNTIF($J$5:$J129,"FB"),"") | O129: =IF($J129="PC",COUNTIF($J$5:$J129,"PC"),"") | P129: 6.2.8 | Q129: Q0125
A130: 6 | B130: Financial Operations | C130: 6.2 | D130: Accounts Receivable | E130: Move-in / move-out and ancillary fee billing | F130: P1 | G130: Beyond regular assessments and special assessments, what other fees does your branch bill to homeowners — move-in fees, parking, storage, amenity access fees, transfer fees? How are these set up and billed? | I130: TBD — confirm with domain SME | M130: =IF($J130="AC",COUNTIF($J$5:$J130,"AC"),"") | N130: =IF($J130="FB",COUNTIF($J$5:$J130,"FB"),"") | O130: =IF($J130="PC",COUNTIF($J$5:$J130,"PC"),"") | P130: 6.2.9 | Q130: Q0126
A131: 6 | B131: Financial Operations | C131: 6.2 | D131: Accounts Receivable | E131: Payment Application Hierarchy | F131: P0 | G131: How are payments from different channels prioritized when an owner pays less than the full balance (dues, fines, assessments, etc.)? | M131: =IF($J131="AC",COUNTIF($J$5:$J131,"AC"),"") | N131: =IF($J131="FB",COUNTIF($J$5:$J131,"FB"),"") | O131: =IF($J131="PC",COUNTIF($J$5:$J131,"PC"),"") | P131: 6.2.10 | Q131: Q0127
A132: 6 | B132: Financial Operations | C132: 6.2 | D132: Accounts Receivable | E132: Billing Rule Propagation | F132: P1 | G132: When assessment rates, billing frequencies, or late-fee rules change, how are those changes updated in statements, portals, and autopay records? | M132: =IF($J132="AC",COUNTIF($J$5:$J132,"AC"),"") | N132: =IF($J132="FB",COUNTIF($J$5:$J132,"FB"),"") | O132: =IF($J132="PC",COUNTIF($J$5:$J132,"PC"),"") | P132: 6.2.11 | Q132: Q0128
A133: 6 | B133: Financial Operations | C133: 6.2 | D133: Accounts Receivable | E133: Cash Receipt Reconciliation | F133: P0 | G133: What is the end-to-end process for reconciling payment files from lockbox, online portal, ACH, and processors against open receivables? | M133: =IF($J133="AC",COUNTIF($J$5:$J133,"AC"),"") | N133: =IF($J133="FB",COUNTIF($J$5:$J133,"FB"),"") | O133: =IF($J133="PC",COUNTIF($J$5:$J133,"PC"),"") | P133: 6.2.12 | Q133: Q0129
A134: 6 | B134: Financial Operations | C134: 6.2 | D134: Accounts Receivable | E134: Cross-System Account Mapping | F134: P1 | G134: Who maintains mapping between the owner ledger and external channels (portal, payment processor, mail vendor, etc.) when an account moves or merges? | M134: =IF($J134="AC",COUNTIF($J$5:$J134,"AC"),"") | N134: =IF($J134="FB",COUNTIF($J$5:$J134,"FB"),"") | O134: =IF($J134="PC",COUNTIF($J$5:$J134,"PC"),"") | P134: 6.2.13 | Q134: Q0130
A135: 6 | B135: Financial Operations | C135: 6.2 | D135: Accounts Receivable | E135: Dispute Handling | F135: P1 | G135: How are card chargebacks and payment disputes recorded, investigated, and connected to the original AR transaction? | M135: =IF($J135="AC",COUNTIF($J$5:$J135,"AC"),"") | N135: =IF($J135="FB",COUNTIF($J$5:$J135,"FB"),"") | O135: =IF($J135="PC",COUNTIF($J$5:$J135,"PC"),"") | P135: 6.2.14 | Q135: Q0131
A136: 6 | B136: Financial Operations | C136: 6.2 | D136: Accounts Receivable | E136: Ownership Change Automation | F136: P1 | G136: When a property changes ownership, how are autopay enrollments, communication preferences, and delinquent balances re-evaluated for the new owner? | M136: =IF($J136="AC",COUNTIF($J$5:$J136,"AC"),"") | N136: =IF($J136="FB",COUNTIF($J$5:$J136,"FB"),"") | O136: =IF($J136="PC",COUNTIF($J$5:$J136,"PC"),"") | P136: 6.2.15 | Q136: Q0132
A137: 6 | B137: Financial Operations | C137: 6.2 | D137: Accounts Receivable | E137: Exception Handling | F137: P1 | G137: How do you identify and resolve AR exceptions needing manual review (e.g., unapplied cash, overpayments, payments with missing references)? | M137: =IF($J137="AC",COUNTIF($J$5:$J137,"AC"),"") | N137: =IF($J137="FB",COUNTIF($J$5:$J137,"FB"),"") | O137: =IF($J137="PC",COUNTIF($J$5:$J137,"PC"),"") | P137: 6.2.16 | Q137: Q0133
A138: 6 | B138: Financial Operations | C138: 6.2 | D138: Accounts Receivable | E138: Balance Adjustment Notification | F138: P0 | G138: Who is notified when an owner’s balance is changed, and how are ledger/portal/customer communications synchronized? | M138: =IF($J138="AC",COUNTIF($J$5:$J138,"AC"),"") | N138: =IF($J138="FB",COUNTIF($J$5:$J138,"FB"),"") | O138: =IF($J138="PC",COUNTIF($J$5:$J138,"PC"),"") | P138: 6.2.17 | Q138: Q0134
A139: 6 | B139: Financial Operations | C139: 6.2 | D139: Accounts Receivable | E139: Owner Communication Preferences | F139: P0 | G139: How does your AR system accommodate owner preferences for payment reminders (email, SMS, mail), and can these be customized per association? | M139: =IF($J139="AC",COUNTIF($J$5:$J139,"AC"),"") | N139: =IF($J139="FB",COUNTIF($J$5:$J139,"FB"),"") | O139: =IF($J139="PC",COUNTIF($J$5:$J139,"PC"),"") | P139: 6.2.18 | Q139: Q0135
A140: 6 | B140: Financial Operations | C140: 6.2 | D140: Accounts Receivable | E140: Accessibility & Inclusivity | F140: P3 | G140: Are payment portals and owner communications accessible for those with disabilities or limited English proficiency? | M140: =IF($J140="AC",COUNTIF($J$5:$J140,"AC"),"") | N140: =IF($J140="FB",COUNTIF($J$5:$J140,"FB"),"") | O140: =IF($J140="PC",COUNTIF($J$5:$J140,"PC"),"") | P140: 6.2.19 | Q140: Q0136
A141: 6 | B141: Financial Operations | C141: 6.2 | D141: Accounts Receivable | E141: Regulatory (Fair Debt Practices) | F141: P0 | G141: How does your AR process ensure compliance with federal/state Fair Debt Collection laws (FDCPA, etc.) in owner communications and collections? | M141: =IF($J141="AC",COUNTIF($J$5:$J141,"AC"),"") | N141: =IF($J141="FB",COUNTIF($J$5:$J141,"FB"),"") | O141: =IF($J141="PC",COUNTIF($J$5:$J141,"PC"),"") | P141: 6.2.20 | Q141: Q0137
A142: 6 | B142: Financial Operations | C142: 6.2 | D142: Accounts Receivable | E142: Credit Reporting | F142: P2 | G142: Does the association ever report delinquencies to credit bureaus, and if so, how is consent managed and what recourse is available to owners? | M142: =IF($J142="AC",COUNTIF($J$5:$J142,"AC"),"") | N142: =IF($J142="FB",COUNTIF($J$5:$J142,"FB"),"") | O142: =IF($J142="PC",COUNTIF($J$5:$J142,"PC"),"") | P142: 6.2.21 | Q142: Q0138
... A154: 6 | B154: Financial Operations | C154: 6.2 | D154: Accounts Receivable | E154: Owner Education & Onboarding | F154: P2 | G154: What strategies are used to educate new owners on financial obligations and using the AR system (guides, webinars, onboarding, etc.)? | M154: =IF($J154="AC",COUNTIF($J$5:$J154,"AC"),"") | N154: =IF($J154="FB",COUNTIF($J$5:$J154,"FB"),"") | O154: =IF($J154="PC",COUNTIF($J$5:$J154,"PC"),"") | P154: 6.2.33 | Q154: Q0150
A155: 6 | B155: Financial Operations | C155: 6.3 | D155: Banking | E155: Bank account setup / mgmt | F155: P0 | G155: Which bank is your branch's primary/partner bank? Please list all bank accounts — operating, reserve, lockbox — for each association. | I155: Each association typically maintains at least two core bank accounts: an operating account and a reserve account. However, the system supports multiple bank accounts per association, and in practice, associations may have anywhere from two to ten or more accounts depending on requirements. Identifying the primary partner bank is important because it affects integration capabilities and overall implementation complexity. | O155: =IF($J155="PC",COUNTIF($J$5:$J155,"PC"),"") | P155: 6.3.1 | Q155: Q0151
A156: 6 | B156: Financial Operations | C156: 6.3 | D156: Banking | E156: Lockbox bank configuration | F156: P0 | G156: Which bank(s) handle lockbox payments? Is the lockbox bank the same as your operating bank, or different? | I156: Lockbox processing may be handled by a bank that is different from the association’s primary operating bank. The key consideration is identifying which bank processes lockbox payments, as this determines the integration method and configuration requirements. Whether the lockbox bank matches the operating bank is less important than understanding the integration setup for lockbox processing. | O156: =IF($J156="PC",COUNTIF($J$5:$J156,"PC"),"") | P156: 6.3.2 | Q156: Q0152
A157: 6 | B157: Financial Operations | C157: 6.3 | D157: Banking | E157: Bank statement reconciliation | F157: P0 | G157: How do you complete monthly bank reconciliations — manually, in the system, or a combination? Walk through the steps. | I157: After config — Bank reconciliation module in TownSq Business. Cleared items matched against GL; reconciliation completed monthly within the system. ✓ | O157: =IF($J157="PC",COUNTIF($J$5:$J157,"PC"),"") | P157: 6.3.3 | Q157: Q0153
A158: 6 | B158: Financial Operations | C158: 6.3 | D158: Banking | E158: FDIC handling / account limits | F158: P1 | G158: Do you have a process for managing FDIC insurance limits across association accounts? Describe how funds are structured to stay within limits. | I158: Not supported — FDIC insurance limit management (e.g., distributing funds across accounts or CDARS/IntraFi) is not automated in TownSq. Must be managed manually and externally. ✓ | O158: =IF($J158="PC",COUNTIF($J$5:$J158,"PC"),"") | P158: 6.3.4 | Q158: Q0154
A159: 6 | B159: Financial Operations | C159: 6.3 | D159: Banking | E159: Investment / CD tracking | F159: P2 | G159: Do you track CDs and investments in your accounting system, or in a separate spreadsheet or elsewhere? How do you manage CD maturity dates? | I159: Not supported — CD and investment tracking not available as a structured module in TownSq. Investments typically tracked in a spreadsheet or bank portal with JEs posted to GL. ✓ | O159: =IF($J159="PC",COUNTIF($J$5:$J159,"PC"),"") | P159: 6.3.5 | Q159: Q0155
A160: 6 | B160: Financial Operations | C160: 6.3 | D160: Banking | E160: Managing the company’s cash position, liquidity, short-term investments, and banking relationships. | F160: P1 | G160: Describe your process for managing the company's daily cash position, specifying the tools you use to monitor bank accounts, the person responsible for executing transfers or investments, and your strategy for maximizing interest income. | I160: TBD — confirm with domain SME | M160: =IF($J160="AC",COUNTIF($J$5:$J160,"AC"),"") | N160: =IF($J160="FB",COUNTIF($J$5:$J160,"FB"),"") | O160: =IF($J160="PC",COUNTIF($J$5:$J160,"PC"),"") | P160: 6.3.6 | Q160: Q0156
A161: 6 | B161: Financial Operations | C161: 6.3 | D161: Banking | E161: Reconciling client association bank accounts with their financial records. | F161: P1 | G161: Could you detail your Bank Reconciliation (Client) process, highlighting inputs, validations, approvals, and outputs? Note the role of the manager vs. specialists, tools used, and how the process adapts for edge cases or exceptions. | I161: TBD — confirm with domain SME | M161: =IF($J161="AC",COUNTIF($J$5:$J161,"AC"),"") | N161: =IF($J161="FB",COUNTIF($J$5:$J161,"FB"),"") | O161: =IF($J161="PC",COUNTIF($J$5:$J161,"PC"),"") | P161: 6.3.7 | Q161: Q0157
A162: 6 | B162: Financial Operations | C162: 6.3 | D162: Banking | E162: Remote deposit capture (RDC) | F162: P2 | G162: Do any of your branches still receive physical checks from homeowners? If so, do you use remote deposit capture to deposit them? Describe the scanning, deposit, and reconciliation steps. | I162: TBD — confirm with domain SME | M162: =IF($J162="AC",COUNTIF($J$5:$J162,"AC"),"") | N162: =IF($J162="FB",COUNTIF($J$5:$J162,"FB"),"") | O162: =IF($J162="PC",COUNTIF($J$5:$J162,"PC"),"") | P162: 6.3.8 | Q162: Q0158
A163: 6 | B163: Financial Operations | C163: 6.3 | D163: Banking | E163: Sweep accounts & overnight investment | F163: P2 | G163: Do any of your associations use bank sweep accounts that automatically invest overnight balances? If so, how are sweep transactions handled in the bank reconciliation? | I163: TBD — confirm with domain SME | M163: =IF($J163="AC",COUNTIF($J$5:$J163,"AC"),"") | N163: =IF($J163="FB",COUNTIF($J$5:$J163,"FB"),"") | O163: =IF($J163="PC",COUNTIF($J$5:$J163,"PC"),"") | P163: 6.3.9 | Q163: Q0159
A164: 6 | B164: Financial Operations | C164: 6.3 | D164: Banking | E164: ↳ Banking Relationships & Account Setup | F164: P0 | G164: What happens when an association switches banks mid-year — how are AR records, payment routing, and bank integrations updated? | I164: When an association switches banks, the existing bank account is not deleted in the system but instead marked as inactive, preserving all historical records. A new bank account is then added, and all future transactions, including AR and payables, are directed to this new account. Payment routing updates involve linking direct debit withdrawals to the new account, ensuring check issuance systems like Strongroom use the correct account, and updating lockbox configurations so incoming payments are matched to the new bank account. For integrations, partner banks provide new login credentials that automatically link to the system, while non-partner banks are set up manually. Existing AR records remain unchanged and continue to reflect past activity tied to the old account. | O164: =IF($J164="PC",COUNTIF($J$5:$J164,"PC"),"") | P164: 6.3.10 | Q164: Q0160
A165: 6 | B165: Financial Operations | C165: 6.3 | D165: Banking | E165: ↳ Banking Relationships & Account Setup | F165: P0 | G165: What is the process for opening a new bank account for an association — who initiates, who approves, and how are bank details entered into the system? | I165: The process begins at the branch level, where roles such as the controller or accounting manager initiate the bank account opening by submitting a request to the bank. Once the bank confirms that the account has been opened, the branch receives the bank account details and submits a help desk ticket. The help desk is responsible for setting up the bank account within C3 or Town Square Business Accounting. This setup is not entirely standardized, as some branches may have direct access to the bank maintenance module depending on their role-based permissions configured within C3, while others rely entirely on the help desk for setup. | O165: =IF($J165="PC",COUNTIF($J$5:$J165,"PC"),"") | P165: 6.3.11 | Q165: Q0161
A166: 6 | B166: Financial Operations | C166: 6.3 | D166: Banking | E166: ↳ Banking Relationships & Account Setup | F166: P0 | G166: How are signatory authorities managed across association bank accounts — who has signing authority and how is that updated when board members change? | I166: Signatory authority is managed directly by the bank rather than within Town Square systems. The bank maintains the official record of who is authorized to sign on the account, and any updates to signatory authority—such as when board members change—must be handled directly with the bank. In some cases, updates can be performed digitally using tools like electronic signature forms. Within the system, signatures may be uploaded into tools like Strongroom for use in processes such as check printing, but there is no dedicated system interface for managing signatory changes. Operationally, signing authority typically resides with management company personnel rather than board members. | O166: =IF($J166="PC",COUNTIF($J$5:$J166,"PC"),"") | P166: 6.3.12 | Q166: Q0162
A167: 6 | B167: Financial Operations | C167: 6.3 | D167: Banking | E167: Cash Management & Investments | F167: P1 | G167: How are investment transactions (CD purchases, interest income, maturities) recorded in the system — posted to a dedicated investment account in the GL? | I167: TBD — confirm with TownSq product team | M167: =IF($J167="AC",COUNTIF($J$5:$J167,"AC"),"") | N167: =IF($J167="FB",COUNTIF($J$5:$J167,"FB"),"") | O167: =IF($J167="PC",COUNTIF($J$5:$J167,"PC"),"") | P167: 6.3.13 | Q167: Q0163
A168: 6 | B168: Financial Operations | C168: 6.3 | D168: Banking | E168: Bank Reconciliation | F168: P0 | G168: Do you have automatic bank reconciliation — is it a bank feed integration, BAI2 file import, or a fully manual process? | I168: TBD — confirm with TownSq product team | M168: =IF($J168="AC",COUNTIF($J$5:$J168,"AC"),"") | N168: =IF($J168="FB",COUNTIF($J$5:$J168,"FB"),"") | O168: =IF($J168="PC",COUNTIF($J$5:$J168,"PC"),"") | P168: 6.3.14 | Q168: Q0164
A169: 6 | B169: Financial Operations | C169: 6.3 | D169: Banking | E169: ↳ Bank Reconciliation | F169: P0 | G169: Who signs off on completed bank reconciliations — is there a secondary reviewer or approval step before the reconciliation is considered final? | I169: Bank reconciliations are completed within the system using a dedicated reconciliation module. Transactions from bank statements are matched against general ledger entries and cleared systematically. While some manual review may still be required depending on the bank integration, the process is largely system-driven and conducted on a regular monthly cycle | M169: =IF($J169="AC",COUNTIF($J$5:$J169,"AC"),"") | N169: =IF($J169="FB",COUNTIF($J$5:$J169,"FB"),"") | O169: =IF($J169="PC",COUNTIF($J$5:$J169,"PC"),"") | P169: 6.3.15 | Q169: Q0165
A170: 6 | B170: Financial Operations | C170: 6.3 | D170: Banking | E170: Transfers & Fraud Controls | F170: P0 | G170: How are inter-account transfers executed and what fraud controls are in place? | I170: TBD — confirm with TownSq product team | M170: =IF($J170="AC",COUNTIF($J$5:$J170,"AC"),"") | N170: =IF($J170="FB",COUNTIF($J$5:$J170,"FB"),"") | O170: =IF($J170="PC",COUNTIF($J$5:$J170,"PC"),"") | P170: 6.3.16 | Q170: Q0166
A171: 6 | B171: Financial Operations | C171: 6.3 | D171: Banking | E171: ↳ Transfers & Fraud Controls | F171: P0 | G171: What dual-control or positive pay controls are in place for outgoing wire transfers and ACH disbursements? | I171: Controls such as dual authorization or positive pay are configured at the bank level rather than within Town Square. Wire transfers cannot be executed directly through the Town Square system and require users to log into the bank’s online portal, where bank-level security measures like multi-factor authentication apply. For ACH disbursements, Town Square can facilitate transactions for partner banks, but broader security controls are still governed by the bank. Overall, Town Square does not provide built-in workflows for dual control or advanced payment safeguards; these controls depend on the bank’s configuration. | O171: =IF($J171="PC",COUNTIF($J$5:$J171,"PC"),"") | P171: 6.3.17 | Q171: Q0167
A172: 6 | B172: Financial Operations | C172: 6.3 | D172: Banking | E172: Autopay Handoff & Banking Changes | F172: P1 | G172: When a new bank account is set up, what is the process for updating routing and account numbers across all affected payment channels — lockbox, ACH, coupon books, homeowner portal? | I172: TBD — confirm with TownSq product team | M172: =IF($J172="AC",COUNTIF($J$5:$J172,"AC"),"") | N172: =IF($J172="FB",COUNTIF($J$5:$J172,"FB"),"") | O172: =IF($J172="PC",COUNTIF($J$5:$J172,"PC"),"") | P172: 6.3.18 | Q172: Q0168
A173: 6 | B173: Financial Operations | C173: 6.3 | D173: Banking | E173: Integrations & Pain Points | F173: P2 | G173: What is the integration between your banking portal(s) and your property management system — real-time, daily file feed, or manual? | I173: TBD — confirm with TownSq product team | M173: =IF($J173="AC",COUNTIF($J$5:$J173,"AC"),"") | N173: =IF($J173="FB",COUNTIF($J$5:$J173,"FB"),"") | O173: =IF($J173="PC",COUNTIF($J$5:$J173,"PC"),"") | P173: 6.3.19 | Q173: Q0169
A174: 6 | B174: Financial Operations | C174: 6.3 | D174: Banking | E174: Integrations & Pain Points | F174: P2 | G174: Are there associations where banking is still managed outside your core platform — e.g., separate online banking portals with no system integration? | I174: RC - Yes. Some associations still manage banking outside of the core platform. If an association uses a bank that is not integrated, users must log in to that bank’s separate online portal with no system-to-system connection. Currently, integrations exist with Alliance, Columbia, FCB, Banc of California, and Sunwest. For all other banks, activity must be managed outside of C3 | O174: =IF($J174="PC",COUNTIF($J$5:$J174,"PC"),"") | P174: 6.3.20 | Q174: Q0170
A175: 6 | B175: Financial Operations | C175: 6.3 | D175: Banking | E175: Integrations & Pain Points | F175: P2 | G175: What are the biggest pain points in your bank reconciliation or cash management process today? | I175: RC - Automated bank reconciliation is still in development. The intended functionality will match system transactions to bank statement records, but it is not fully available yet. Additionally, the ability to manually upload bank statements is being built, but currently only certain banks are supported and additional development is still required, which indicates incomplete coverage and functionality. | O175: =IF($J175="PC",COUNTIF($J$5:$J175,"PC"),"") | P175: 6.3.21 | Q175: Q0171
A176: 6 | B176: Financial Operations | C176: 6.4 | D176: General Ledger / Financial Ops | E176: Chart of accounts structure | F176: P0 | G176: Is your branch using a standard chart of accounts across all associations, or does each association have its own customized COA? | I176: Associa uses a standardized chart of accounts across associations. During onboarding, all incoming branches and associations are mapped to this common COA structure as part of the implementation process. While legacy systems may have variations, the expectation is to normalize everything to the standard COA to ensure consistency in reporting and financial operations. | O176: =IF($J176="PC",COUNTIF($J$5:$J176,"PC"),"") | P176: 6.4.1 | Q176: Q0172
A177: 6 | B177: Financial Operations | C177: 6.4 | D177: General Ledger / Financial Ops | E177: Accounting method | F177: P0 | G177: Which accounting method do you currently use — Cash, Modified Cash, Modified Accrual, or Full Accrual? Does this vary by association? | I177: The standard accounting method used by Associa is modified accrual. While the system supports other methods such as cash or modified cash, these are not recommended and are used only in limited cases. In most scenarios, new associations are onboarded directly into modified accrual to avoid the complexity of converting accounting methods later. | O177: =IF($J177="PC",COUNTIF($J$5:$J177,"PC"),"") | P177: 6.4.2 | Q177: Q0173
A178: 6 | B178: Financial Operations | C178: 6.4 | D178: General Ledger / Financial Ops | E178: Recurring journal entries | F178: P0 | G178: Does your branch use recurring journal entries? If yes, give examples — prepaid insurance, management fee accruals, etc. | I178: Recurring journal entries are a standard practice across associations and are widely used. Common examples include prepaid insurance amortization, management fee accrals, and other routine accounting postings. These entries are typically configured to run automatically on a schedule, making this a standard and expected capability in financial operations | O178: =IF($J178="PC",COUNTIF($J$5:$J178,"PC"),"") | P178: 6.4.3 | Q178: Q0174
A179: 6 | B179: Financial Operations | C179: 6.4 | D179: General Ledger / Financial Ops | E179: Monthly financial package | F179: P0 | G179: How do you generate monthly financials — one report at a time or as a full package? What reports are included in the standard package? | I179: Monthly financials are generated as a standardized reporting package that typically includes the balance sheet, income statement, accounts receivable aging, accounts payable aging, and bank reconciliation reports. While the base package structure is standardized, associations can customize the contents or formats of specific reports, such as delinquency or income statement layouts, based on board preferences. | O179: =IF($J179="PC",COUNTIF($J$5:$J179,"PC"),"") | P179: 6.4.4 | Q179: Q0175
A180: 6 | B180: Financial Operations | C180: 6.4 | D180: General Ledger / Financial Ops | E180: Year-end close process | F180: P1 | G180: How do you complete year-end processing? What are the key steps, who is involved, and what is the typical timeline? | I180: After config — Year-end close process supported in TownSq. Retained earnings roll, period close, and next-year opening all within the system. Policy guidance available on Associa intranet. ~ | O180: =IF($J180="PC",COUNTIF($J$5:$J180,"PC"),"") | P180: 6.4.5 | Q180: Q0176
A181: 6 | B181: Financial Operations | C181: 6.4 | D181: General Ledger / Financial Ops | E181: Audit journal entries | F181: P1 | G181: What is your process for posting audit entries — do you post to the current year or reopen the prior year? Who approves audit JEs? | I181: Partial — Audit journal entries can be posted in TownSq. Prior-year reopening is supported but requires admin unlock; policy governs whether current-year or prior-year entry is used. ~ confirm Associa policy | O181: =IF($J181="PC",COUNTIF($J$5:$J181,"PC"),"") | P181: 6.4.6 | Q181: Q0177
A182: 6 | B182: Financial Operations | C182: 6.4 | D182: General Ledger / Financial Ops | E182: Reserve balance tracking in GL | F182: P1 | G182: How are reserve fund balances represented in the GL? Are they tracked in a separate reserve fund or within the operating GL? | I182: After config — Reserve fund balances tracked through dedicated reserve GL accounts. Separate fund reporting available. ✓ | O182: =IF($J182="PC",COUNTIF($J$5:$J182,"PC"),"") | P182: 6.4.7 | Q182: Q0178
A183: 6 | B183: Financial Operations | C183: 6.4 | D183: General Ledger / Financial Ops | E183: Month-end close checklist enforcement | F183: P1 | G183: Is there a formal month-end close checklist with mandatory steps before a period is locked? Who enforces it, and what happens if a step is missed or skipped? | I183: TBD — confirm with domain SME | M183: =IF($J183="AC",COUNTIF($J$5:$J183,"AC"),"") | N183: =IF($J183="FB",COUNTIF($J$5:$J183,"FB"),"") | O183: =IF($J183="PC",COUNTIF($J$5:$J183,"PC"),"") | P183: 6.4.8 | Q183: Q0179
A184: 6 | B184: Financial Operations | C184: 6.4 | D184: General Ledger / Financial Ops | E184: Accrual reversals | F184: P2 | G184: When accruals are posted at month-end (e.g., accrued interest, prepaid insurance amortization), are the reversals automated in the following period or manually entered? | I184: TBD — confirm with domain SME | M184: =IF($J184="AC",COUNTIF($J$5:$J184,"AC"),"") | N184: =IF($J184="FB",COUNTIF($J$5:$J184,"FB"),"") | O184: =IF($J184="PC",COUNTIF($J$5:$J184,"PC"),"") | P184: 6.4.9 | Q184: Q0180
A185: 6 | B185: Financial Operations | C185: 6.4 | D185: General Ledger / Financial Ops | E185: Core GL Systems & Platforms | F185: P0 | G185: What role does the Corporate Accounting department perform in GL ownership vs. branch-level accounting teams? | I185: Corporate GL and Client GL are clearly seperate. Corporate accounting and client (association) accounting operate on completely separate general ledgers, with no direct technical dependency or enforcement between them. Corporate accounting is managed within an ERP system (Dynamics 365 at Associa), while association-level accounting is handled within the property management accounting platform. There is no system-driven requirement for branches to follow corporate GL structures; instead, standardization is achieved through best practices and operational governance. As clarified during the discussion, this separation exists because corporate financials represent the management company, whereas association financials represent individual communities, making them fundamentally different accounting domains. [FinOps Rub...Continued | Word] | O185: =IF($J185="PC",COUNTIF($J$5:$J185,"PC"),"") | P185: 6.4.10 | Q185: Q0181
A186: 6 | B186: Financial Operations | C186: 6.4 | D186: General Ledger / Financial Ops | E186: ↳ Core GL Systems & Platforms | F186: P0 | G186: What is the primary system of record for the General Ledger — is it your property management platform (e.g., Jenark, Caliber, TOPS, Vantaca), a standalone ERP (e.g., Sage Intacct, NetSuite), or a combination? | I186: The system of record is split between corporate and client accounting. Corporate accounting is maintained in an ERP system (Dynamics 365), while association-level general ledgers reside within the property management accounting platform. This dual-system setup is intentional, as corporate accounting requirements differ significantly from HOA/client accounting. During the discussion, it was highlighted that this distinction becomes important in migration scenarios, as the corporate book of record must be aligned with ERP standards before client accounting transitions can be effectively executed. | O186: =IF($J186="PC",COUNTIF($J$5:$J186,"PC"),"") | P186: 6.4.11 | Q186: Q0182
A187: 6 | B187: Financial Operations | C187: 6.4 | D187: General Ledger / Financial Ops | E187: ↳ Core GL Systems & Platforms | F187: P0 | G187: Is the GL maintained within a single platform across all associations and portfolios, or are there multiple systems in use due to acquisitions, regional differences, or legacy contracts? | I187: General ledger systems vary across organizations, with some using standalone ERP systems (such as Sage or Dynamics) and others embedding corporate accounting within property management platforms. Migration is significantly easier when the source organization already uses an ERP system, as the transition aligns with Associa’s corporate accounting model. However, when corporate accounting is embedded within a property management system, migration becomes more complex because the corporate books must first be separated and rebuilt within an ERP structure, along with re-establishing integrations such as invoicing and revenue flows. This distinction is a critical driver of implementation complexity. | O187: =IF($J187="PC",COUNTIF($J$5:$J187,"PC"),"") | P187: 6.4.12 | Q187: Q0183
A188: 6 | B188: Financial Operations | C188: 6.4 | D188: General Ledger / Financial Ops | E188: ↳ Chart of Accounts Structure & Governance | F188: P0 | G188: Who holds responsibility for maintaining changes or edits to the chart of accounts — is there a central owner or is it managed branch by branch? | I188: General ledger governance is centralized to ensure consistency and prevent uncontrolled expansion. In shared service center models, branches have limited authority to modify GL structures and must submit requests for changes such as renaming accounts or introducing new configurations. Even in decentralized branch models, best practice is to restrict GL changes to a small group of knowledgeable users to maintain control. The level of control depends on the operating model—shared service centers enforce stricter governance, while independent branches maintain some flexibility but are still expected to follow standardized practices to avoid “GL sprawl.” | O188: =IF($J188="PC",COUNTIF($J$5:$J188,"PC"),"") | P188: 6.4.13 | Q188: Q0184
A189: 6 | B189: Financial Operations | C189: 6.4 | D189: General Ledger / Financial Ops | E189: ↳ Chart of Accounts Structure & Governance | F189: P0 | G189: Do you utilize sub-accounts within any of your charts of accounts? If so, what is the typical structure and how many levels deep? | I189: Sub-accounts are generally discouraged and are not part of the standard chart of accounts structure. Instead, segmentation is achieved using alternative constructs such as departments and projects, which allow for reporting across dimensions like buildings, funds, or operational areas. If a branch relies heavily on sub-accounts, it is treated as a complexity indicator during migration, requiring additional effort to map those structures into the preferred departmental model. The presence of deep sub-account hierarchies often signals more complex accounting requirements and necessitates careful analysis during onboarding. | M189: =IF($J189="AC",COUNTIF($J$5:$J189,"AC"),"") | N189: =IF($J189="FB",COUNTIF($J$5:$J189,"FB"),"") | O189: =IF($J189="PC",COUNTIF($J$5:$J189,"PC"),"") | P189: 6.4.14 | Q189: Q0185
A190: 6 | B190: Financial Operations | C190: 6.4 | D190: General Ledger / Financial Ops | E190: ↳ Chart of Accounts Structure & Governance | F190: P0 | G190: How are new GL accounts requested, approved, and activated? Is there a formal change control process or is it ad hoc? | I190: There is a formal governance process for requesting new GL accounts. When a branch requests a new account, subject matter experts review the request to determine whether an existing account within the standard COA can fulfill the need. Given the large superset of approximately 2,000 accounts, most requirements can be met without creating new accounts. Only when no suitable match exists is a new account introduced. This process ensures consistency, avoids duplication, and reinforces disciplined management of the chart of accounts. | O190: =IF($J190="PC",COUNTIF($J$5:$J190,"PC"),"") | P190: 6.4.15 | Q190: Q0186
A191: 6 | B191: Financial Operations | C191: 6.4 | D191: General Ledger / Financial Ops | E191: ↳ Chart of Accounts Structure & Governance | F191: P0 | G191: How is the CoA structured to support fund accounting — operating fund, reserve fund, special assessment fund — at the association level? | I191: Fund accounting is implemented through a departmental structure rather than sub-accounts. By default, every association is configured with at least two funds: an operating fund and a reserve fund. Additional funds can be created for specific purposes such as special assessments or project-based tracking. These departments enable clear financial segmentation and reporting without increasing GL complexity. The discussion also clarified that multiple reserve or project-specific funds can exist within an association, with each tracked separately for inflows and outflows. Follow-Up Question: How are inter-fund transfers handled and controlled? Answer: Inter-fund transfers typically involve moving cash between bank accounts, such as transferring funds from operating to reserve accounts. These are recorded in the general ledger through journal entries and executed through banking transactions. However, they are not purely manual; they are governed by approval workflows within the accounts payable system. Transfers above defined thresholds require approval (for example, from a branch manager), after which the transaction is executed, often via ACH. This ensures appropriate financial control and auditability of fund movements | O191: =IF($J191="PC",COUNTIF($J$5:$J191,"PC"),"") | P191: 6.4.16 | Q191: Q0187
A192: 6 | B192: Financial Operations | C192: 6.4 | D192: General Ledger / Financial Ops | E192: ↳ Chart of Accounts Structure & Governance | F192: P0 | G192: Is there a corporate-level standardized CoA template that all associations are expected to map to? How is compliance with that standard enforced? | I192: Yes, Associa maintains a corporate-level standardized chart of accounts that all associations are expected to map to during onboarding. This standard consists of a comprehensive superset of approximately 2,000 predefined GL accounts, designed to cover all potential use cases across associations. Rather than allowing branches to create independent COA structures, the onboarding process requires mapping legacy accounts to this standardized template, ensuring consistency across the portfolio. [FinOps Rub...Continued | Word] Compliance with this standard is enforced primarily through the implementation and governance process rather than strict system-level constraints. During onboarding, the implementation team performs detailed mapping from the branch’s legacy COA to the standard Associa COA, and new accounts are only introduced after expert review confirms that no existing account can serve the purpose. Additionally, governance controls—especially in shared service center models—limit the ability of branches to independently modify the COA, requiring centralized approval for changes. [FinOps Rub...Continued | Word] Follow-up discussion further clarified that while there is some limited flexibility (such as renaming account labels or activating/deactivating accounts), the underlying GL codes and structure remain fixed, reinforcing compliance with the standard. Deviations from this model (as seen in prior cases like Castle) have led to operational challenges, which is why current and future onboarding efforts emphasize strict adherence to the standardized COA. | O192: =IF($J192="PC",COUNTIF($J$5:$J192,"PC"),"") | P192: 6.4.17 | Q192: Q0188
A193: 6 | B193: Financial Operations | C193: 6.4 | D193: General Ledger / Financial Ops | E193: ↳ Month-End & Period Close | F193: P0 | G193: What is the designated day of the month by which financials are due? | I193: Financial close timing is fully configurable and varies across associations. Rather than enforcing a single close date, workloads are distributed across the month to balance operational capacity, especially given the scale of thousands of associations. Financial statement preparation is staggered across a range (typically from early to mid-month), although some associations may have priority deadlines based on contractual agreements. This staggered approach is essential to operational scalability and avoids bottlenecks in the closing process. | O193: =IF($J193="PC",COUNTIF($J$5:$J193,"PC"),"") | P193: 6.4.18 | Q193: Q0189
A194: 6 | B194: Financial Operations | C194: 6.4 | D194: General Ledger / Financial Ops | E194: ↳ Month-End & Period Close | F194: P0 | G194: Are there any associations with fiscal year ends that deviate from the standard calendar year-end (non-December)? How many? | I194: There is no mandated fiscal year across associations. While a majority of associations follow a calendar year for simplicity, others use different fiscal year cycles based on their formation or operational needs. Supporting varied fiscal years does not fundamentally change accounting processes but introduces additional complexity in reporting timelines and workload distribution. The system fully supports this variability, but it is treated as a complexity factor during operations and implementation. | M194: =IF($J194="AC",COUNTIF($J$5:$J194,"AC"),"") | N194: =IF($J194="FB",COUNTIF($J$5:$J194,"FB"),"") | O194: =IF($J194="PC",COUNTIF($J$5:$J194,"PC"),"") | P194: 6.4.19 | Q194: Q0190
A195: 6 | B195: Financial Operations | C195: 6.4 | D195: General Ledger / Financial Ops | E195: Financial Reporting | F195: P1 | G195: How is consolidated financial reporting handled across multiple associations — can the GL produce roll-up reports, or is that done in Excel? | I195: RC: The GL provides built-in consolidated reports (balance sheet, income statement, GL, AP). Users group communities and generate roll-ups directly in the system; Excel is not required. [Ronald Chu...iority Q&A | Word] | O195: =IF($J195="PC",COUNTIF($J$5:$J195,"PC"),"") | P195: 6.4.20 | Q195: Q0191
A196: 6 | B196: Financial Operations | C196: 6.4 | D196: General Ledger / Financial Ops | E196: Financial Reporting | F196: P1 | G196: Are there any special or custom reports offered to clients outside the standard package? | I196: RC: A report package builder allows combining standard reports. User-defined reports are available but export raw data to Excel for further manipulation | O196: =IF($J196="PC",COUNTIF($J$5:$J196,"PC"),"") | P196: 6.4.21 | Q196: Q0192
...

Sheet Change Plan (PC)
A1: CHANGE PLAN (PC)
A3: Process Change items — TownSq supports these natively but the branch currently works differently. Column 'TownSq supports today' shows exactly what TownSq does. Fill in the required workflow change, assign an Owner, and set a Target Date.
A4: Row# | B4: Domain | C4: Capability | D4: Dimension | E4: Discovery Question | F4: Branch Answer | G4: TownSq supports today | H4: Required change in TownSq | I4: Owner | J4: Target Date
A5: =IFERROR(MATCH(1,Assessment!$O:$O,0),"") | B5: =IF($A5="","",INDEX(Assessment!$B:$B,$A5)) | C5: =IF($A5="","",INDEX(Assessment!$D:$D,$A5)) | D5: =IF($A5="","",INDEX(Assessment!$E:$E,$A5)) | E5: =IF($A5="","",INDEX(Assessment!$G:$G,$A5)) | F5: =IF($A5="","",INDEX(Assessment!$H:$H,$A5)) | G5: =IF($A5="","",INDEX(Assessment!$I:$I,$A5))
A6: =IFERROR(MATCH(2,Assessment!$O:$O,0),"") | B6: =IF($A6="","",INDEX(Assessment!$B:$B,$A6)) | C6: =IF($A6="","",INDEX(Assessment!$D:$D,$A6)) | D6: =IF($A6="","",INDEX(Assessment!$E:$E,$A6)) | E6: =IF($A6="","",INDEX(Assessment!$G:$G,$A6)) | F6: =IF($A6="","",INDEX(Assessment!$H:$H,$A6)) | G6: =IF($A6="","",INDEX(Assessment!$I:$I,$A6))
A7: =IFERROR(MATCH(3,Assessment!$O:$O,0),"") | B7: =IF($A7="","",INDEX(Assessment!$B:$B,$A7)) | C7: =IF($A7="","",INDEX(Assessment!$D:$D,$A7)) | D7: =IF($A7="","",INDEX(Assessment!$E:$E,$A7)) | E7: =IF($A7="","",INDEX(Assessment!$G:$G,$A7)) | F7: =IF($A7="","",INDEX(Assessment!$H:$H,$A7)) | G7: =IF($A7="","",INDEX(Assessment!$I:$I,$A7))
A8: =IFERROR(MATCH(4,Assessment!$O:$O,0),"") | B8: =IF($A8="","",INDEX(Assessment!$B:$B,$A8)) | C8: =IF($A8="","",INDEX(Assessment!$D:$D,$A8)) | D8: =IF($A8="","",INDEX(Assessment!$E:$E,$A8)) | E8: =IF($A8="","",INDEX(Assessment!$G:$G,$A8)) | F8: =IF($A8="","",INDEX(Assessment!$H:$H,$A8)) | G8: =IF($A8="","",INDEX(Assessment!$I:$I,$A8))
A9: =IFERROR(MATCH(5,Assessment!$O:$O,0),"") | B9: =IF($A9="","",INDEX(Assessment!$B:$B,$A9)) | C9: =IF($A9="","",INDEX(Assessment!$D:$D,$A9)) | D9: =IF($A9="","",INDEX(Assessment!$E:$E,$A9)) | E9: =IF($A9="","",INDEX(Assessment!$G:$G,$A9)) | F9: =IF($A9="","",INDEX(Assessment!$H:$H,$A9)) | G9: =IF($A9="","",INDEX(Assessment!$I:$I,$A9))
A10: =IFERROR(MATCH(6,Assessment!$O:$O,0),"") | B10: =IF($A10="","",INDEX(Assessment!$B:$B,$A10)) | C10: =IF($A10="","",INDEX(Assessment!$D:$D,$A10)) | D10: =IF($A10="","",INDEX(Assessment!$E:$E,$A10)) | E10: =IF($A10="","",INDEX(Assessment!$G:$G,$A10)) | F10: =IF($A10="","",INDEX(Assessment!$H:$H,$A10)) | G10: =IF($A10="","",INDEX(Assessment!$I:$I,$A10))
A11: =IFERROR(MATCH(7,Assessment!$O:$O,0),"") | B11: =IF($A11="","",INDEX(Assessment!$B:$B,$A11)) | C11: =IF($A11="","",INDEX(Assessment!$D:$D,$A11)) | D11: =IF($A11="","",INDEX(Assessment!$E:$E,$A11)) | E11: =IF($A11="","",INDEX(Assessment!$G:$G,$A11)) | F11: =IF($A11="","",INDEX(Assessment!$H:$H,$A11)) | G11: =IF($A11="","",INDEX(Assessment!$I:$I,$A11))
A12: =IFERROR(MATCH(8,Assessment!$O:$O,0),"") | B12: =IF($A12="","",INDEX(Assessment!$B:$B,$A12)) | C12: =IF($A12="","",INDEX(Assessment!$D:$D,$A12)) | D12: =IF($A12="","",INDEX(Assessment!$E:$E,$A12)) | E12: =IF($A12="","",INDEX(Assessment!$G:$G,$A12)) | F12: =IF($A12="","",INDEX(Assessment!$H:$H,$A12)) | G12: =IF($A12="","",INDEX(Assessment!$I:$I,$A12))
A13: =IFERROR(MATCH(9,Assessment!$O:$O,0),"") | B13: =IF($A13="","",INDEX(Assessment!$B:$B,$A13)) | C13: =IF($A13="","",INDEX(Assessment!$D:$D,$A13)) | D13: =IF($A13="","",INDEX(Assessment!$E:$E,$A13)) | E13: =IF($A13="","",INDEX(Assessment!$G:$G,$A13)) | F13: =IF($A13="","",INDEX(Assessment!$H:$H,$A13)) | G13: =IF($A13="","",INDEX(Assessment!$I:$I,$A13))
A14: =IFERROR(MATCH(10,Assessment!$O:$O,0),"") | B14: =IF($A14="","",INDEX(Assessment!$B:$B,$A14)) | C14: =IF($A14="","",INDEX(Assessment!$D:$D,$A14)) | D14: =IF($A14="","",INDEX(Assessment!$E:$E,$A14)) | E14: =IF($A14="","",INDEX(Assessment!$G:$G,$A14)) | F14: =IF($A14="","",INDEX(Assessment!$H:$H,$A14)) | G14: =IF($A14="","",INDEX(Assessment!$I:$I,$A14))
A15: =IFERROR(MATCH(11,Assessment!$O:$O,0),"") | B15: =IF($A15="","",INDEX(Assessment!$B:$B,$A15)) | C15: =IF($A15="","",INDEX(Assessment!$D:$D,$A15)) | D15: =IF($A15="","",INDEX(Assessment!$E:$E,$A15)) | E15: =IF($A15="","",INDEX(Assessment!$G:$G,$A15)) | F15: =IF($A15="","",INDEX(Assessment!$H:$H,$A15)) | G15: =IF($A15="","",INDEX(Assessment!$I:$I,$A15))
A16: =IFERROR(MATCH(12,Assessment!$O:$O,0),"") | B16: =IF($A16="","",INDEX(Assessment!$B:$B,$A16)) | C16: =IF($A16="","",INDEX(Assessment!$D:$D,$A16)) | D16: =IF($A16="","",INDEX(Assessment!$E:$E,$A16)) | E16: =IF($A16="","",INDEX(Assessment!$G:$G,$A16)) | F16: =IF($A16="","",INDEX(Assessment!$H:$H,$A16)) | G16: =IF($A16="","",INDEX(Assessment!$I:$I,$A16))
A17: =IFERROR(MATCH(13,Assessment!$O:$O,0),"") | B17: =IF($A17="","",INDEX(Assessment!$B:$B,$A17)) | C17: =IF($A17="","",INDEX(Assessment!$D:$D,$A17)) | D17: =IF($A17="","",INDEX(Assessment!$E:$E,$A17)) | E17: =IF($A17="","",INDEX(Assessment!$G:$G,$A17)) | F17: =IF($A17="","",INDEX(Assessment!$H:$H,$A17)) | G17: =IF($A17="","",INDEX(Assessment!$I:$I,$A17))
A18: =IFERROR(MATCH(14,Assessment!$O:$O,0),"") | B18: =IF($A18="","",INDEX(Assessment!$B:$B,$A18)) | C18: =IF($A18="","",INDEX(Assessment!$D:$D,$A18)) | D18: =IF($A18="","",INDEX(Assessment!$E:$E,$A18)) | E18: =IF($A18="","",INDEX(Assessment!$G:$G,$A18)) | F18: =IF($A18="","",INDEX(Assessment!$H:$H,$A18)) | G18: =IF($A18="","",INDEX(Assessment!$I:$I,$A18))
A19: =IFERROR(MATCH(15,Assessment!$O:$O,0),"") | B19: =IF($A19="","",INDEX(Assessment!$B:$B,$A19)) | C19: =IF($A19="","",INDEX(Assessment!$D:$D,$A19)) | D19: =IF($A19="","",INDEX(Assessment!$E:$E,$A19)) | E19: =IF($A19="","",INDEX(Assessment!$G:$G,$A19)) | F19: =IF($A19="","",INDEX(Assessment!$H:$H,$A19)) | G19: =IF($A19="","",INDEX(Assessment!$I:$I,$A19))
A20: =IFERROR(MATCH(16,Assessment!$O:$O,0),"") | B20: =IF($A20="","",INDEX(Assessment!$B:$B,$A20)) | C20: =IF($A20="","",INDEX(Assessment!$D:$D,$A20)) | D20: =IF($A20="","",INDEX(Assessment!$E:$E,$A20)) | E20: =IF($A20="","",INDEX(Assessment!$G:$G,$A20)) | F20: =IF($A20="","",INDEX(Assessment!$H:$H,$A20)) | G20: =IF($A20="","",INDEX(Assessment!$I:$I,$A20))
A21: =IFERROR(MATCH(17,Assessment!$O:$O,0),"") | B21: =IF($A21="","",INDEX(Assessment!$B:$B,$A21)) | C21: =IF($A21="","",INDEX(Assessment!$D:$D,$A21)) | D21: =IF($A21="","",INDEX(Assessment!$E:$E,$A21)) | E21: =IF($A21="","",INDEX(Assessment!$G:$G,$A21)) | F21: =IF($A21="","",INDEX(Assessment!$H:$H,$A21)) | G21: =IF($A21="","",INDEX(Assessment!$I:$I,$A21))
A22: =IFERROR(MATCH(18,Assessment!$O:$O,0),"") | B22: =IF($A22="","",INDEX(Assessment!$B:$B,$A22)) | C22: =IF($A22="","",INDEX(Assessment!$D:$D,$A22)) | D22: =IF($A22="","",INDEX(Assessment!$E:$E,$A22)) | E22: =IF($A22="","",INDEX(Assessment!$G:$G,$A22)) | F22: =IF($A22="","",INDEX(Assessment!$H:$H,$A22)) | G22: =IF($A22="","",INDEX(Assessment!$I:$I,$A22))
A23: =IFERROR(MATCH(19,Assessment!$O:$O,0),"") | B23: =IF($A23="","",INDEX(Assessment!$B:$B,$A23)) | C23: =IF($A23="","",INDEX(Assessment!$D:$D,$A23)) | D23: =IF($A23="","",INDEX(Assessment!$E:$E,$A23)) | E23: =IF($A23="","",INDEX(Assessment!$G:$G,$A23)) | F23: =IF($A23="","",INDEX(Assessment!$H:$H,$A23)) | G23: =IF($A23="","",INDEX(Assessment!$I:$I,$A23))
A24: =IFERROR(MATCH(20,Assessment!$O:$O,0),"") | B24: =IF($A24="","",INDEX(Assessment!$B:$B,$A24)) | C24: =IF($A24="","",INDEX(Assessment!$D:$D,$A24)) | D24: =IF($A24="","",INDEX(Assessment!$E:$E,$A24)) | E24: =IF($A24="","",INDEX(Assessment!$G:$G,$A24)) | F24: =IF($A24="","",INDEX(Assessment!$H:$H,$A24)) | G24: =IF($A24="","",INDEX(Assessment!$I:$I,$A24))
A25: =IFERROR(MATCH(21,Assessment!$O:$O,0),"") | B25: =IF($A25="","",INDEX(Assessment!$B:$B,$A25)) | C25: =IF($A25="","",INDEX(Assessment!$D:$D,$A25)) | D25: =IF($A25="","",INDEX(Assessment!$E:$E,$A25)) | E25: =IF($A25="","",INDEX(Assessment!$G:$G,$A25)) | F25: =IF($A25="","",INDEX(Assessment!$H:$H,$A25)) | G25: =IF($A25="","",INDEX(Assessment!$I:$I,$A25))
A26: =IFERROR(MATCH(22,Assessment!$O:$O,0),"") | B26: =IF($A26="","",INDEX(Assessment!$B:$B,$A26)) | C26: =IF($A26="","",INDEX(Assessment!$D:$D,$A26)) | D26: =IF($A26="","",INDEX(Assessment!$E:$E,$A26)) | E26: =IF($A26="","",INDEX(Assessment!$G:$G,$A26)) | F26: =IF($A26="","",INDEX(Assessment!$H:$H,$A26)) | G26: =IF($A26="","",INDEX(Assessment!$I:$I,$A26))
A27: =IFERROR(MATCH(23,Assessment!$O:$O,0),"") | B27: =IF($A27="","",INDEX(Assessment!$B:$B,$A27)) | C27: =IF($A27="","",INDEX(Assessment!$D:$D,$A27)) | D27: =IF($A27="","",INDEX(Assessment!$E:$E,$A27)) | E27: =IF($A27="","",INDEX(Assessment!$G:$G,$A27)) | F27: =IF($A27="","",INDEX(Assessment!$H:$H,$A27)) | G27: =IF($A27="","",INDEX(Assessment!$I:$I,$A27))
A28: =IFERROR(MATCH(24,Assessment!$O:$O,0),"") | B28: =IF($A28="","",INDEX(Assessment!$B:$B,$A28)) | C28: =IF($A28="","",INDEX(Assessment!$D:$D,$A28)) | D28: =IF($A28="","",INDEX(Assessment!$E:$E,$A28)) | E28: =IF($A28="","",INDEX(Assessment!$G:$G,$A28)) | F28: =IF($A28="","",INDEX(Assessment!$H:$H,$A28)) | G28: =IF($A28="","",INDEX(Assessment!$I:$I,$A28))
A29: =IFERROR(MATCH(25,Assessment!$O:$O,0),"") | B29: =IF($A29="","",INDEX(Assessment!$B:$B,$A29)) | C29: =IF($A29="","",INDEX(Assessment!$D:$D,$A29)) | D29: =IF($A29="","",INDEX(Assessment!$E:$E,$A29)) | E29: =IF($A29="","",INDEX(Assessment!$G:$G,$A29)) | F29: =IF($A29="","",INDEX(Assessment!$H:$H,$A29)) | G29: =IF($A29="","",INDEX(Assessment!$I:$I,$A29))
A30: =IFERROR(MATCH(26,Assessment!$O:$O,0),"") | B30: =IF($A30="","",INDEX(Assessment!$B:$B,$A30)) | C30: =IF($A30="","",INDEX(Assessment!$D:$D,$A30)) | D30: =IF($A30="","",INDEX(Assessment!$E:$E,$A30)) | E30: =IF($A30="","",INDEX(Assessment!$G:$G,$A30)) | F30: =IF($A30="","",INDEX(Assessment!$H:$H,$A30)) | G30: =IF($A30="","",INDEX(Assessment!$I:$I,$A30))
A31: =IFERROR(MATCH(27,Assessment!$O:$O,0),"") | B31: =IF($A31="","",INDEX(Assessment!$B:$B,$A31)) | C31: =IF($A31="","",INDEX(Assessment!$D:$D,$A31)) | D31: =IF($A31="","",INDEX(Assessment!$E:$E,$A31)) | E31: =IF($A31="","",INDEX(Assessment!$G:$G,$A31)) | F31: =IF($A31="","",INDEX(Assessment!$H:$H,$A31)) | G31: =IF($A31="","",INDEX(Assessment!$I:$I,$A31))
A32: =IFERROR(MATCH(28,Assessment!$O:$O,0),"") | B32: =IF($A32="","",INDEX(Assessment!$B:$B,$A32)) | C32: =IF($A32="","",INDEX(Assessment!$D:$D,$A32)) | D32: =IF($A32="","",INDEX(Assessment!$E:$E,$A32)) | E32: =IF($A32="","",INDEX(Assessment!$G:$G,$A32)) | F32: =IF($A32="","",INDEX(Assessment!$H:$H,$A32)) | G32: =IF($A32="","",INDEX(Assessment!$I:$I,$A32))
A33: =IFERROR(MATCH(29,Assessment!$O:$O,0),"") | B33: =IF($A33="","",INDEX(Assessment!$B:$B,$A33)) | C33: =IF($A33="","",INDEX(Assessment!$D:$D,$A33)) | D33: =IF($A33="","",INDEX(Assessment!$E:$E,$A33)) | E33: =IF($A33="","",INDEX(Assessment!$G:$G,$A33)) | F33: =IF($A33="","",INDEX(Assessment!$H:$H,$A33)) | G33: =IF($A33="","",INDEX(Assessment!$I:$I,$A33))
A34: =IFERROR(MATCH(30,Assessment!$O:$O,0),"") | B34: =IF($A34="","",INDEX(Assessment!$B:$B,$A34)) | C34: =IF($A34="","",INDEX(Assessment!$D:$D,$A34)) | D34: =IF($A34="","",INDEX(Assessment!$E:$E,$A34)) | E34: =IF($A34="","",INDEX(Assessment!$G:$G,$A34)) | F34: =IF($A34="","",INDEX(Assessment!$H:$H,$A34)) | G34: =IF($A34="","",INDEX(Assessment!$I:$I,$A34))
A35: =IFERROR(MATCH(31,Assessment!$O:$O,0),"") | B35: =IF($A35="","",INDEX(Assessment!$B:$B,$A35)) | C35: =IF($A35="","",INDEX(Assessment!$D:$D,$A35)) | D35: =IF($A35="","",INDEX(Assessment!$E:$E,$A35)) | E35: =IF($A35="","",INDEX(Assessment!$G:$G,$A35)) | F35: =IF($A35="","",INDEX(Assessment!$H:$H,$A35)) | G35: =IF($A35="","",INDEX(Assessment!$I:$I,$A35))
A36: =IFERROR(MATCH(32,Assessment!$O:$O,0),"") | B36: =IF($A36="","",INDEX(Assessment!$B:$B,$A36)) | C36: =IF($A36="","",INDEX(Assessment!$D:$D,$A36)) | D36: =IF($A36="","",INDEX(Assessment!$E:$E,$A36)) | E36: =IF($A36="","",INDEX(Assessment!$G:$G,$A36)) | F36: =IF($A36="","",INDEX(Assessment!$H:$H,$A36)) | G36: =IF($A36="","",INDEX(Assessment!$I:$I,$A36))
A37: =IFERROR(MATCH(33,Assessment!$O:$O,0),"") | B37: =IF($A37="","",INDEX(Assessment!$B:$B,$A37)) | C37: =IF($A37="","",INDEX(Assessment!$D:$D,$A37)) | D37: =IF($A37="","",INDEX(Assessment!$E:$E,$A37)) | E37: =IF($A37="","",INDEX(Assessment!$G:$G,$A37)) | F37: =IF($A37="","",INDEX(Assessment!$H:$H,$A37)) | G37: =IF($A37="","",INDEX(Assessment!$I:$I,$A37))
A38: =IFERROR(MATCH(34,Assessment!$O:$O,0),"") | B38: =IF($A38="","",INDEX(Assessment!$B:$B,$A38)) | C38: =IF($A38="","",INDEX(Assessment!$D:$D,$A38)) | D38: =IF($A38="","",INDEX(Assessment!$E:$E,$A38)) | E38: =IF($A38="","",INDEX(Assessment!$G:$G,$A38)) | F38: =IF($A38="","",INDEX(Assessment!$H:$H,$A38)) | G38: =IF($A38="","",INDEX(Assessment!$I:$I,$A38))
A39: =IFERROR(MATCH(35,Assessment!$O:$O,0),"") | B39: =IF($A39="","",INDEX(Assessment!$B:$B,$A39)) | C39: =IF($A39="","",INDEX(Assessment!$D:$D,$A39)) | D39: =IF($A39="","",INDEX(Assessment!$E:$E,$A39)) | E39: =IF($A39="","",INDEX(Assessment!$G:$G,$A39)) | F39: =IF($A39="","",INDEX(Assessment!$H:$H,$A39)) | G39: =IF($A39="","",INDEX(Assessment!$I:$I,$A39))
A40: =IFERROR(MATCH(36,Assessment!$O:$O,0),"") | B40: =IF($A40="","",INDEX(Assessment!$B:$B,$A40)) | C40: =IF($A40="","",INDEX(Assessment!$D:$D,$A40)) | D40: =IF($A40="","",INDEX(Assessment!$E:$E,$A40)) | E40: =IF($A40="","",INDEX(Assessment!$G:$G,$A40)) | F40: =IF($A40="","",INDEX(Assessment!$H:$H,$A40)) | G40: =IF($A40="","",INDEX(Assessment!$I:$I,$A40))
A41: =IFERROR(MATCH(37,Assessment!$O:$O,0),"") | B41: =IF($A41="","",INDEX(Assessment!$B:$B,$A41)) | C41: =IF($A41="","",INDEX(Assessment!$D:$D,$A41)) | D41: =IF($A41="","",INDEX(Assessment!$E:$E,$A41)) | E41: =IF($A41="","",INDEX(Assessment!$G:$G,$A41)) | F41: =IF($A41="","",INDEX(Assessment!$H:$H,$A41)) | G41: =IF($A41="","",INDEX(Assessment!$I:$I,$A41))
A42: =IFERROR(MATCH(38,Assessment!$O:$O,0),"") | B42: =IF($A42="","",INDEX(Assessment!$B:$B,$A42)) | C42: =IF($A42="","",INDEX(Assessment!$D:$D,$A42)) | D42: =IF($A42="","",INDEX(Assessment!$E:$E,$A42)) | E42: =IF($A42="","",INDEX(Assessment!$G:$G,$A42)) | F42: =IF($A42="","",INDEX(Assessment!$H:$H,$A42)) | G42: =IF($A42="","",INDEX(Assessment!$I:$I,$A42))
A43: =IFERROR(MATCH(39,Assessment!$O:$O,0),"") | B43: =IF($A43="","",INDEX(Assessment!$B:$B,$A43)) | C43: =IF($A43="","",INDEX(Assessment!$D:$D,$A43)) | D43: =IF($A43="","",INDEX(Assessment!$E:$E,$A43)) | E43: =IF($A43="","",INDEX(Assessment!$G:$G,$A43)) | F43: =IF($A43="","",INDEX(Assessment!$H:$H,$A43)) | G43: =IF($A43="","",INDEX(Assessment!$I:$I,$A43))
A44: =IFERROR(MATCH(40,Assessment!$O:$O,0),"") | B44: =IF($A44="","",INDEX(Assessment!$B:$B,$A44)) | C44: =IF($A44="","",INDEX(Assessment!$D:$D,$A44)) | D44: =IF($A44="","",INDEX(Assessment!$E:$E,$A44)) | E44: =IF($A44="","",INDEX(Assessment!$G:$G,$A44)) | F44: =IF($A44="","",INDEX(Assessment!$H:$H,$A44)) | G44: =IF($A44="","",INDEX(Assessment!$I:$I,$A44))
A45: =IFERROR(MATCH(41,Assessment!$O:$O,0),"") | B45: =IF($A45="","",INDEX(Assessment!$B:$B,$A45)) | C45: =IF($A45="","",INDEX(Assessment!$D:$D,$A45)) | D45: =IF($A45="","",INDEX(Assessment!$E:$E,$A45)) | E45: =IF($A45="","",INDEX(Assessment!$G:$G,$A45)) | F45: =IF($A45="","",INDEX(Assessment!$H:$H,$A45)) | G45: =IF($A45="","",INDEX(Assessment!$I:$I,$A45))
A46: =IFERROR(MATCH(42,Assessment!$O:$O,0),"") | B46: =IF($A46="","",INDEX(Assessment!$B:$B,$A46)) | C46: =IF($A46="","",INDEX(Assessment!$D:$D,$A46)) | D46: =IF($A46="","",INDEX(Assessment!$E:$E,$A46)) | E46: =IF($A46="","",INDEX(Assessment!$G:$G,$A46)) | F46: =IF($A46="","",INDEX(Assessment!$H:$H,$A46)) | G46: =IF($A46="","",INDEX(Assessment!$I:$I,$A46))
A47: =IFERROR(MATCH(43,Assessment!$O:$O,0),"") | B47: =IF($A47="","",INDEX(Assessment!$B:$B,$A47)) | C47: =IF($A47="","",INDEX(Assessment!$D:$D,$A47)) | D47: =IF($A47="","",INDEX(Assessment!$E:$E,$A47)) | E47: =IF($A47="","",INDEX(Assessment!$G:$G,$A47)) | F47: =IF($A47="","",INDEX(Assessment!$H:$H,$A47)) | G47: =IF($A47="","",INDEX(Assessment!$I:$I,$A47))
A48: =IFERROR(MATCH(44,Assessment!$O:$O,0),"") | B48: =IF($A48="","",INDEX(Assessment!$B:$B,$A48)) | C48: =IF($A48="","",INDEX(Assessment!$D:$D,$A48)) | D48: =IF($A48="","",INDEX(Assessment!$E:$E,$A48)) | E48: =IF($A48="","",INDEX(Assessment!$G:$G,$A48)) | F48: =IF($A48="","",INDEX(Assessment!$H:$H,$A48)) | G48: =IF($A48="","",INDEX(Assessment!$I:$I,$A48))
A49: =IFERROR(MATCH(45,Assessment!$O:$O,0),"") | B49: =IF($A49="","",INDEX(Assessment!$B:$B,$A49)) | C49: =IF($A49="","",INDEX(Assessment!$D:$D,$A49)) | D49: =IF($A49="","",INDEX(Assessment!$E:$E,$A49)) | E49: =IF($A49="","",INDEX(Assessment!$G:$G,$A49)) | F49: =IF($A49="","",INDEX(Assessment!$H:$H,$A49)) | G49: =IF($A49="","",INDEX(Assessment!$I:$I,$A49))
A50: =IFERROR(MATCH(46,Assessment!$O:$O,0),"") | B50: =IF($A50="","",INDEX(Assessment!$B:$B,$A50)) | C50: =IF($A50="","",INDEX(Assessment!$D:$D,$A50)) | D50: =IF($A50="","",INDEX(Assessment!$E:$E,$A50)) | E50: =IF($A50="","",INDEX(Assessment!$G:$G,$A50)) | F50: =IF($A50="","",INDEX(Assessment!$H:$H,$A50)) | G50: =IF($A50="","",INDEX(Assessment!$I:$I,$A50))
A51: =IFERROR(MATCH(47,Assessment!$O:$O,0),"") | B51: =IF($A51="","",INDEX(Assessment!$B:$B,$A51)) | C51: =IF($A51="","",INDEX(Assessment!$D:$D,$A51)) | D51: =IF($A51="","",INDEX(Assessment!$E:$E,$A51)) | E51: =IF($A51="","",INDEX(Assessment!$G:$G,$A51)) | F51: =IF($A51="","",INDEX(Assessment!$H:$H,$A51)) | G51: =IF($A51="","",INDEX(Assessment!$I:$I,$A51))
A52: =IFERROR(MATCH(48,Assessment!$O:$O,0),"") | B52: =IF($A52="","",INDEX(Assessment!$B:$B,$A52)) | C52: =IF($A52="","",INDEX(Assessment!$D:$D,$A52)) | D52: =IF($A52="","",INDEX(Assessment!$E:$E,$A52)) | E52: =IF($A52="","",INDEX(Assessment!$G:$G,$A52)) | F52: =IF($A52="","",INDEX(Assessment!$H:$H,$A52)) | G52: =IF($A52="","",INDEX(Assessment!$I:$I,$A52))
A53: =IFERROR(MATCH(49,Assessment!$O:$O,0),"") | B53: =IF($A53="","",INDEX(Assessment!$B:$B,$A53)) | C53: =IF($A53="","",INDEX(Assessment!$D:$D,$A53)) | D53: =IF($A53="","",INDEX(Assessment!$E:$E,$A53)) | E53: =IF($A53="","",INDEX(Assessment!$G:$G,$A53)) | F53: =IF($A53="","",INDEX(Assessment!$H:$H,$A53)) | G53: =IF($A53="","",INDEX(Assessment!$I:$I,$A53))
A54: =IFERROR(MATCH(50,Assessment!$O:$O,0),"") | B54: =IF($A54="","",INDEX(Assessment!$B:$B,$A54)) | C54: =IF($A54="","",INDEX(Assessment!$D:$D,$A54)) | D54: =IF($A54="","",INDEX(Assessment!$E:$E,$A54)) | E54: =IF($A54="","",INDEX(Assessment!$G:$G,$A54)) | F54: =IF($A54="","",INDEX(Assessment!$H:$H,$A54)) | G54: =IF($A54="","",INDEX(Assessment!$I:$I,$A54))
A55: =IFERROR(MATCH(51,Assessment!$O:$O,0),"") | B55: =IF($A55="","",INDEX(Assessment!$B:$B,$A55)) | C55: =IF($A55="","",INDEX(Assessment!$D:$D,$A55)) | D55: =IF($A55="","",INDEX(Assessment!$E:$E,$A55)) | E55: =IF($A55="","",INDEX(Assessment!$G:$G,$A55)) | F55: =IF($A55="","",INDEX(Assessment!$H:$H,$A55)) | G55: =IF($A55="","",INDEX(Assessment!$I:$I,$A55))
A56: =IFERROR(MATCH(52,Assessment!$O:$O,0),"") | B56: =IF($A56="","",INDEX(Assessment!$B:$B,$A56)) | C56: =IF($A56="","",INDEX(Assessment!$D:$D,$A56)) | D56: =IF($A56="","",INDEX(Assessment!$E:$E,$A56)) | E56: =IF($A56="","",INDEX(Assessment!$G:$G,$A56)) | F56: =IF($A56="","",INDEX(Assessment!$H:$H,$A56)) | G56: =IF($A56="","",INDEX(Assessment!$I:$I,$A56))
A57: =IFERROR(MATCH(53,Assessment!$O:$O,0),"") | B57: =IF($A57="","",INDEX(Assessment!$B:$B,$A57)) | C57: =IF($A57="","",INDEX(Assessment!$D:$D,$A57)) | D57: =IF($A57="","",INDEX(Assessment!$E:$E,$A57)) | E57: =IF($A57="","",INDEX(Assessment!$G:$G,$A57)) | F57: =IF($A57="","",INDEX(Assessment!$H:$H,$A57)) | G57: =IF($A57="","",INDEX(Assessment!$I:$I,$A57))
A58: =IFERROR(MATCH(54,Assessment!$O:$O,0),"") | B58: =IF($A58="","",INDEX(Assessment!$B:$B,$A58)) | C58: =IF($A58="","",INDEX(Assessment!$D:$D,$A58)) | D58: =IF($A58="","",INDEX(Assessment!$E:$E,$A58)) | E58: =IF($A58="","",INDEX(Assessment!$G:$G,$A58)) | F58: =IF($A58="","",INDEX(Assessment!$H:$H,$A58)) | G58: =IF($A58="","",INDEX(Assessment!$I:$I,$A58))
A59: =IFERROR(MATCH(55,Assessment!$O:$O,0),"") | B59: =IF($A59="","",INDEX(Assessment!$B:$B,$A59)) | C59: =IF($A59="","",INDEX(Assessment!$D:$D,$A59)) | D59: =IF($A59="","",INDEX(Assessment!$E:$E,$A59)) | E59: =IF($A59="","",INDEX(Assessment!$G:$G,$A59)) | F59: =IF($A59="","",INDEX(Assessment!$H:$H,$A59)) | G59: =IF($A59="","",INDEX(Assessment!$I:$I,$A59))
A60: =IFERROR(MATCH(56,Assessment!$O:$O,0),"") | B60: =IF($A60="","",INDEX(Assessment!$B:$B,$A60)) | C60: =IF($A60="","",INDEX(Assessment!$D:$D,$A60)) | D60: =IF($A60="","",INDEX(Assessment!$E:$E,$A60)) | E60: =IF($A60="","",INDEX(Assessment!$G:$G,$A60)) | F60: =IF($A60="","",INDEX(Assessment!$H:$H,$A60)) | G60: =IF($A60="","",INDEX(Assessment!$I:$I,$A60))
A61: =IFERROR(MATCH(57,Assessment!$O:$O,0),"") | B61: =IF($A61="","",INDEX(Assessment!$B:$B,$A61)) | C61: =IF($A61="","",INDEX(Assessment!$D:$D,$A61)) | D61: =IF($A61="","",INDEX(Assessment!$E:$E,$A61)) | E61: =IF($A61="","",INDEX(Assessment!$G:$G,$A61)) | F61: =IF($A61="","",INDEX(Assessment!$H:$H,$A61)) | G61: =IF($A61="","",INDEX(Assessment!$I:$I,$A61))
A62: =IFERROR(MATCH(58,Assessment!$O:$O,0),"") | B62: =IF($A62="","",INDEX(Assessment!$B:$B,$A62)) | C62: =IF($A62="","",INDEX(Assessment!$D:$D,$A62)) | D62: =IF($A62="","",INDEX(Assessment!$E:$E,$A62)) | E62: =IF($A62="","",INDEX(Assessment!$G:$G,$A62)) | F62: =IF($A62="","",INDEX(Assessment!$H:$H,$A62)) | G62: =IF($A62="","",INDEX(Assessment!$I:$I,$A62))
A63: =IFERROR(MATCH(59,Assessment!$O:$O,0),"") | B63: =IF($A63="","",INDEX(Assessment!$B:$B,$A63)) | C63: =IF($A63="","",INDEX(Assessment!$D:$D,$A63)) | D63: =IF($A63="","",INDEX(Assessment!$E:$E,$A63)) | E63: =IF($A63="","",INDEX(Assessment!$G:$G,$A63)) | F63: =IF($A63="","",INDEX(Assessment!$H:$H,$A63)) | G63: =IF($A63="","",INDEX(Assessment!$I:$I,$A63))
A64: =IFERROR(MATCH(60,Assessment!$O:$O,0),"") | B64: =IF($A64="","",INDEX(Assessment!$B:$B,$A64)) | C64: =IF($A64="","",INDEX(Assessment!$D:$D,$A64)) | D64: =IF($A64="","",INDEX(Assessment!$E:$E,$A64)) | E64: =IF($A64="","",INDEX(Assessment!$G:$G,$A64)) | F64: =IF($A64="","",INDEX(Assessment!$H:$H,$A64)) | G64: =IF($A64="","",INDEX(Assessment!$I:$I,$A64))
A65: =IFERROR(MATCH(61,Assessment!$O:$O,0),"") | B65: =IF($A65="","",INDEX(Assessment!$B:$B,$A65)) | C65: =IF($A65="","",INDEX(Assessment!$D:$D,$A65)) | D65: =IF($A65="","",INDEX(Assessment!$E:$E,$A65)) | E65: =IF($A65="","",INDEX(Assessment!$G:$G,$A65)) | F65: =IF($A65="","",INDEX(Assessment!$H:$H,$A65)) | G65: =IF($A65="","",INDEX(Assessment!$I:$I,$A65))
A66: =IFERROR(MATCH(62,Assessment!$O:$O,0),"") | B66: =IF($A66="","",INDEX(Assessment!$B:$B,$A66)) | C66: =IF($A66="","",INDEX(Assessment!$D:$D,$A66)) | D66: =IF($A66="","",INDEX(Assessment!$E:$E,$A66)) | E66: =IF($A66="","",INDEX(Assessment!$G:$G,$A66)) | F66: =IF($A66="","",INDEX(Assessment!$H:$H,$A66)) | G66: =IF($A66="","",INDEX(Assessment!$I:$I,$A66))
A67: =IFERROR(MATCH(63,Assessment!$O:$O,0),"") | B67: =IF($A67="","",INDEX(Assessment!$B:$B,$A67)) | C67: =IF($A67="","",INDEX(Assessment!$D:$D,$A67)) | D67: =IF($A67="","",INDEX(Assessment!$E:$E,$A67)) | E67: =IF($A67="","",INDEX(Assessment!$G:$G,$A67)) | F67: =IF($A67="","",INDEX(Assessment!$H:$H,$A67)) | G67: =IF($A67="","",INDEX(Assessment!$I:$I,$A67))
A68: =IFERROR(MATCH(64,Assessment!$O:$O,0),"") | B68: =IF($A68="","",INDEX(Assessment!$B:$B,$A68)) | C68: =IF($A68="","",INDEX(Assessment!$D:$D,$A68)) | D68: =IF($A68="","",INDEX(Assessment!$E:$E,$A68)) | E68: =IF($A68="","",INDEX(Assessment!$G:$G,$A68)) | F68: =IF($A68="","",INDEX(Assessment!$H:$H,$A68)) | G68: =IF($A68="","",INDEX(Assessment!$I:$I,$A68))
A69: =IFERROR(MATCH(65,Assessment!$O:$O,0),"") | B69: =IF($A69="","",INDEX(Assessment!$B:$B,$A69)) | C69: =IF($A69="","",INDEX(Assessment!$D:$D,$A69)) | D69: =IF($A69="","",INDEX(Assessment!$E:$E,$A69)) | E69: =IF($A69="","",INDEX(Assessment!$G:$G,$A69)) | F69: =IF($A69="","",INDEX(Assessment!$H:$H,$A69)) | G69: =IF($A69="","",INDEX(Assessment!$I:$I,$A69))
A70: =IFERROR(MATCH(66,Assessment!$O:$O,0),"") | B70: =IF($A70="","",INDEX(Assessment!$B:$B,$A70)) | C70: =IF($A70="","",INDEX(Assessment!$D:$D,$A70)) | D70: =IF($A70="","",INDEX(Assessment!$E:$E,$A70)) | E70: =IF($A70="","",INDEX(Assessment!$G:$G,$A70)) | F70: =IF($A70="","",INDEX(Assessment!$H:$H,$A70)) | G70: =IF($A70="","",INDEX(Assessment!$I:$I,$A70))
A71: =IFERROR(MATCH(67,Assessment!$O:$O,0),"") | B71: =IF($A71="","",INDEX(Assessment!$B:$B,$A71)) | C71: =IF($A71="","",INDEX(Assessment!$D:$D,$A71)) | D71: =IF($A71="","",INDEX(Assessment!$E:$E,$A71)) | E71: =IF($A71="","",INDEX(Assessment!$G:$G,$A71)) | F71: =IF($A71="","",INDEX(Assessment!$H:$H,$A71)) | G71: =IF($A71="","",INDEX(Assessment!$I:$I,$A71))
A72: =IFERROR(MATCH(68,Assessment!$O:$O,0),"") | B72: =IF($A72="","",INDEX(Assessment!$B:$B,$A72)) | C72: =IF($A72="","",INDEX(Assessment!$D:$D,$A72)) | D72: =IF($A72="","",INDEX(Assessment!$E:$E,$A72)) | E72: =IF($A72="","",INDEX(Assessment!$G:$G,$A72)) | F72: =IF($A72="","",INDEX(Assessment!$H:$H,$A72)) | G72: =IF($A72="","",INDEX(Assessment!$I:$I,$A72))
A73: =IFERROR(MATCH(69,Assessment!$O:$O,0),"") | B73: =IF($A73="","",INDEX(Assessment!$B:$B,$A73)) | C73: =IF($A73="","",INDEX(Assessment!$D:$D,$A73)) | D73: =IF($A73="","",INDEX(Assessment!$E:$E,$A73)) | E73: =IF($A73="","",INDEX(Assessment!$G:$G,$A73)) | F73: =IF($A73="","",INDEX(Assessment!$H:$H,$A73)) | G73: =IF($A73="","",INDEX(Assessment!$I:$I,$A73))
A74: =IFERROR(MATCH(70,Assessment!$O:$O,0),"") | B74: =IF($A74="","",INDEX(Assessment!$B:$B,$A74)) | C74: =IF($A74="","",INDEX(Assessment!$D:$D,$A74)) | D74: =IF($A74="","",INDEX(Assessment!$E:$E,$A74)) | E74: =IF($A74="","",INDEX(Assessment!$G:$G,$A74)) | F74: =IF($A74="","",INDEX(Assessment!$H:$H,$A74)) | G74: =IF($A74="","",INDEX(Assessment!$I:$I,$A74))
A75: =IFERROR(MATCH(71,Assessment!$O:$O,0),"") | B75: =IF($A75="","",INDEX(Assessment!$B:$B,$A75)) | C75: =IF($A75="","",INDEX(Assessment!$D:$D,$A75)) | D75: =IF($A75="","",INDEX(Assessment!$E:$E,$A75)) | E75: =IF($A75="","",INDEX(Assessment!$G:$G,$A75)) | F75: =IF($A75="","",INDEX(Assessment!$H:$H,$A75)) | G75: =IF($A75="","",INDEX(Assessment!$I:$I,$A75))
A76: =IFERROR(MATCH(72,Assessment!$O:$O,0),"") | B76: =IF($A76="","",INDEX(Assessment!$B:$B,$A76)) | C76: =IF($A76="","",INDEX(Assessment!$D:$D,$A76)) | D76: =IF($A76="","",INDEX(Assessment!$E:$E,$A76)) | E76: =IF($A76="","",INDEX(Assessment!$G:$G,$A76)) | F76: =IF($A76="","",INDEX(Assessment!$H:$H,$A76)) | G76: =IF($A76="","",INDEX(Assessment!$I:$I,$A76))
A77: =IFERROR(MATCH(73,Assessment!$O:$O,0),"") | B77: =IF($A77="","",INDEX(Assessment!$B:$B,$A77)) | C77: =IF($A77="","",INDEX(Assessment!$D:$D,$A77)) | D77: =IF($A77="","",INDEX(Assessment!$E:$E,$A77)) | E77: =IF($A77="","",INDEX(Assessment!$G:$G,$A77)) | F77: =IF($A77="","",INDEX(Assessment!$H:$H,$A77)) | G77: =IF($A77="","",INDEX(Assessment!$I:$I,$A77))
A78: =IFERROR(MATCH(74,Assessment!$O:$O,0),"") | B78: =IF($A78="","",INDEX(Assessment!$B:$B,$A78)) | C78: =IF($A78="","",INDEX(Assessment!$D:$D,$A78)) | D78: =IF($A78="","",INDEX(Assessment!$E:$E,$A78)) | E78: =IF($A78="","",INDEX(Assessment!$G:$G,$A78)) | F78: =IF($A78="","",INDEX(Assessment!$H:$H,$A78)) | G78: =IF($A78="","",INDEX(Assessment!$I:$I,$A78))
A79: =IFERROR(MATCH(75,Assessment!$O:$O,0),"") | B79: =IF($A79="","",INDEX(Assessment!$B:$B,$A79)) | C79: =IF($A79="","",INDEX(Assessment!$D:$D,$A79)) | D79: =IF($A79="","",INDEX(Assessment!$E:$E,$A79)) | E79: =IF($A79="","",INDEX(Assessment!$G:$G,$A79)) | F79: =IF($A79="","",INDEX(Assessment!$H:$H,$A79)) | G79: =IF($A79="","",INDEX(Assessment!$I:$I,$A79))
A80: =IFERROR(MATCH(76,Assessment!$O:$O,0),"") | B80: =IF($A80="","",INDEX(Assessment!$B:$B,$A80)) | C80: =IF($A80="","",INDEX(Assessment!$D:$D,$A80)) | D80: =IF($A80="","",INDEX(Assessment!$E:$E,$A80)) | E80: =IF($A80="","",INDEX(Assessment!$G:$G,$A80)) | F80: =IF($A80="","",INDEX(Assessment!$H:$H,$A80)) | G80: =IF($A80="","",INDEX(Assessment!$I:$I,$A80))
A81: =IFERROR(MATCH(77,Assessment!$O:$O,0),"") | B81: =IF($A81="","",INDEX(Assessment!$B:$B,$A81)) | C81: =IF($A81="","",INDEX(Assessment!$D:$D,$A81)) | D81: =IF($A81="","",INDEX(Assessment!$E:$E,$A81)) | E81: =IF($A81="","",INDEX(Assessment!$G:$G,$A81)) | F81: =IF($A81="","",INDEX(Assessment!$H:$H,$A81)) | G81: =IF($A81="","",INDEX(Assessment!$I:$I,$A81))
A82: =IFERROR(MATCH(78,Assessment!$O:$O,0),"") | B82: =IF($A82="","",INDEX(Assessment!$B:$B,$A82)) | C82: =IF($A82="","",INDEX(Assessment!$D:$D,$A82)) | D82: =IF($A82="","",INDEX(Assessment!$E:$E,$A82)) | E82: =IF($A82="","",INDEX(Assessment!$G:$G,$A82)) | F82: =IF($A82="","",INDEX(Assessment!$H:$H,$A82)) | G82: =IF($A82="","",INDEX(Assessment!$I:$I,$A82))
A83: =IFERROR(MATCH(79,Assessment!$O:$O,0),"") | B83: =IF($A83="","",INDEX(Assessment!$B:$B,$A83)) | C83: =IF($A83="","",INDEX(Assessment!$D:$D,$A83)) | D83: =IF($A83="","",INDEX(Assessment!$E:$E,$A83)) | E83: =IF($A83="","",INDEX(Assessment!$G:$G,$A83)) | F83: =IF($A83="","",INDEX(Assessment!$H:$H,$A83)) | G83: =IF($A83="","",INDEX(Assessment!$I:$I,$A83))
A84: =IFERROR(MATCH(80,Assessment!$O:$O,0),"") | B84: =IF($A84="","",INDEX(Assessment!$B:$B,$A84)) | C84: =IF($A84="","",INDEX(Assessment!$D:$D,$A84)) | D84: =IF($A84="","",INDEX(Assessment!$E:$E,$A84)) | E84: =IF($A84="","",INDEX(Assessment!$G:$G,$A84)) | F84: =IF($A84="","",INDEX(Assessment!$H:$H,$A84)) | G84: =IF($A84="","",INDEX(Assessment!$I:$I,$A84))
A85: =IFERROR(MATCH(81,Assessment!$O:$O,0),"") | B85: =IF($A85="","",INDEX(Assessment!$B:$B,$A85)) | C85: =IF($A85="","",INDEX(Assessment!$D:$D,$A85)) | D85: =IF($A85="","",INDEX(Assessment!$E:$E,$A85)) | E85: =IF($A85="","",INDEX(Assessment!$G:$G,$A85)) | F85: =IF($A85="","",INDEX(Assessment!$H:$H,$A85)) | G85: =IF($A85="","",INDEX(Assessment!$I:$I,$A85))
A86: =IFERROR(MATCH(82,Assessment!$O:$O,0),"") | B86: =IF($A86="","",INDEX(Assessment!$B:$B,$A86)) | C86: =IF($A86="","",INDEX(Assessment!$D:$D,$A86)) | D86: =IF($A86="","",INDEX(Assessment!$E:$E,$A86)) | E86: =IF($A86="","",INDEX(Assessment!$G:$G,$A86)) | F86: =IF($A86="","",INDEX(Assessment!$H:$H,$A86)) | G86: =IF($A86="","",INDEX(Assessment!$I:$I,$A86))
A87: =IFERROR(MATCH(83,Assessment!$O:$O,0),"") | B87: =IF($A87="","",INDEX(Assessment!$B:$B,$A87)) | C87: =IF($A87="","",INDEX(Assessment!$D:$D,$A87)) | D87: =IF($A87="","",INDEX(Assessment!$E:$E,$A87)) | E87: =IF($A87="","",INDEX(Assessment!$G:$G,$A87)) | F87: =IF($A87="","",INDEX(Assessment!$H:$H,$A87)) | G87: =IF($A87="","",INDEX(Assessment!$I:$I,$A87))
A88: =IFERROR(MATCH(84,Assessment!$O:$O,0),"") | B88: =IF($A88="","",INDEX(Assessment!$B:$B,$A88)) | C88: =IF($A88="","",INDEX(Assessment!$D:$D,$A88)) | D88: =IF($A88="","",INDEX(Assessment!$E:$E,$A88)) | E88: =IF($A88="","",INDEX(Assessment!$G:$G,$A88)) | F88: =IF($A88="","",INDEX(Assessment!$H:$H,$A88)) | G88: =IF($A88="","",INDEX(Assessment!$I:$I,$A88))
A89: =IFERROR(MATCH(85,Assessment!$O:$O,0),"") | B89: =IF($A89="","",INDEX(Assessment!$B:$B,$A89)) | C89: =IF($A89="","",INDEX(Assessment!$D:$D,$A89)) | D89: =IF($A89="","",INDEX(Assessment!$E:$E,$A89)) | E89: =IF($A89="","",INDEX(Assessment!$G:$G,$A89)) | F89: =IF($A89="","",INDEX(Assessment!$H:$H,$A89)) | G89: =IF($A89="","",INDEX(Assessment!$I:$I,$A89))
A90: =IFERROR(MATCH(86,Assessment!$O:$O,0),"") | B90: =IF($A90="","",INDEX(Assessment!$B:$B,$A90)) | C90: =IF($A90="","",INDEX(Assessment!$D:$D,$A90)) | D90: =IF($A90="","",INDEX(Assessment!$E:$E,$A90)) | E90: =IF($A90="","",INDEX(Assessment!$G:$G,$A90)) | F90: =IF($A90="","",INDEX(Assessment!$H:$H,$A90)) | G90: =IF($A90="","",INDEX(Assessment!$I:$I,$A90))
A91: =IFERROR(MATCH(87,Assessment!$O:$O,0),"") | B91: =IF($A91="","",INDEX(Assessment!$B:$B,$A91)) | C91: =IF($A91="","",INDEX(Assessment!$D:$D,$A91)) | D91: =IF($A91="","",INDEX(Assessment!$E:$E,$A91)) | E91: =IF($A91="","",INDEX(Assessment!$G:$G,$A91)) | F91: =IF($A91="","",INDEX(Assessment!$H:$H,$A91)) | G91: =IF($A91="","",INDEX(Assessment!$I:$I,$A91))
A92: =IFERROR(MATCH(88,Assessment!$O:$O,0),"") | B92: =IF($A92="","",INDEX(Assessment!$B:$B,$A92)) | C92: =IF($A92="","",INDEX(Assessment!$D:$D,$A92)) | D92: =IF($A92="","",INDEX(Assessment!$E:$E,$A92)) | E92: =IF($A92="","",INDEX(Assessment!$G:$G,$A92)) | F92: =IF($A92="","",INDEX(Assessment!$H:$H,$A92)) | G92: =IF($A92="","",INDEX(Assessment!$I:$I,$A92))
A93: =IFERROR(MATCH(89,Assessment!$O:$O,0),"") | B93: =IF($A93="","",INDEX(Assessment!$B:$B,$A93)) | C93: =IF($A93="","",INDEX(Assessment!$D:$D,$A93)) | D93: =IF($A93="","",INDEX(Assessment!$E:$E,$A93)) | E93: =IF($A93="","",INDEX(Assessment!$G:$G,$A93)) | F93: =IF($A93="","",INDEX(Assessment!$H:$H,$A93)) | G93: =IF($A93="","",INDEX(Assessment!$I:$I,$A93))
A94: =IFERROR(MATCH(90,Assessment!$O:$O,0),"") | B94: =IF($A94="","",INDEX(Assessment!$B:$B,$A94)) | C94: =IF($A94="","",INDEX(Assessment!$D:$D,$A94)) | D94: =IF($A94="","",INDEX(Assessment!$E:$E,$A94)) | E94: =IF($A94="","",INDEX(Assessment!$G:$G,$A94)) | F94: =IF($A94="","",INDEX(Assessment!$H:$H,$A94)) | G94: =IF($A94="","",INDEX(Assessment!$I:$I,$A94))
A95: =IFERROR(MATCH(91,Assessment!$O:$O,0),"") | B95: =IF($A95="","",INDEX(Assessment!$B:$B,$A95)) | C95: =IF($A95="","",INDEX(Assessment!$D:$D,$A95)) | D95: =IF($A95="","",INDEX(Assessment!$E:$E,$A95)) | E95: =IF($A95="","",INDEX(Assessment!$G:$G,$A95)) | F95: =IF($A95="","",INDEX(Assessment!$H:$H,$A95)) | G95: =IF($A95="","",INDEX(Assessment!$I:$I,$A95))
A96: =IFERROR(MATCH(92,Assessment!$O:$O,0),"") | B96: =IF($A96="","",INDEX(Assessment!$B:$B,$A96)) | C96: =IF($A96="","",INDEX(Assessment!$D:$D,$A96)) | D96: =IF($A96="","",INDEX(Assessment!$E:$E,$A96)) | E96: =IF($A96="","",INDEX(Assessment!$G:$G,$A96)) | F96: =IF($A96="","",INDEX(Assessment!$H:$H,$A96)) | G96: =IF($A96="","",INDEX(Assessment!$I:$I,$A96))
A97: =IFERROR(MATCH(93,Assessment!$O:$O,0),"") | B97: =IF($A97="","",INDEX(Assessment!$B:$B,$A97)) | C97: =IF($A97="","",INDEX(Assessment!$D:$D,$A97)) | D97: =IF($A97="","",INDEX(Assessment!$E:$E,$A97)) | E97: =IF($A97="","",INDEX(Assessment!$G:$G,$A97)) | F97: =IF($A97="","",INDEX(Assessment!$H:$H,$A97)) | G97: =IF($A97="","",INDEX(Assessment!$I:$I,$A97))
A98: =IFERROR(MATCH(94,Assessment!$O:$O,0),"") | B98: =IF($A98="","",INDEX(Assessment!$B:$B,$A98)) | C98: =IF($A98="","",INDEX(Assessment!$D:$D,$A98)) | D98: =IF($A98="","",INDEX(Assessment!$E:$E,$A98)) | E98: =IF($A98="","",INDEX(Assessment!$G:$G,$A98)) | F98: =IF($A98="","",INDEX(Assessment!$H:$H,$A98)) | G98: =IF($A98="","",INDEX(Assessment!$I:$I,$A98))
A99: =IFERROR(MATCH(95,Assessment!$O:$O,0),"") | B99: =IF($A99="","",INDEX(Assessment!$B:$B,$A99)) | C99: =IF($A99="","",INDEX(Assessment!$D:$D,$A99)) | D99: =IF($A99="","",INDEX(Assessment!$E:$E,$A99)) | E99: =IF($A99="","",INDEX(Assessment!$G:$G,$A99)) | F99: =IF($A99="","",INDEX(Assessment!$H:$H,$A99)) | G99: =IF($A99="","",INDEX(Assessment!$I:$I,$A99))
A100: =IFERROR(MATCH(96,Assessment!$O:$O,0),"") | B100: =IF($A100="","",INDEX(Assessment!$B:$B,$A100)) | C100: =IF($A100="","",INDEX(Assessment!$D:$D,$A100)) | D100: =IF($A100="","",INDEX(Assessment!$E:$E,$A100)) | E100: =IF($A100="","",INDEX(Assessment!$G:$G,$A100)) | F100: =IF($A100="","",INDEX(Assessment!$H:$H,$A100)) | G100: =IF($A100="","",INDEX(Assessment!$I:$I,$A100))
A101: =IFERROR(MATCH(97,Assessment!$O:$O,0),"") | B101: =IF($A101="","",INDEX(Assessment!$B:$B,$A101)) | C101: =IF($A101="","",INDEX(Assessment!$D:$D,$A101)) | D101: =IF($A101="","",INDEX(Assessment!$E:$E,$A101)) | E101: =IF($A101="","",INDEX(Assessment!$G:$G,$A101)) | F101: =IF($A101="","",INDEX(Assessment!$H:$H,$A101)) | G101: =IF($A101="","",INDEX(Assessment!$I:$I,$A101))
...

Sheet Onboarding List (AC)
A1: ONBOARDING LIST (AC)
A3: Adoption / Config items — TownSq can do this after setup, configuration, or training. Column 'TownSq supports today' shows what needs to be configured. All items must be resolved before or at go-live.
A4: Row# | B4: Domain | C4: Capability | D4: Dimension | E4: Discovery Question | F4: Branch Answer | G4: TownSq supports today | H4: Setup / Config Needed | I4: Training Required? | J4: Owner | K4: Status
A5: =IFERROR(MATCH(1,Assessment!$M:$M,0),"") | B5: =IF($A5="","",INDEX(Assessment!$B:$B,$A5)) | C5: =IF($A5="","",INDEX(Assessment!$D:$D,$A5)) | D5: =IF($A5="","",INDEX(Assessment!$E:$E,$A5)) | E5: =IF($A5="","",INDEX(Assessment!$G:$G,$A5)) | F5: =IF($A5="","",INDEX(Assessment!$H:$H,$A5)) | G5: =IF($A5="","",INDEX(Assessment!$I:$I,$A5))
A6: =IFERROR(MATCH(2,Assessment!$M:$M,0),"") | B6: =IF($A6="","",INDEX(Assessment!$B:$B,$A6)) | C6: =IF($A6="","",INDEX(Assessment!$D:$D,$A6)) | D6: =IF($A6="","",INDEX(Assessment!$E:$E,$A6)) | E6: =IF($A6="","",INDEX(Assessment!$G:$G,$A6)) | F6: =IF($A6="","",INDEX(Assessment!$H:$H,$A6)) | G6: =IF($A6="","",INDEX(Assessment!$I:$I,$A6))
A7: =IFERROR(MATCH(3,Assessment!$M:$M,0),"") | B7: =IF($A7="","",INDEX(Assessment!$B:$B,$A7)) | C7: =IF($A7="","",INDEX(Assessment!$D:$D,$A7)) | D7: =IF($A7="","",INDEX(Assessment!$E:$E,$A7)) | E7: =IF($A7="","",INDEX(Assessment!$G:$G,$A7)) | F7: =IF($A7="","",INDEX(Assessment!$H:$H,$A7)) | G7: =IF($A7="","",INDEX(Assessment!$I:$I,$A7))
A8: =IFERROR(MATCH(4,Assessment!$M:$M,0),"") | B8: =IF($A8="","",INDEX(Assessment!$B:$B,$A8)) | C8: =IF($A8="","",INDEX(Assessment!$D:$D,$A8)) | D8: =IF($A8="","",INDEX(Assessment!$E:$E,$A8)) | E8: =IF($A8="","",INDEX(Assessment!$G:$G,$A8)) | F8: =IF($A8="","",INDEX(Assessment!$H:$H,$A8)) | G8: =IF($A8="","",INDEX(Assessment!$I:$I,$A8))
A9: =IFERROR(MATCH(5,Assessment!$M:$M,0),"") | B9: =IF($A9="","",INDEX(Assessment!$B:$B,$A9)) | C9: =IF($A9="","",INDEX(Assessment!$D:$D,$A9)) | D9: =IF($A9="","",INDEX(Assessment!$E:$E,$A9)) | E9: =IF($A9="","",INDEX(Assessment!$G:$G,$A9)) | F9: =IF($A9="","",INDEX(Assessment!$H:$H,$A9)) | G9: =IF($A9="","",INDEX(Assessment!$I:$I,$A9))
A10: =IFERROR(MATCH(6,Assessment!$M:$M,0),"") | B10: =IF($A10="","",INDEX(Assessment!$B:$B,$A10)) | C10: =IF($A10="","",INDEX(Assessment!$D:$D,$A10)) | D10: =IF($A10="","",INDEX(Assessment!$E:$E,$A10)) | E10: =IF($A10="","",INDEX(Assessment!$G:$G,$A10)) | F10: =IF($A10="","",INDEX(Assessment!$H:$H,$A10)) | G10: =IF($A10="","",INDEX(Assessment!$I:$I,$A10))
A11: =IFERROR(MATCH(7,Assessment!$M:$M,0),"") | B11: =IF($A11="","",INDEX(Assessment!$B:$B,$A11)) | C11: =IF($A11="","",INDEX(Assessment!$D:$D,$A11)) | D11: =IF($A11="","",INDEX(Assessment!$E:$E,$A11)) | E11: =IF($A11="","",INDEX(Assessment!$G:$G,$A11)) | F11: =IF($A11="","",INDEX(Assessment!$H:$H,$A11)) | G11: =IF($A11="","",INDEX(Assessment!$I:$I,$A11))
A12: =IFERROR(MATCH(8,Assessment!$M:$M,0),"") | B12: =IF($A12="","",INDEX(Assessment!$B:$B,$A12)) | C12: =IF($A12="","",INDEX(Assessment!$D:$D,$A12)) | D12: =IF($A12="","",INDEX(Assessment!$E:$E,$A12)) | E12: =IF($A12="","",INDEX(Assessment!$G:$G,$A12)) | F12: =IF($A12="","",INDEX(Assessment!$H:$H,$A12)) | G12: =IF($A12="","",INDEX(Assessment!$I:$I,$A12))
A13: =IFERROR(MATCH(9,Assessment!$M:$M,0),"") | B13: =IF($A13="","",INDEX(Assessment!$B:$B,$A13)) | C13: =IF($A13="","",INDEX(Assessment!$D:$D,$A13)) | D13: =IF($A13="","",INDEX(Assessment!$E:$E,$A13)) | E13: =IF($A13="","",INDEX(Assessment!$G:$G,$A13)) | F13: =IF($A13="","",INDEX(Assessment!$H:$H,$A13)) | G13: =IF($A13="","",INDEX(Assessment!$I:$I,$A13))
A14: =IFERROR(MATCH(10,Assessment!$M:$M,0),"") | B14: =IF($A14="","",INDEX(Assessment!$B:$B,$A14)) | C14: =IF($A14="","",INDEX(Assessment!$D:$D,$A14)) | D14: =IF($A14="","",INDEX(Assessment!$E:$E,$A14)) | E14: =IF($A14="","",INDEX(Assessment!$G:$G,$A14)) | F14: =IF($A14="","",INDEX(Assessment!$H:$H,$A14)) | G14: =IF($A14="","",INDEX(Assessment!$I:$I,$A14))
A15: =IFERROR(MATCH(11,Assessment!$M:$M,0),"") | B15: =IF($A15="","",INDEX(Assessment!$B:$B,$A15)) | C15: =IF($A15="","",INDEX(Assessment!$D:$D,$A15)) | D15: =IF($A15="","",INDEX(Assessment!$E:$E,$A15)) | E15: =IF($A15="","",INDEX(Assessment!$G:$G,$A15)) | F15: =IF($A15="","",INDEX(Assessment!$H:$H,$A15)) | G15: =IF($A15="","",INDEX(Assessment!$I:$I,$A15))
A16: =IFERROR(MATCH(12,Assessment!$M:$M,0),"") | B16: =IF($A16="","",INDEX(Assessment!$B:$B,$A16)) | C16: =IF($A16="","",INDEX(Assessment!$D:$D,$A16)) | D16: =IF($A16="","",INDEX(Assessment!$E:$E,$A16)) | E16: =IF($A16="","",INDEX(Assessment!$G:$G,$A16)) | F16: =IF($A16="","",INDEX(Assessment!$H:$H,$A16)) | G16: =IF($A16="","",INDEX(Assessment!$I:$I,$A16))
A17: =IFERROR(MATCH(13,Assessment!$M:$M,0),"") | B17: =IF($A17="","",INDEX(Assessment!$B:$B,$A17)) | C17: =IF($A17="","",INDEX(Assessment!$D:$D,$A17)) | D17: =IF($A17="","",INDEX(Assessment!$E:$E,$A17)) | E17: =IF($A17="","",INDEX(Assessment!$G:$G,$A17)) | F17: =IF($A17="","",INDEX(Assessment!$H:$H,$A17)) | G17: =IF($A17="","",INDEX(Assessment!$I:$I,$A17))
A18: =IFERROR(MATCH(14,Assessment!$M:$M,0),"") | B18: =IF($A18="","",INDEX(Assessment!$B:$B,$A18)) | C18: =IF($A18="","",INDEX(Assessment!$D:$D,$A18)) | D18: =IF($A18="","",INDEX(Assessment!$E:$E,$A18)) | E18: =IF($A18="","",INDEX(Assessment!$G:$G,$A18)) | F18: =IF($A18="","",INDEX(Assessment!$H:$H,$A18)) | G18: =IF($A18="","",INDEX(Assessment!$I:$I,$A18))
A19: =IFERROR(MATCH(15,Assessment!$M:$M,0),"") | B19: =IF($A19="","",INDEX(Assessment!$B:$B,$A19)) | C19: =IF($A19="","",INDEX(Assessment!$D:$D,$A19)) | D19: =IF($A19="","",INDEX(Assessment!$E:$E,$A19)) | E19: =IF($A19="","",INDEX(Assessment!$G:$G,$A19)) | F19: =IF($A19="","",INDEX(Assessment!$H:$H,$A19)) | G19: =IF($A19="","",INDEX(Assessment!$I:$I,$A19))
A20: =IFERROR(MATCH(16,Assessment!$M:$M,0),"") | B20: =IF($A20="","",INDEX(Assessment!$B:$B,$A20)) | C20: =IF($A20="","",INDEX(Assessment!$D:$D,$A20)) | D20: =IF($A20="","",INDEX(Assessment!$E:$E,$A20)) | E20: =IF($A20="","",INDEX(Assessment!$G:$G,$A20)) | F20: =IF($A20="","",INDEX(Assessment!$H:$H,$A20)) | G20: =IF($A20="","",INDEX(Assessment!$I:$I,$A20))
A21: =IFERROR(MATCH(17,Assessment!$M:$M,0),"") | B21: =IF($A21="","",INDEX(Assessment!$B:$B,$A21)) | C21: =IF($A21="","",INDEX(Assessment!$D:$D,$A21)) | D21: =IF($A21="","",INDEX(Assessment!$E:$E,$A21)) | E21: =IF($A21="","",INDEX(Assessment!$G:$G,$A21)) | F21: =IF($A21="","",INDEX(Assessment!$H:$H,$A21)) | G21: =IF($A21="","",INDEX(Assessment!$I:$I,$A21))
A22: =IFERROR(MATCH(18,Assessment!$M:$M,0),"") | B22: =IF($A22="","",INDEX(Assessment!$B:$B,$A22)) | C22: =IF($A22="","",INDEX(Assessment!$D:$D,$A22)) | D22: =IF($A22="","",INDEX(Assessment!$E:$E,$A22)) | E22: =IF($A22="","",INDEX(Assessment!$G:$G,$A22)) | F22: =IF($A22="","",INDEX(Assessment!$H:$H,$A22)) | G22: =IF($A22="","",INDEX(Assessment!$I:$I,$A22))
A23: =IFERROR(MATCH(19,Assessment!$M:$M,0),"") | B23: =IF($A23="","",INDEX(Assessment!$B:$B,$A23)) | C23: =IF($A23="","",INDEX(Assessment!$D:$D,$A23)) | D23: =IF($A23="","",INDEX(Assessment!$E:$E,$A23)) | E23: =IF($A23="","",INDEX(Assessment!$G:$G,$A23)) | F23: =IF($A23="","",INDEX(Assessment!$H:$H,$A23)) | G23: =IF($A23="","",INDEX(Assessment!$I:$I,$A23))
A24: =IFERROR(MATCH(20,Assessment!$M:$M,0),"") | B24: =IF($A24="","",INDEX(Assessment!$B:$B,$A24)) | C24: =IF($A24="","",INDEX(Assessment!$D:$D,$A24)) | D24: =IF($A24="","",INDEX(Assessment!$E:$E,$A24)) | E24: =IF($A24="","",INDEX(Assessment!$G:$G,$A24)) | F24: =IF($A24="","",INDEX(Assessment!$H:$H,$A24)) | G24: =IF($A24="","",INDEX(Assessment!$I:$I,$A24))
A25: =IFERROR(MATCH(21,Assessment!$M:$M,0),"") | B25: =IF($A25="","",INDEX(Assessment!$B:$B,$A25)) | C25: =IF($A25="","",INDEX(Assessment!$D:$D,$A25)) | D25: =IF($A25="","",INDEX(Assessment!$E:$E,$A25)) | E25: =IF($A25="","",INDEX(Assessment!$G:$G,$A25)) | F25: =IF($A25="","",INDEX(Assessment!$H:$H,$A25)) | G25: =IF($A25="","",INDEX(Assessment!$I:$I,$A25))
A26: =IFERROR(MATCH(22,Assessment!$M:$M,0),"") | B26: =IF($A26="","",INDEX(Assessment!$B:$B,$A26)) | C26: =IF($A26="","",INDEX(Assessment!$D:$D,$A26)) | D26: =IF($A26="","",INDEX(Assessment!$E:$E,$A26)) | E26: =IF($A26="","",INDEX(Assessment!$G:$G,$A26)) | F26: =IF($A26="","",INDEX(Assessment!$H:$H,$A26)) | G26: =IF($A26="","",INDEX(Assessment!$I:$I,$A26))
A27: =IFERROR(MATCH(23,Assessment!$M:$M,0),"") | B27: =IF($A27="","",INDEX(Assessment!$B:$B,$A27)) | C27: =IF($A27="","",INDEX(Assessment!$D:$D,$A27)) | D27: =IF($A27="","",INDEX(Assessment!$E:$E,$A27)) | E27: =IF($A27="","",INDEX(Assessment!$G:$G,$A27)) | F27: =IF($A27="","",INDEX(Assessment!$H:$H,$A27)) | G27: =IF($A27="","",INDEX(Assessment!$I:$I,$A27))
A28: =IFERROR(MATCH(24,Assessment!$M:$M,0),"") | B28: =IF($A28="","",INDEX(Assessment!$B:$B,$A28)) | C28: =IF($A28="","",INDEX(Assessment!$D:$D,$A28)) | D28: =IF($A28="","",INDEX(Assessment!$E:$E,$A28)) | E28: =IF($A28="","",INDEX(Assessment!$G:$G,$A28)) | F28: =IF($A28="","",INDEX(Assessment!$H:$H,$A28)) | G28: =IF($A28="","",INDEX(Assessment!$I:$I,$A28))
A29: =IFERROR(MATCH(25,Assessment!$M:$M,0),"") | B29: =IF($A29="","",INDEX(Assessment!$B:$B,$A29)) | C29: =IF($A29="","",INDEX(Assessment!$D:$D,$A29)) | D29: =IF($A29="","",INDEX(Assessment!$E:$E,$A29)) | E29: =IF($A29="","",INDEX(Assessment!$G:$G,$A29)) | F29: =IF($A29="","",INDEX(Assessment!$H:$H,$A29)) | G29: =IF($A29="","",INDEX(Assessment!$I:$I,$A29))
A30: =IFERROR(MATCH(26,Assessment!$M:$M,0),"") | B30: =IF($A30="","",INDEX(Assessment!$B:$B,$A30)) | C30: =IF($A30="","",INDEX(Assessment!$D:$D,$A30)) | D30: =IF($A30="","",INDEX(Assessment!$E:$E,$A30)) | E30: =IF($A30="","",INDEX(Assessment!$G:$G,$A30)) | F30: =IF($A30="","",INDEX(Assessment!$H:$H,$A30)) | G30: =IF($A30="","",INDEX(Assessment!$I:$I,$A30))
A31: =IFERROR(MATCH(27,Assessment!$M:$M,0),"") | B31: =IF($A31="","",INDEX(Assessment!$B:$B,$A31)) | C31: =IF($A31="","",INDEX(Assessment!$D:$D,$A31)) | D31: =IF($A31="","",INDEX(Assessment!$E:$E,$A31)) | E31: =IF($A31="","",INDEX(Assessment!$G:$G,$A31)) | F31: =IF($A31="","",INDEX(Assessment!$H:$H,$A31)) | G31: =IF($A31="","",INDEX(Assessment!$I:$I,$A31))
A32: =IFERROR(MATCH(28,Assessment!$M:$M,0),"") | B32: =IF($A32="","",INDEX(Assessment!$B:$B,$A32)) | C32: =IF($A32="","",INDEX(Assessment!$D:$D,$A32)) | D32: =IF($A32="","",INDEX(Assessment!$E:$E,$A32)) | E32: =IF($A32="","",INDEX(Assessment!$G:$G,$A32)) | F32: =IF($A32="","",INDEX(Assessment!$H:$H,$A32)) | G32: =IF($A32="","",INDEX(Assessment!$I:$I,$A32))
A33: =IFERROR(MATCH(29,Assessment!$M:$M,0),"") | B33: =IF($A33="","",INDEX(Assessment!$B:$B,$A33)) | C33: =IF($A33="","",INDEX(Assessment!$D:$D,$A33)) | D33: =IF($A33="","",INDEX(Assessment!$E:$E,$A33)) | E33: =IF($A33="","",INDEX(Assessment!$G:$G,$A33)) | F33: =IF($A33="","",INDEX(Assessment!$H:$H,$A33)) | G33: =IF($A33="","",INDEX(Assessment!$I:$I,$A33))
A34: =IFERROR(MATCH(30,Assessment!$M:$M,0),"") | B34: =IF($A34="","",INDEX(Assessment!$B:$B,$A34)) | C34: =IF($A34="","",INDEX(Assessment!$D:$D,$A34)) | D34: =IF($A34="","",INDEX(Assessment!$E:$E,$A34)) | E34: =IF($A34="","",INDEX(Assessment!$G:$G,$A34)) | F34: =IF($A34="","",INDEX(Assessment!$H:$H,$A34)) | G34: =IF($A34="","",INDEX(Assessment!$I:$I,$A34))
A35: =IFERROR(MATCH(31,Assessment!$M:$M,0),"") | B35: =IF($A35="","",INDEX(Assessment!$B:$B,$A35)) | C35: =IF($A35="","",INDEX(Assessment!$D:$D,$A35)) | D35: =IF($A35="","",INDEX(Assessment!$E:$E,$A35)) | E35: =IF($A35="","",INDEX(Assessment!$G:$G,$A35)) | F35: =IF($A35="","",INDEX(Assessment!$H:$H,$A35)) | G35: =IF($A35="","",INDEX(Assessment!$I:$I,$A35))
A36: =IFERROR(MATCH(32,Assessment!$M:$M,0),"") | B36: =IF($A36="","",INDEX(Assessment!$B:$B,$A36)) | C36: =IF($A36="","",INDEX(Assessment!$D:$D,$A36)) | D36: =IF($A36="","",INDEX(Assessment!$E:$E,$A36)) | E36: =IF($A36="","",INDEX(Assessment!$G:$G,$A36)) | F36: =IF($A36="","",INDEX(Assessment!$H:$H,$A36)) | G36: =IF($A36="","",INDEX(Assessment!$I:$I,$A36))
A37: =IFERROR(MATCH(33,Assessment!$M:$M,0),"") | B37: =IF($A37="","",INDEX(Assessment!$B:$B,$A37)) | C37: =IF($A37="","",INDEX(Assessment!$D:$D,$A37)) | D37: =IF($A37="","",INDEX(Assessment!$E:$E,$A37)) | E37: =IF($A37="","",INDEX(Assessment!$G:$G,$A37)) | F37: =IF($A37="","",INDEX(Assessment!$H:$H,$A37)) | G37: =IF($A37="","",INDEX(Assessment!$I:$I,$A37))
A38: =IFERROR(MATCH(34,Assessment!$M:$M,0),"") | B38: =IF($A38="","",INDEX(Assessment!$B:$B,$A38)) | C38: =IF($A38="","",INDEX(Assessment!$D:$D,$A38)) | D38: =IF($A38="","",INDEX(Assessment!$E:$E,$A38)) | E38: =IF($A38="","",INDEX(Assessment!$G:$G,$A38)) | F38: =IF($A38="","",INDEX(Assessment!$H:$H,$A38)) | G38: =IF($A38="","",INDEX(Assessment!$I:$I,$A38))
A39: =IFERROR(MATCH(35,Assessment!$M:$M,0),"") | B39: =IF($A39="","",INDEX(Assessment!$B:$B,$A39)) | C39: =IF($A39="","",INDEX(Assessment!$D:$D,$A39)) | D39: =IF($A39="","",INDEX(Assessment!$E:$E,$A39)) | E39: =IF($A39="","",INDEX(Assessment!$G:$G,$A39)) | F39: =IF($A39="","",INDEX(Assessment!$H:$H,$A39)) | G39: =IF($A39="","",INDEX(Assessment!$I:$I,$A39))
A40: =IFERROR(MATCH(36,Assessment!$M:$M,0),"") | B40: =IF($A40="","",INDEX(Assessment!$B:$B,$A40)) | C40: =IF($A40="","",INDEX(Assessment!$D:$D,$A40)) | D40: =IF($A40="","",INDEX(Assessment!$E:$E,$A40)) | E40: =IF($A40="","",INDEX(Assessment!$G:$G,$A40)) | F40: =IF($A40="","",INDEX(Assessment!$H:$H,$A40)) | G40: =IF($A40="","",INDEX(Assessment!$I:$I,$A40))
A41: =IFERROR(MATCH(37,Assessment!$M:$M,0),"") | B41: =IF($A41="","",INDEX(Assessment!$B:$B,$A41)) | C41: =IF($A41="","",INDEX(Assessment!$D:$D,$A41)) | D41: =IF($A41="","",INDEX(Assessment!$E:$E,$A41)) | E41: =IF($A41="","",INDEX(Assessment!$G:$G,$A41)) | F41: =IF($A41="","",INDEX(Assessment!$H:$H,$A41)) | G41: =IF($A41="","",INDEX(Assessment!$I:$I,$A41))
A42: =IFERROR(MATCH(38,Assessment!$M:$M,0),"") | B42: =IF($A42="","",INDEX(Assessment!$B:$B,$A42)) | C42: =IF($A42="","",INDEX(Assessment!$D:$D,$A42)) | D42: =IF($A42="","",INDEX(Assessment!$E:$E,$A42)) | E42: =IF($A42="","",INDEX(Assessment!$G:$G,$A42)) | F42: =IF($A42="","",INDEX(Assessment!$H:$H,$A42)) | G42: =IF($A42="","",INDEX(Assessment!$I:$I,$A42))
A43: =IFERROR(MATCH(39,Assessment!$M:$M,0),"") | B43: =IF($A43="","",INDEX(Assessment!$B:$B,$A43)) | C43: =IF($A43="","",INDEX(Assessment!$D:$D,$A43)) | D43: =IF($A43="","",INDEX(Assessment!$E:$E,$A43)) | E43: =IF($A43="","",INDEX(Assessment!$G:$G,$A43)) | F43: =IF($A43="","",INDEX(Assessment!$H:$H,$A43)) | G43: =IF($A43="","",INDEX(Assessment!$I:$I,$A43))
A44: =IFERROR(MATCH(40,Assessment!$M:$M,0),"") | B44: =IF($A44="","",INDEX(Assessment!$B:$B,$A44)) | C44: =IF($A44="","",INDEX(Assessment!$D:$D,$A44)) | D44: =IF($A44="","",INDEX(Assessment!$E:$E,$A44)) | E44: =IF($A44="","",INDEX(Assessment!$G:$G,$A44)) | F44: =IF($A44="","",INDEX(Assessment!$H:$H,$A44)) | G44: =IF($A44="","",INDEX(Assessment!$I:$I,$A44))
A45: =IFERROR(MATCH(41,Assessment!$M:$M,0),"") | B45: =IF($A45="","",INDEX(Assessment!$B:$B,$A45)) | C45: =IF($A45="","",INDEX(Assessment!$D:$D,$A45)) | D45: =IF($A45="","",INDEX(Assessment!$E:$E,$A45)) | E45: =IF($A45="","",INDEX(Assessment!$G:$G,$A45)) | F45: =IF($A45="","",INDEX(Assessment!$H:$H,$A45)) | G45: =IF($A45="","",INDEX(Assessment!$I:$I,$A45))
A46: =IFERROR(MATCH(42,Assessment!$M:$M,0),"") | B46: =IF($A46="","",INDEX(Assessment!$B:$B,$A46)) | C46: =IF($A46="","",INDEX(Assessment!$D:$D,$A46)) | D46: =IF($A46="","",INDEX(Assessment!$E:$E,$A46)) | E46: =IF($A46="","",INDEX(Assessment!$G:$G,$A46)) | F46: =IF($A46="","",INDEX(Assessment!$H:$H,$A46)) | G46: =IF($A46="","",INDEX(Assessment!$I:$I,$A46))
A47: =IFERROR(MATCH(43,Assessment!$M:$M,0),"") | B47: =IF($A47="","",INDEX(Assessment!$B:$B,$A47)) | C47: =IF($A47="","",INDEX(Assessment!$D:$D,$A47)) | D47: =IF($A47="","",INDEX(Assessment!$E:$E,$A47)) | E47: =IF($A47="","",INDEX(Assessment!$G:$G,$A47)) | F47: =IF($A47="","",INDEX(Assessment!$H:$H,$A47)) | G47: =IF($A47="","",INDEX(Assessment!$I:$I,$A47))
A48: =IFERROR(MATCH(44,Assessment!$M:$M,0),"") | B48: =IF($A48="","",INDEX(Assessment!$B:$B,$A48)) | C48: =IF($A48="","",INDEX(Assessment!$D:$D,$A48)) | D48: =IF($A48="","",INDEX(Assessment!$E:$E,$A48)) | E48: =IF($A48="","",INDEX(Assessment!$G:$G,$A48)) | F48: =IF($A48="","",INDEX(Assessment!$H:$H,$A48)) | G48: =IF($A48="","",INDEX(Assessment!$I:$I,$A48))
A49: =IFERROR(MATCH(45,Assessment!$M:$M,0),"") | B49: =IF($A49="","",INDEX(Assessment!$B:$B,$A49)) | C49: =IF($A49="","",INDEX(Assessment!$D:$D,$A49)) | D49: =IF($A49="","",INDEX(Assessment!$E:$E,$A49)) | E49: =IF($A49="","",INDEX(Assessment!$G:$G,$A49)) | F49: =IF($A49="","",INDEX(Assessment!$H:$H,$A49)) | G49: =IF($A49="","",INDEX(Assessment!$I:$I,$A49))
A50: =IFERROR(MATCH(46,Assessment!$M:$M,0),"") | B50: =IF($A50="","",INDEX(Assessment!$B:$B,$A50)) | C50: =IF($A50="","",INDEX(Assessment!$D:$D,$A50)) | D50: =IF($A50="","",INDEX(Assessment!$E:$E,$A50)) | E50: =IF($A50="","",INDEX(Assessment!$G:$G,$A50)) | F50: =IF($A50="","",INDEX(Assessment!$H:$H,$A50)) | G50: =IF($A50="","",INDEX(Assessment!$I:$I,$A50))
A51: =IFERROR(MATCH(47,Assessment!$M:$M,0),"") | B51: =IF($A51="","",INDEX(Assessment!$B:$B,$A51)) | C51: =IF($A51="","",INDEX(Assessment!$D:$D,$A51)) | D51: =IF($A51="","",INDEX(Assessment!$E:$E,$A51)) | E51: =IF($A51="","",INDEX(Assessment!$G:$G,$A51)) | F51: =IF($A51="","",INDEX(Assessment!$H:$H,$A51)) | G51: =IF($A51="","",INDEX(Assessment!$I:$I,$A51))
A52: =IFERROR(MATCH(48,Assessment!$M:$M,0),"") | B52: =IF($A52="","",INDEX(Assessment!$B:$B,$A52)) | C52: =IF($A52="","",INDEX(Assessment!$D:$D,$A52)) | D52: =IF($A52="","",INDEX(Assessment!$E:$E,$A52)) | E52: =IF($A52="","",INDEX(Assessment!$G:$G,$A52)) | F52: =IF($A52="","",INDEX(Assessment!$H:$H,$A52)) | G52: =IF($A52="","",INDEX(Assessment!$I:$I,$A52))
A53: =IFERROR(MATCH(49,Assessment!$M:$M,0),"") | B53: =IF($A53="","",INDEX(Assessment!$B:$B,$A53)) | C53: =IF($A53="","",INDEX(Assessment!$D:$D,$A53)) | D53: =IF($A53="","",INDEX(Assessment!$E:$E,$A53)) | E53: =IF($A53="","",INDEX(Assessment!$G:$G,$A53)) | F53: =IF($A53="","",INDEX(Assessment!$H:$H,$A53)) | G53: =IF($A53="","",INDEX(Assessment!$I:$I,$A53))
A54: =IFERROR(MATCH(50,Assessment!$M:$M,0),"") | B54: =IF($A54="","",INDEX(Assessment!$B:$B,$A54)) | C54: =IF($A54="","",INDEX(Assessment!$D:$D,$A54)) | D54: =IF($A54="","",INDEX(Assessment!$E:$E,$A54)) | E54: =IF($A54="","",INDEX(Assessment!$G:$G,$A54)) | F54: =IF($A54="","",INDEX(Assessment!$H:$H,$A54)) | G54: =IF($A54="","",INDEX(Assessment!$I:$I,$A54))
A55: =IFERROR(MATCH(51,Assessment!$M:$M,0),"") | B55: =IF($A55="","",INDEX(Assessment!$B:$B,$A55)) | C55: =IF($A55="","",INDEX(Assessment!$D:$D,$A55)) | D55: =IF($A55="","",INDEX(Assessment!$E:$E,$A55)) | E55: =IF($A55="","",INDEX(Assessment!$G:$G,$A55)) | F55: =IF($A55="","",INDEX(Assessment!$H:$H,$A55)) | G55: =IF($A55="","",INDEX(Assessment!$I:$I,$A55))
A56: =IFERROR(MATCH(52,Assessment!$M:$M,0),"") | B56: =IF($A56="","",INDEX(Assessment!$B:$B,$A56)) | C56: =IF($A56="","",INDEX(Assessment!$D:$D,$A56)) | D56: =IF($A56="","",INDEX(Assessment!$E:$E,$A56)) | E56: =IF($A56="","",INDEX(Assessment!$G:$G,$A56)) | F56: =IF($A56="","",INDEX(Assessment!$H:$H,$A56)) | G56: =IF($A56="","",INDEX(Assessment!$I:$I,$A56))
A57: =IFERROR(MATCH(53,Assessment!$M:$M,0),"") | B57: =IF($A57="","",INDEX(Assessment!$B:$B,$A57)) | C57: =IF($A57="","",INDEX(Assessment!$D:$D,$A57)) | D57: =IF($A57="","",INDEX(Assessment!$E:$E,$A57)) | E57: =IF($A57="","",INDEX(Assessment!$G:$G,$A57)) | F57: =IF($A57="","",INDEX(Assessment!$H:$H,$A57)) | G57: =IF($A57="","",INDEX(Assessment!$I:$I,$A57))
A58: =IFERROR(MATCH(54,Assessment!$M:$M,0),"") | B58: =IF($A58="","",INDEX(Assessment!$B:$B,$A58)) | C58: =IF($A58="","",INDEX(Assessment!$D:$D,$A58)) | D58: =IF($A58="","",INDEX(Assessment!$E:$E,$A58)) | E58: =IF($A58="","",INDEX(Assessment!$G:$G,$A58)) | F58: =IF($A58="","",INDEX(Assessment!$H:$H,$A58)) | G58: =IF($A58="","",INDEX(Assessment!$I:$I,$A58))
A59: =IFERROR(MATCH(55,Assessment!$M:$M,0),"") | B59: =IF($A59="","",INDEX(Assessment!$B:$B,$A59)) | C59: =IF($A59="","",INDEX(Assessment!$D:$D,$A59)) | D59: =IF($A59="","",INDEX(Assessment!$E:$E,$A59)) | E59: =IF($A59="","",INDEX(Assessment!$G:$G,$A59)) | F59: =IF($A59="","",INDEX(Assessment!$H:$H,$A59)) | G59: =IF($A59="","",INDEX(Assessment!$I:$I,$A59))
A60: =IFERROR(MATCH(56,Assessment!$M:$M,0),"") | B60: =IF($A60="","",INDEX(Assessment!$B:$B,$A60)) | C60: =IF($A60="","",INDEX(Assessment!$D:$D,$A60)) | D60: =IF($A60="","",INDEX(Assessment!$E:$E,$A60)) | E60: =IF($A60="","",INDEX(Assessment!$G:$G,$A60)) | F60: =IF($A60="","",INDEX(Assessment!$H:$H,$A60)) | G60: =IF($A60="","",INDEX(Assessment!$I:$I,$A60))
A61: =IFERROR(MATCH(57,Assessment!$M:$M,0),"") | B61: =IF($A61="","",INDEX(Assessment!$B:$B,$A61)) | C61: =IF($A61="","",INDEX(Assessment!$D:$D,$A61)) | D61: =IF($A61="","",INDEX(Assessment!$E:$E,$A61)) | E61: =IF($A61="","",INDEX(Assessment!$G:$G,$A61)) | F61: =IF($A61="","",INDEX(Assessment!$H:$H,$A61)) | G61: =IF($A61="","",INDEX(Assessment!$I:$I,$A61))
A62: =IFERROR(MATCH(58,Assessment!$M:$M,0),"") | B62: =IF($A62="","",INDEX(Assessment!$B:$B,$A62)) | C62: =IF($A62="","",INDEX(Assessment!$D:$D,$A62)) | D62: =IF($A62="","",INDEX(Assessment!$E:$E,$A62)) | E62: =IF($A62="","",INDEX(Assessment!$G:$G,$A62)) | F62: =IF($A62="","",INDEX(Assessment!$H:$H,$A62)) | G62: =IF($A62="","",INDEX(Assessment!$I:$I,$A62))
A63: =IFERROR(MATCH(59,Assessment!$M:$M,0),"") | B63: =IF($A63="","",INDEX(Assessment!$B:$B,$A63)) | C63: =IF($A63="","",INDEX(Assessment!$D:$D,$A63)) | D63: =IF($A63="","",INDEX(Assessment!$E:$E,$A63)) | E63: =IF($A63="","",INDEX(Assessment!$G:$G,$A63)) | F63: =IF($A63="","",INDEX(Assessment!$H:$H,$A63)) | G63: =IF($A63="","",INDEX(Assessment!$I:$I,$A63))
A64: =IFERROR(MATCH(60,Assessment!$M:$M,0),"") | B64: =IF($A64="","",INDEX(Assessment!$B:$B,$A64)) | C64: =IF($A64="","",INDEX(Assessment!$D:$D,$A64)) | D64: =IF($A64="","",INDEX(Assessment!$E:$E,$A64)) | E64: =IF($A64="","",INDEX(Assessment!$G:$G,$A64)) | F64: =IF($A64="","",INDEX(Assessment!$H:$H,$A64)) | G64: =IF($A64="","",INDEX(Assessment!$I:$I,$A64))
A65: =IFERROR(MATCH(61,Assessment!$M:$M,0),"") | B65: =IF($A65="","",INDEX(Assessment!$B:$B,$A65)) | C65: =IF($A65="","",INDEX(Assessment!$D:$D,$A65)) | D65: =IF($A65="","",INDEX(Assessment!$E:$E,$A65)) | E65: =IF($A65="","",INDEX(Assessment!$G:$G,$A65)) | F65: =IF($A65="","",INDEX(Assessment!$H:$H,$A65)) | G65: =IF($A65="","",INDEX(Assessment!$I:$I,$A65))
A66: =IFERROR(MATCH(62,Assessment!$M:$M,0),"") | B66: =IF($A66="","",INDEX(Assessment!$B:$B,$A66)) | C66: =IF($A66="","",INDEX(Assessment!$D:$D,$A66)) | D66: =IF($A66="","",INDEX(Assessment!$E:$E,$A66)) | E66: =IF($A66="","",INDEX(Assessment!$G:$G,$A66)) | F66: =IF($A66="","",INDEX(Assessment!$H:$H,$A66)) | G66: =IF($A66="","",INDEX(Assessment!$I:$I,$A66))
A67: =IFERROR(MATCH(63,Assessment!$M:$M,0),"") | B67: =IF($A67="","",INDEX(Assessment!$B:$B,$A67)) | C67: =IF($A67="","",INDEX(Assessment!$D:$D,$A67)) | D67: =IF($A67="","",INDEX(Assessment!$E:$E,$A67)) | E67: =IF($A67="","",INDEX(Assessment!$G:$G,$A67)) | F67: =IF($A67="","",INDEX(Assessment!$H:$H,$A67)) | G67: =IF($A67="","",INDEX(Assessment!$I:$I,$A67))
A68: =IFERROR(MATCH(64,Assessment!$M:$M,0),"") | B68: =IF($A68="","",INDEX(Assessment!$B:$B,$A68)) | C68: =IF($A68="","",INDEX(Assessment!$D:$D,$A68)) | D68: =IF($A68="","",INDEX(Assessment!$E:$E,$A68)) | E68: =IF($A68="","",INDEX(Assessment!$G:$G,$A68)) | F68: =IF($A68="","",INDEX(Assessment!$H:$H,$A68)) | G68: =IF($A68="","",INDEX(Assessment!$I:$I,$A68))
A69: =IFERROR(MATCH(65,Assessment!$M:$M,0),"") | B69: =IF($A69="","",INDEX(Assessment!$B:$B,$A69)) | C69: =IF($A69="","",INDEX(Assessment!$D:$D,$A69)) | D69: =IF($A69="","",INDEX(Assessment!$E:$E,$A69)) | E69: =IF($A69="","",INDEX(Assessment!$G:$G,$A69)) | F69: =IF($A69="","",INDEX(Assessment!$H:$H,$A69)) | G69: =IF($A69="","",INDEX(Assessment!$I:$I,$A69))
A70: =IFERROR(MATCH(66,Assessment!$M:$M,0),"") | B70: =IF($A70="","",INDEX(Assessment!$B:$B,$A70)) | C70: =IF($A70="","",INDEX(Assessment!$D:$D,$A70)) | D70: =IF($A70="","",INDEX(Assessment!$E:$E,$A70)) | E70: =IF($A70="","",INDEX(Assessment!$G:$G,$A70)) | F70: =IF($A70="","",INDEX(Assessment!$H:$H,$A70)) | G70: =IF($A70="","",INDEX(Assessment!$I:$I,$A70))
A71: =IFERROR(MATCH(67,Assessment!$M:$M,0),"") | B71: =IF($A71="","",INDEX(Assessment!$B:$B,$A71)) | C71: =IF($A71="","",INDEX(Assessment!$D:$D,$A71)) | D71: =IF($A71="","",INDEX(Assessment!$E:$E,$A71)) | E71: =IF($A71="","",INDEX(Assessment!$G:$G,$A71)) | F71: =IF($A71="","",INDEX(Assessment!$H:$H,$A71)) | G71: =IF($A71="","",INDEX(Assessment!$I:$I,$A71))
A72: =IFERROR(MATCH(68,Assessment!$M:$M,0),"") | B72: =IF($A72="","",INDEX(Assessment!$B:$B,$A72)) | C72: =IF($A72="","",INDEX(Assessment!$D:$D,$A72)) | D72: =IF($A72="","",INDEX(Assessment!$E:$E,$A72)) | E72: =IF($A72="","",INDEX(Assessment!$G:$G,$A72)) | F72: =IF($A72="","",INDEX(Assessment!$H:$H,$A72)) | G72: =IF($A72="","",INDEX(Assessment!$I:$I,$A72))
A73: =IFERROR(MATCH(69,Assessment!$M:$M,0),"") | B73: =IF($A73="","",INDEX(Assessment!$B:$B,$A73)) | C73: =IF($A73="","",INDEX(Assessment!$D:$D,$A73)) | D73: =IF($A73="","",INDEX(Assessment!$E:$E,$A73)) | E73: =IF($A73="","",INDEX(Assessment!$G:$G,$A73)) | F73: =IF($A73="","",INDEX(Assessment!$H:$H,$A73)) | G73: =IF($A73="","",INDEX(Assessment!$I:$I,$A73))
A74: =IFERROR(MATCH(70,Assessment!$M:$M,0),"") | B74: =IF($A74="","",INDEX(Assessment!$B:$B,$A74)) | C74: =IF($A74="","",INDEX(Assessment!$D:$D,$A74)) | D74: =IF($A74="","",INDEX(Assessment!$E:$E,$A74)) | E74: =IF($A74="","",INDEX(Assessment!$G:$G,$A74)) | F74: =IF($A74="","",INDEX(Assessment!$H:$H,$A74)) | G74: =IF($A74="","",INDEX(Assessment!$I:$I,$A74))
A75: =IFERROR(MATCH(71,Assessment!$M:$M,0),"") | B75: =IF($A75="","",INDEX(Assessment!$B:$B,$A75)) | C75: =IF($A75="","",INDEX(Assessment!$D:$D,$A75)) | D75: =IF($A75="","",INDEX(Assessment!$E:$E,$A75)) | E75: =IF($A75="","",INDEX(Assessment!$G:$G,$A75)) | F75: =IF($A75="","",INDEX(Assessment!$H:$H,$A75)) | G75: =IF($A75="","",INDEX(Assessment!$I:$I,$A75))
A76: =IFERROR(MATCH(72,Assessment!$M:$M,0),"") | B76: =IF($A76="","",INDEX(Assessment!$B:$B,$A76)) | C76: =IF($A76="","",INDEX(Assessment!$D:$D,$A76)) | D76: =IF($A76="","",INDEX(Assessment!$E:$E,$A76)) | E76: =IF($A76="","",INDEX(Assessment!$G:$G,$A76)) | F76: =IF($A76="","",INDEX(Assessment!$H:$H,$A76)) | G76: =IF($A76="","",INDEX(Assessment!$I:$I,$A76))
A77: =IFERROR(MATCH(73,Assessment!$M:$M,0),"") | B77: =IF($A77="","",INDEX(Assessment!$B:$B,$A77)) | C77: =IF($A77="","",INDEX(Assessment!$D:$D,$A77)) | D77: =IF($A77="","",INDEX(Assessment!$E:$E,$A77)) | E77: =IF($A77="","",INDEX(Assessment!$G:$G,$A77)) | F77: =IF($A77="","",INDEX(Assessment!$H:$H,$A77)) | G77: =IF($A77="","",INDEX(Assessment!$I:$I,$A77))
A78: =IFERROR(MATCH(74,Assessment!$M:$M,0),"") | B78: =IF($A78="","",INDEX(Assessment!$B:$B,$A78)) | C78: =IF($A78="","",INDEX(Assessment!$D:$D,$A78)) | D78: =IF($A78="","",INDEX(Assessment!$E:$E,$A78)) | E78: =IF($A78="","",INDEX(Assessment!$G:$G,$A78)) | F78: =IF($A78="","",INDEX(Assessment!$H:$H,$A78)) | G78: =IF($A78="","",INDEX(Assessment!$I:$I,$A78))
A79: =IFERROR(MATCH(75,Assessment!$M:$M,0),"") | B79: =IF($A79="","",INDEX(Assessment!$B:$B,$A79)) | C79: =IF($A79="","",INDEX(Assessment!$D:$D,$A79)) | D79: =IF($A79="","",INDEX(Assessment!$E:$E,$A79)) | E79: =IF($A79="","",INDEX(Assessment!$G:$G,$A79)) | F79: =IF($A79="","",INDEX(Assessment!$H:$H,$A79)) | G79: =IF($A79="","",INDEX(Assessment!$I:$I,$A79))
A80: =IFERROR(MATCH(76,Assessment!$M:$M,0),"") | B80: =IF($A80="","",INDEX(Assessment!$B:$B,$A80)) | C80: =IF($A80="","",INDEX(Assessment!$D:$D,$A80)) | D80: =IF($A80="","",INDEX(Assessment!$E:$E,$A80)) | E80: =IF($A80="","",INDEX(Assessment!$G:$G,$A80)) | F80: =IF($A80="","",INDEX(Assessment!$H:$H,$A80)) | G80: =IF($A80="","",INDEX(Assessment!$I:$I,$A80))
A81: =IFERROR(MATCH(77,Assessment!$M:$M,0),"") | B81: =IF($A81="","",INDEX(Assessment!$B:$B,$A81)) | C81: =IF($A81="","",INDEX(Assessment!$D:$D,$A81)) | D81: =IF($A81="","",INDEX(Assessment!$E:$E,$A81)) | E81: =IF($A81="","",INDEX(Assessment!$G:$G,$A81)) | F81: =IF($A81="","",INDEX(Assessment!$H:$H,$A81)) | G81: =IF($A81="","",INDEX(Assessment!$I:$I,$A81))
A82: =IFERROR(MATCH(78,Assessment!$M:$M,0),"") | B82: =IF($A82="","",INDEX(Assessment!$B:$B,$A82)) | C82: =IF($A82="","",INDEX(Assessment!$D:$D,$A82)) | D82: =IF($A82="","",INDEX(Assessment!$E:$E,$A82)) | E82: =IF($A82="","",INDEX(Assessment!$G:$G,$A82)) | F82: =IF($A82="","",INDEX(Assessment!$H:$H,$A82)) | G82: =IF($A82="","",INDEX(Assessment!$I:$I,$A82))
A83: =IFERROR(MATCH(79,Assessment!$M:$M,0),"") | B83: =IF($A83="","",INDEX(Assessment!$B:$B,$A83)) | C83: =IF($A83="","",INDEX(Assessment!$D:$D,$A83)) | D83: =IF($A83="","",INDEX(Assessment!$E:$E,$A83)) | E83: =IF($A83="","",INDEX(Assessment!$G:$G,$A83)) | F83: =IF($A83="","",INDEX(Assessment!$H:$H,$A83)) | G83: =IF($A83="","",INDEX(Assessment!$I:$I,$A83))
A84: =IFERROR(MATCH(80,Assessment!$M:$M,0),"") | B84: =IF($A84="","",INDEX(Assessment!$B:$B,$A84)) | C84: =IF($A84="","",INDEX(Assessment!$D:$D,$A84)) | D84: =IF($A84="","",INDEX(Assessment!$E:$E,$A84)) | E84: =IF($A84="","",INDEX(Assessment!$G:$G,$A84)) | F84: =IF($A84="","",INDEX(Assessment!$H:$H,$A84)) | G84: =IF($A84="","",INDEX(Assessment!$I:$I,$A84))
A85: =IFERROR(MATCH(81,Assessment!$M:$M,0),"") | B85: =IF($A85="","",INDEX(Assessment!$B:$B,$A85)) | C85: =IF($A85="","",INDEX(Assessment!$D:$D,$A85)) | D85: =IF($A85="","",INDEX(Assessment!$E:$E,$A85)) | E85: =IF($A85="","",INDEX(Assessment!$G:$G,$A85)) | F85: =IF($A85="","",INDEX(Assessment!$H:$H,$A85)) | G85: =IF($A85="","",INDEX(Assessment!$I:$I,$A85))
A86: =IFERROR(MATCH(82,Assessment!$M:$M,0),"") | B86: =IF($A86="","",INDEX(Assessment!$B:$B,$A86)) | C86: =IF($A86="","",INDEX(Assessment!$D:$D,$A86)) | D86: =IF($A86="","",INDEX(Assessment!$E:$E,$A86)) | E86: =IF($A86="","",INDEX(Assessment!$G:$G,$A86)) | F86: =IF($A86="","",INDEX(Assessment!$H:$H,$A86)) | G86: =IF($A86="","",INDEX(Assessment!$I:$I,$A86))
A87: =IFERROR(MATCH(83,Assessment!$M:$M,0),"") | B87: =IF($A87="","",INDEX(Assessment!$B:$B,$A87)) | C87: =IF($A87="","",INDEX(Assessment!$D:$D,$A87)) | D87: =IF($A87="","",INDEX(Assessment!$E:$E,$A87)) | E87: =IF($A87="","",INDEX(Assessment!$G:$G,$A87)) | F87: =IF($A87="","",INDEX(Assessment!$H:$H,$A87)) | G87: =IF($A87="","",INDEX(Assessment!$I:$I,$A87))
A88: =IFERROR(MATCH(84,Assessment!$M:$M,0),"") | B88: =IF($A88="","",INDEX(Assessment!$B:$B,$A88)) | C88: =IF($A88="","",INDEX(Assessment!$D:$D,$A88)) | D88: =IF($A88="","",INDEX(Assessment!$E:$E,$A88)) | E88: =IF($A88="","",INDEX(Assessment!$G:$G,$A88)) | F88: =IF($A88="","",INDEX(Assessment!$H:$H,$A88)) | G88: =IF($A88="","",INDEX(Assessment!$I:$I,$A88))
A89: =IFERROR(MATCH(85,Assessment!$M:$M,0),"") | B89: =IF($A89="","",INDEX(Assessment!$B:$B,$A89)) | C89: =IF($A89="","",INDEX(Assessment!$D:$D,$A89)) | D89: =IF($A89="","",INDEX(Assessment!$E:$E,$A89)) | E89: =IF($A89="","",INDEX(Assessment!$G:$G,$A89)) | F89: =IF($A89="","",INDEX(Assessment!$H:$H,$A89)) | G89: =IF($A89="","",INDEX(Assessment!$I:$I,$A89))
A90: =IFERROR(MATCH(86,Assessment!$M:$M,0),"") | B90: =IF($A90="","",INDEX(Assessment!$B:$B,$A90)) | C90: =IF($A90="","",INDEX(Assessment!$D:$D,$A90)) | D90: =IF($A90="","",INDEX(Assessment!$E:$E,$A90)) | E90: =IF($A90="","",INDEX(Assessment!$G:$G,$A90)) | F90: =IF($A90="","",INDEX(Assessment!$H:$H,$A90)) | G90: =IF($A90="","",INDEX(Assessment!$I:$I,$A90))
A91: =IFERROR(MATCH(87,Assessment!$M:$M,0),"") | B91: =IF($A91="","",INDEX(Assessment!$B:$B,$A91)) | C91: =IF($A91="","",INDEX(Assessment!$D:$D,$A91)) | D91: =IF($A91="","",INDEX(Assessment!$E:$E,$A91)) | E91: =IF($A91="","",INDEX(Assessment!$G:$G,$A91)) | F91: =IF($A91="","",INDEX(Assessment!$H:$H,$A91)) | G91: =IF($A91="","",INDEX(Assessment!$I:$I,$A91))
A92: =IFERROR(MATCH(88,Assessment!$M:$M,0),"") | B92: =IF($A92="","",INDEX(Assessment!$B:$B,$A92)) | C92: =IF($A92="","",INDEX(Assessment!$D:$D,$A92)) | D92: =IF($A92="","",INDEX(Assessment!$E:$E,$A92)) | E92: =IF($A92="","",INDEX(Assessment!$G:$G,$A92)) | F92: =IF($A92="","",INDEX(Assessment!$H:$H,$A92)) | G92: =IF($A92="","",INDEX(Assessment!$I:$I,$A92))
A93: =IFERROR(MATCH(89,Assessment!$M:$M,0),"") | B93: =IF($A93="","",INDEX(Assessment!$B:$B,$A93)) | C93: =IF($A93="","",INDEX(Assessment!$D:$D,$A93)) | D93: =IF($A93="","",INDEX(Assessment!$E:$E,$A93)) | E93: =IF($A93="","",INDEX(Assessment!$G:$G,$A93)) | F93: =IF($A93="","",INDEX(Assessment!$H:$H,$A93)) | G93: =IF($A93="","",INDEX(Assessment!$I:$I,$A93))
A94: =IFERROR(MATCH(90,Assessment!$M:$M,0),"") | B94: =IF($A94="","",INDEX(Assessment!$B:$B,$A94)) | C94: =IF($A94="","",INDEX(Assessment!$D:$D,$A94)) | D94: =IF($A94="","",INDEX(Assessment!$E:$E,$A94)) | E94: =IF($A94="","",INDEX(Assessment!$G:$G,$A94)) | F94: =IF($A94="","",INDEX(Assessment!$H:$H,$A94)) | G94: =IF($A94="","",INDEX(Assessment!$I:$I,$A94))
A95: =IFERROR(MATCH(91,Assessment!$M:$M,0),"") | B95: =IF($A95="","",INDEX(Assessment!$B:$B,$A95)) | C95: =IF($A95="","",INDEX(Assessment!$D:$D,$A95)) | D95: =IF($A95="","",INDEX(Assessment!$E:$E,$A95)) | E95: =IF($A95="","",INDEX(Assessment!$G:$G,$A95)) | F95: =IF($A95="","",INDEX(Assessment!$H:$H,$A95)) | G95: =IF($A95="","",INDEX(Assessment!$I:$I,$A95))
A96: =IFERROR(MATCH(92,Assessment!$M:$M,0),"") | B96: =IF($A96="","",INDEX(Assessment!$B:$B,$A96)) | C96: =IF($A96="","",INDEX(Assessment!$D:$D,$A96)) | D96: =IF($A96="","",INDEX(Assessment!$E:$E,$A96)) | E96: =IF($A96="","",INDEX(Assessment!$G:$G,$A96)) | F96: =IF($A96="","",INDEX(Assessment!$H:$H,$A96)) | G96: =IF($A96="","",INDEX(Assessment!$I:$I,$A96))
A97: =IFERROR(MATCH(93,Assessment!$M:$M,0),"") | B97: =IF($A97="","",INDEX(Assessment!$B:$B,$A97)) | C97: =IF($A97="","",INDEX(Assessment!$D:$D,$A97)) | D97: =IF($A97="","",INDEX(Assessment!$E:$E,$A97)) | E97: =IF($A97="","",INDEX(Assessment!$G:$G,$A97)) | F97: =IF($A97="","",INDEX(Assessment!$H:$H,$A97)) | G97: =IF($A97="","",INDEX(Assessment!$I:$I,$A97))
A98: =IFERROR(MATCH(94,Assessment!$M:$M,0),"") | B98: =IF($A98="","",INDEX(Assessment!$B:$B,$A98)) | C98: =IF($A98="","",INDEX(Assessment!$D:$D,$A98)) | D98: =IF($A98="","",INDEX(Assessment!$E:$E,$A98)) | E98: =IF($A98="","",INDEX(Assessment!$G:$G,$A98)) | F98: =IF($A98="","",INDEX(Assessment!$H:$H,$A98)) | G98: =IF($A98="","",INDEX(Assessment!$I:$I,$A98))
A99: =IFERROR(MATCH(95,Assessment!$M:$M,0),"") | B99: =IF($A99="","",INDEX(Assessment!$B:$B,$A99)) | C99: =IF($A99="","",INDEX(Assessment!$D:$D,$A99)) | D99: =IF($A99="","",INDEX(Assessment!$E:$E,$A99)) | E99: =IF($A99="","",INDEX(Assessment!$G:$G,$A99)) | F99: =IF($A99="","",INDEX(Assessment!$H:$H,$A99)) | G99: =IF($A99="","",INDEX(Assessment!$I:$I,$A99))
A100: =IFERROR(MATCH(96,Assessment!$M:$M,0),"") | B100: =IF($A100="","",INDEX(Assessment!$B:$B,$A100)) | C100: =IF($A100="","",INDEX(Assessment!$D:$D,$A100)) | D100: =IF($A100="","",INDEX(Assessment!$E:$E,$A100)) | E100: =IF($A100="","",INDEX(Assessment!$G:$G,$A100)) | F100: =IF($A100="","",INDEX(Assessment!$H:$H,$A100)) | G100: =IF($A100="","",INDEX(Assessment!$I:$I,$A100))
A101: =IFERROR(MATCH(97,Assessment!$M:$M,0),"") | B101: =IF($A101="","",INDEX(Assessment!$B:$B,$A101)) | C101: =IF($A101="","",INDEX(Assessment!$D:$D,$A101)) | D101: =IF($A101="","",INDEX(Assessment!$E:$E,$A101)) | E101: =IF($A101="","",INDEX(Assessment!$G:$G,$A101)) | F101: =IF($A101="","",INDEX(Assessment!$H:$H,$A101)) | G101: =IF($A101="","",INDEX(Assessment!$I:$I,$A101))
...

Sheet Product Backlog (FB)
A1: PRODUCT BACKLOG (FB)
A3: Feature Gap items — TownSq genuinely cannot support these today. Column 'TownSq today' shows the current constraint. Assign P0–P3 priority. These drive the TownSq product roadmap.
A4: Row# | B4: Priority (P0–P3) | C4: Domain | D4: Capability | E4: Dimension | F4: Discovery Question | G4: Branch Answer (evidence) | H4: TownSq today (why it's a gap) | I4: Gap Description | J4: Effort Estimate | K4: Status
A5: =IFERROR(MATCH(1,Assessment!$N:$N,0),"") | B5: =IF($A5="","",INDEX(Assessment!$K:$K,$A5)) | C5: =IF($A5="","",INDEX(Assessment!$B:$B,$A5)) | D5: =IF($A5="","",INDEX(Assessment!$D:$D,$A5)) | E5: =IF($A5="","",INDEX(Assessment!$E:$E,$A5)) | F5: =IF($A5="","",INDEX(Assessment!$G:$G,$A5)) | G5: =IF($A5="","",INDEX(Assessment!$H:$H,$A5)) | H5: =IF($A5="","",INDEX(Assessment!$I:$I,$A5))
A6: =IFERROR(MATCH(2,Assessment!$N:$N,0),"") | B6: =IF($A6="","",INDEX(Assessment!$K:$K,$A6)) | C6: =IF($A6="","",INDEX(Assessment!$B:$B,$A6)) | D6: =IF($A6="","",INDEX(Assessment!$D:$D,$A6)) | E6: =IF($A6="","",INDEX(Assessment!$E:$E,$A6)) | F6: =IF($A6="","",INDEX(Assessment!$G:$G,$A6)) | G6: =IF($A6="","",INDEX(Assessment!$H:$H,$A6)) | H6: =IF($A6="","",INDEX(Assessment!$I:$I,$A6))
A7: =IFERROR(MATCH(3,Assessment!$N:$N,0),"") | B7: =IF($A7="","",INDEX(Assessment!$K:$K,$A7)) | C7: =IF($A7="","",INDEX(Assessment!$B:$B,$A7)) | D7: =IF($A7="","",INDEX(Assessment!$D:$D,$A7)) | E7: =IF($A7="","",INDEX(Assessment!$E:$E,$A7)) | F7: =IF($A7="","",INDEX(Assessment!$G:$G,$A7)) | G7: =IF($A7="","",INDEX(Assessment!$H:$H,$A7)) | H7: =IF($A7="","",INDEX(Assessment!$I:$I,$A7))
A8: =IFERROR(MATCH(4,Assessment!$N:$N,0),"") | B8: =IF($A8="","",INDEX(Assessment!$K:$K,$A8)) | C8: =IF($A8="","",INDEX(Assessment!$B:$B,$A8)) | D8: =IF($A8="","",INDEX(Assessment!$D:$D,$A8)) | E8: =IF($A8="","",INDEX(Assessment!$E:$E,$A8)) | F8: =IF($A8="","",INDEX(Assessment!$G:$G,$A8)) | G8: =IF($A8="","",INDEX(Assessment!$H:$H,$A8)) | H8: =IF($A8="","",INDEX(Assessment!$I:$I,$A8))
A9: =IFERROR(MATCH(5,Assessment!$N:$N,0),"") | B9: =IF($A9="","",INDEX(Assessment!$K:$K,$A9)) | C9: =IF($A9="","",INDEX(Assessment!$B:$B,$A9)) | D9: =IF($A9="","",INDEX(Assessment!$D:$D,$A9)) | E9: =IF($A9="","",INDEX(Assessment!$E:$E,$A9)) | F9: =IF($A9="","",INDEX(Assessment!$G:$G,$A9)) | G9: =IF($A9="","",INDEX(Assessment!$H:$H,$A9)) | H9: =IF($A9="","",INDEX(Assessment!$I:$I,$A9))
A10: =IFERROR(MATCH(6,Assessment!$N:$N,0),"") | B10: =IF($A10="","",INDEX(Assessment!$K:$K,$A10)) | C10: =IF($A10="","",INDEX(Assessment!$B:$B,$A10)) | D10: =IF($A10="","",INDEX(Assessment!$D:$D,$A10)) | E10: =IF($A10="","",INDEX(Assessment!$E:$E,$A10)) | F10: =IF($A10="","",INDEX(Assessment!$G:$G,$A10)) | G10: =IF($A10="","",INDEX(Assessment!$H:$H,$A10)) | H10: =IF($A10="","",INDEX(Assessment!$I:$I,$A10))
A11: =IFERROR(MATCH(7,Assessment!$N:$N,0),"") | B11: =IF($A11="","",INDEX(Assessment!$K:$K,$A11)) | C11: =IF($A11="","",INDEX(Assessment!$B:$B,$A11)) | D11: =IF($A11="","",INDEX(Assessment!$D:$D,$A11)) | E11: =IF($A11="","",INDEX(Assessment!$E:$E,$A11)) | F11: =IF($A11="","",INDEX(Assessment!$G:$G,$A11)) | G11: =IF($A11="","",INDEX(Assessment!$H:$H,$A11)) | H11: =IF($A11="","",INDEX(Assessment!$I:$I,$A11))
A12: =IFERROR(MATCH(8,Assessment!$N:$N,0),"") | B12: =IF($A12="","",INDEX(Assessment!$K:$K,$A12)) | C12: =IF($A12="","",INDEX(Assessment!$B:$B,$A12)) | D12: =IF($A12="","",INDEX(Assessment!$D:$D,$A12)) | E12: =IF($A12="","",INDEX(Assessment!$E:$E,$A12)) | F12: =IF($A12="","",INDEX(Assessment!$G:$G,$A12)) | G12: =IF($A12="","",INDEX(Assessment!$H:$H,$A12)) | H12: =IF($A12="","",INDEX(Assessment!$I:$I,$A12))
A13: =IFERROR(MATCH(9,Assessment!$N:$N,0),"") | B13: =IF($A13="","",INDEX(Assessment!$K:$K,$A13)) | C13: =IF($A13="","",INDEX(Assessment!$B:$B,$A13)) | D13: =IF($A13="","",INDEX(Assessment!$D:$D,$A13)) | E13: =IF($A13="","",INDEX(Assessment!$E:$E,$A13)) | F13: =IF($A13="","",INDEX(Assessment!$G:$G,$A13)) | G13: =IF($A13="","",INDEX(Assessment!$H:$H,$A13)) | H13: =IF($A13="","",INDEX(Assessment!$I:$I,$A13))
A14: =IFERROR(MATCH(10,Assessment!$N:$N,0),"") | B14: =IF($A14="","",INDEX(Assessment!$K:$K,$A14)) | C14: =IF($A14="","",INDEX(Assessment!$B:$B,$A14)) | D14: =IF($A14="","",INDEX(Assessment!$D:$D,$A14)) | E14: =IF($A14="","",INDEX(Assessment!$E:$E,$A14)) | F14: =IF($A14="","",INDEX(Assessment!$G:$G,$A14)) | G14: =IF($A14="","",INDEX(Assessment!$H:$H,$A14)) | H14: =IF($A14="","",INDEX(Assessment!$I:$I,$A14))
A15: =IFERROR(MATCH(11,Assessment!$N:$N,0),"") | B15: =IF($A15="","",INDEX(Assessment!$K:$K,$A15)) | C15: =IF($A15="","",INDEX(Assessment!$B:$B,$A15)) | D15: =IF($A15="","",INDEX(Assessment!$D:$D,$A15)) | E15: =IF($A15="","",INDEX(Assessment!$E:$E,$A15)) | F15: =IF($A15="","",INDEX(Assessment!$G:$G,$A15)) | G15: =IF($A15="","",INDEX(Assessment!$H:$H,$A15)) | H15: =IF($A15="","",INDEX(Assessment!$I:$I,$A15))
A16: =IFERROR(MATCH(12,Assessment!$N:$N,0),"") | B16: =IF($A16="","",INDEX(Assessment!$K:$K,$A16)) | C16: =IF($A16="","",INDEX(Assessment!$B:$B,$A16)) | D16: =IF($A16="","",INDEX(Assessment!$D:$D,$A16)) | E16: =IF($A16="","",INDEX(Assessment!$E:$E,$A16)) | F16: =IF($A16="","",INDEX(Assessment!$G:$G,$A16)) | G16: =IF($A16="","",INDEX(Assessment!$H:$H,$A16)) | H16: =IF($A16="","",INDEX(Assessment!$I:$I,$A16))
A17: =IFERROR(MATCH(13,Assessment!$N:$N,0),"") | B17: =IF($A17="","",INDEX(Assessment!$K:$K,$A17)) | C17: =IF($A17="","",INDEX(Assessment!$B:$B,$A17)) | D17: =IF($A17="","",INDEX(Assessment!$D:$D,$A17)) | E17: =IF($A17="","",INDEX(Assessment!$E:$E,$A17)) | F17: =IF($A17="","",INDEX(Assessment!$G:$G,$A17)) | G17: =IF($A17="","",INDEX(Assessment!$H:$H,$A17)) | H17: =IF($A17="","",INDEX(Assessment!$I:$I,$A17))
A18: =IFERROR(MATCH(14,Assessment!$N:$N,0),"") | B18: =IF($A18="","",INDEX(Assessment!$K:$K,$A18)) | C18: =IF($A18="","",INDEX(Assessment!$B:$B,$A18)) | D18: =IF($A18="","",INDEX(Assessment!$D:$D,$A18)) | E18: =IF($A18="","",INDEX(Assessment!$E:$E,$A18)) | F18: =IF($A18="","",INDEX(Assessment!$G:$G,$A18)) | G18: =IF($A18="","",INDEX(Assessment!$H:$H,$A18)) | H18: =IF($A18="","",INDEX(Assessment!$I:$I,$A18))
A19: =IFERROR(MATCH(15,Assessment!$N:$N,0),"") | B19: =IF($A19="","",INDEX(Assessment!$K:$K,$A19)) | C19: =IF($A19="","",INDEX(Assessment!$B:$B,$A19)) | D19: =IF($A19="","",INDEX(Assessment!$D:$D,$A19)) | E19: =IF($A19="","",INDEX(Assessment!$E:$E,$A19)) | F19: =IF($A19="","",INDEX(Assessment!$G:$G,$A19)) | G19: =IF($A19="","",INDEX(Assessment!$H:$H,$A19)) | H19: =IF($A19="","",INDEX(Assessment!$I:$I,$A19))
A20: =IFERROR(MATCH(16,Assessment!$N:$N,0),"") | B20: =IF($A20="","",INDEX(Assessment!$K:$K,$A20)) | C20: =IF($A20="","",INDEX(Assessment!$B:$B,$A20)) | D20: =IF($A20="","",INDEX(Assessment!$D:$D,$A20)) | E20: =IF($A20="","",INDEX(Assessment!$E:$E,$A20)) | F20: =IF($A20="","",INDEX(Assessment!$G:$G,$A20)) | G20: =IF($A20="","",INDEX(Assessment!$H:$H,$A20)) | H20: =IF($A20="","",INDEX(Assessment!$I:$I,$A20))
A21: =IFERROR(MATCH(17,Assessment!$N:$N,0),"") | B21: =IF($A21="","",INDEX(Assessment!$K:$K,$A21)) | C21: =IF($A21="","",INDEX(Assessment!$B:$B,$A21)) | D21: =IF($A21="","",INDEX(Assessment!$D:$D,$A21)) | E21: =IF($A21="","",INDEX(Assessment!$E:$E,$A21)) | F21: =IF($A21="","",INDEX(Assessment!$G:$G,$A21)) | G21: =IF($A21="","",INDEX(Assessment!$H:$H,$A21)) | H21: =IF($A21="","",INDEX(Assessment!$I:$I,$A21))
A22: =IFERROR(MATCH(18,Assessment!$N:$N,0),"") | B22: =IF($A22="","",INDEX(Assessment!$K:$K,$A22)) | C22: =IF($A22="","",INDEX(Assessment!$B:$B,$A22)) | D22: =IF($A22="","",INDEX(Assessment!$D:$D,$A22)) | E22: =IF($A22="","",INDEX(Assessment!$E:$E,$A22)) | F22: =IF($A22="","",INDEX(Assessment!$G:$G,$A22)) | G22: =IF($A22="","",INDEX(Assessment!$H:$H,$A22)) | H22: =IF($A22="","",INDEX(Assessment!$I:$I,$A22))
A23: =IFERROR(MATCH(19,Assessment!$N:$N,0),"") | B23: =IF($A23="","",INDEX(Assessment!$K:$K,$A23)) | C23: =IF($A23="","",INDEX(Assessment!$B:$B,$A23)) | D23: =IF($A23="","",INDEX(Assessment!$D:$D,$A23)) | E23: =IF($A23="","",INDEX(Assessment!$E:$E,$A23)) | F23: =IF($A23="","",INDEX(Assessment!$G:$G,$A23)) | G23: =IF($A23="","",INDEX(Assessment!$H:$H,$A23)) | H23: =IF($A23="","",INDEX(Assessment!$I:$I,$A23))
A24: =IFERROR(MATCH(20,Assessment!$N:$N,0),"") | B24: =IF($A24="","",INDEX(Assessment!$K:$K,$A24)) | C24: =IF($A24="","",INDEX(Assessment!$B:$B,$A24)) | D24: =IF($A24="","",INDEX(Assessment!$D:$D,$A24)) | E24: =IF($A24="","",INDEX(Assessment!$E:$E,$A24)) | F24: =IF($A24="","",INDEX(Assessment!$G:$G,$A24)) | G24: =IF($A24="","",INDEX(Assessment!$H:$H,$A24)) | H24: =IF($A24="","",INDEX(Assessment!$I:$I,$A24))
A25: =IFERROR(MATCH(21,Assessment!$N:$N,0),"") | B25: =IF($A25="","",INDEX(Assessment!$K:$K,$A25)) | C25: =IF($A25="","",INDEX(Assessment!$B:$B,$A25)) | D25: =IF($A25="","",INDEX(Assessment!$D:$D,$A25)) | E25: =IF($A25="","",INDEX(Assessment!$E:$E,$A25)) | F25: =IF($A25="","",INDEX(Assessment!$G:$G,$A25)) | G25: =IF($A25="","",INDEX(Assessment!$H:$H,$A25)) | H25: =IF($A25="","",INDEX(Assessment!$I:$I,$A25))
A26: =IFERROR(MATCH(22,Assessment!$N:$N,0),"") | B26: =IF($A26="","",INDEX(Assessment!$K:$K,$A26)) | C26: =IF($A26="","",INDEX(Assessment!$B:$B,$A26)) | D26: =IF($A26="","",INDEX(Assessment!$D:$D,$A26)) | E26: =IF($A26="","",INDEX(Assessment!$E:$E,$A26)) | F26: =IF($A26="","",INDEX(Assessment!$G:$G,$A26)) | G26: =IF($A26="","",INDEX(Assessment!$H:$H,$A26)) | H26: =IF($A26="","",INDEX(Assessment!$I:$I,$A26))
A27: =IFERROR(MATCH(23,Assessment!$N:$N,0),"") | B27: =IF($A27="","",INDEX(Assessment!$K:$K,$A27)) | C27: =IF($A27="","",INDEX(Assessment!$B:$B,$A27)) | D27: =IF($A27="","",INDEX(Assessment!$D:$D,$A27)) | E27: =IF($A27="","",INDEX(Assessment!$E:$E,$A27)) | F27: =IF($A27="","",INDEX(Assessment!$G:$G,$A27)) | G27: =IF($A27="","",INDEX(Assessment!$H:$H,$A27)) | H27: =IF($A27="","",INDEX(Assessment!$I:$I,$A27))
A28: =IFERROR(MATCH(24,Assessment!$N:$N,0),"") | B28: =IF($A28="","",INDEX(Assessment!$K:$K,$A28)) | C28: =IF($A28="","",INDEX(Assessment!$B:$B,$A28)) | D28: =IF($A28="","",INDEX(Assessment!$D:$D,$A28)) | E28: =IF($A28="","",INDEX(Assessment!$E:$E,$A28)) | F28: =IF($A28="","",INDEX(Assessment!$G:$G,$A28)) | G28: =IF($A28="","",INDEX(Assessment!$H:$H,$A28)) | H28: =IF($A28="","",INDEX(Assessment!$I:$I,$A28))
A29: =IFERROR(MATCH(25,Assessment!$N:$N,0),"") | B29: =IF($A29="","",INDEX(Assessment!$K:$K,$A29)) | C29: =IF($A29="","",INDEX(Assessment!$B:$B,$A29)) | D29: =IF($A29="","",INDEX(Assessment!$D:$D,$A29)) | E29: =IF($A29="","",INDEX(Assessment!$E:$E,$A29)) | F29: =IF($A29="","",INDEX(Assessment!$G:$G,$A29)) | G29: =IF($A29="","",INDEX(Assessment!$H:$H,$A29)) | H29: =IF($A29="","",INDEX(Assessment!$I:$I,$A29))
A30: =IFERROR(MATCH(26,Assessment!$N:$N,0),"") | B30: =IF($A30="","",INDEX(Assessment!$K:$K,$A30)) | C30: =IF($A30="","",INDEX(Assessment!$B:$B,$A30)) | D30: =IF($A30="","",INDEX(Assessment!$D:$D,$A30)) | E30: =IF($A30="","",INDEX(Assessment!$E:$E,$A30)) | F30: =IF($A30="","",INDEX(Assessment!$G:$G,$A30)) | G30: =IF($A30="","",INDEX(Assessment!$H:$H,$A30)) | H30: =IF($A30="","",INDEX(Assessment!$I:$I,$A30))
A31: =IFERROR(MATCH(27,Assessment!$N:$N,0),"") | B31: =IF($A31="","",INDEX(Assessment!$K:$K,$A31)) | C31: =IF($A31="","",INDEX(Assessment!$B:$B,$A31)) | D31: =IF($A31="","",INDEX(Assessment!$D:$D,$A31)) | E31: =IF($A31="","",INDEX(Assessment!$E:$E,$A31)) | F31: =IF($A31="","",INDEX(Assessment!$G:$G,$A31)) | G31: =IF($A31="","",INDEX(Assessment!$H:$H,$A31)) | H31: =IF($A31="","",INDEX(Assessment!$I:$I,$A31))
A32: =IFERROR(MATCH(28,Assessment!$N:$N,0),"") | B32: =IF($A32="","",INDEX(Assessment!$K:$K,$A32)) | C32: =IF($A32="","",INDEX(Assessment!$B:$B,$A32)) | D32: =IF($A32="","",INDEX(Assessment!$D:$D,$A32)) | E32: =IF($A32="","",INDEX(Assessment!$E:$E,$A32)) | F32: =IF($A32="","",INDEX(Assessment!$G:$G,$A32)) | G32: =IF($A32="","",INDEX(Assessment!$H:$H,$A32)) | H32: =IF($A32="","",INDEX(Assessment!$I:$I,$A32))
A33: =IFERROR(MATCH(29,Assessment!$N:$N,0),"") | B33: =IF($A33="","",INDEX(Assessment!$K:$K,$A33)) | C33: =IF($A33="","",INDEX(Assessment!$B:$B,$A33)) | D33: =IF($A33="","",INDEX(Assessment!$D:$D,$A33)) | E33: =IF($A33="","",INDEX(Assessment!$E:$E,$A33)) | F33: =IF($A33="","",INDEX(Assessment!$G:$G,$A33)) | G33: =IF($A33="","",INDEX(Assessment!$H:$H,$A33)) | H33: =IF($A33="","",INDEX(Assessment!$I:$I,$A33))
A34: =IFERROR(MATCH(30,Assessment!$N:$N,0),"") | B34: =IF($A34="","",INDEX(Assessment!$K:$K,$A34)) | C34: =IF($A34="","",INDEX(Assessment!$B:$B,$A34)) | D34: =IF($A34="","",INDEX(Assessment!$D:$D,$A34)) | E34: =IF($A34="","",INDEX(Assessment!$E:$E,$A34)) | F34: =IF($A34="","",INDEX(Assessment!$G:$G,$A34)) | G34: =IF($A34="","",INDEX(Assessment!$H:$H,$A34)) | H34: =IF($A34="","",INDEX(Assessment!$I:$I,$A34))
A35: =IFERROR(MATCH(31,Assessment!$N:$N,0),"") | B35: =IF($A35="","",INDEX(Assessment!$K:$K,$A35)) | C35: =IF($A35="","",INDEX(Assessment!$B:$B,$A35)) | D35: =IF($A35="","",INDEX(Assessment!$D:$D,$A35)) | E35: =IF($A35="","",INDEX(Assessment!$E:$E,$A35)) | F35: =IF($A35="","",INDEX(Assessment!$G:$G,$A35)) | G35: =IF($A35="","",INDEX(Assessment!$H:$H,$A35)) | H35: =IF($A35="","",INDEX(Assessment!$I:$I,$A35))
A36: =IFERROR(MATCH(32,Assessment!$N:$N,0),"") | B36: =IF($A36="","",INDEX(Assessment!$K:$K,$A36)) | C36: =IF($A36="","",INDEX(Assessment!$B:$B,$A36)) | D36: =IF($A36="","",INDEX(Assessment!$D:$D,$A36)) | E36: =IF($A36="","",INDEX(Assessment!$E:$E,$A36)) | F36: =IF($A36="","",INDEX(Assessment!$G:$G,$A36)) | G36: =IF($A36="","",INDEX(Assessment!$H:$H,$A36)) | H36: =IF($A36="","",INDEX(Assessment!$I:$I,$A36))
A37: =IFERROR(MATCH(33,Assessment!$N:$N,0),"") | B37: =IF($A37="","",INDEX(Assessment!$K:$K,$A37)) | C37: =IF($A37="","",INDEX(Assessment!$B:$B,$A37)) | D37: =IF($A37="","",INDEX(Assessment!$D:$D,$A37)) | E37: =IF($A37="","",INDEX(Assessment!$E:$E,$A37)) | F37: =IF($A37="","",INDEX(Assessment!$G:$G,$A37)) | G37: =IF($A37="","",INDEX(Assessment!$H:$H,$A37)) | H37: =IF($A37="","",INDEX(Assessment!$I:$I,$A37))
A38: =IFERROR(MATCH(34,Assessment!$N:$N,0),"") | B38: =IF($A38="","",INDEX(Assessment!$K:$K,$A38)) | C38: =IF($A38="","",INDEX(Assessment!$B:$B,$A38)) | D38: =IF($A38="","",INDEX(Assessment!$D:$D,$A38)) | E38: =IF($A38="","",INDEX(Assessment!$E:$E,$A38)) | F38: =IF($A38="","",INDEX(Assessment!$G:$G,$A38)) | G38: =IF($A38="","",INDEX(Assessment!$H:$H,$A38)) | H38: =IF($A38="","",INDEX(Assessment!$I:$I,$A38))
A39: =IFERROR(MATCH(35,Assessment!$N:$N,0),"") | B39: =IF($A39="","",INDEX(Assessment!$K:$K,$A39)) | C39: =IF($A39="","",INDEX(Assessment!$B:$B,$A39)) | D39: =IF($A39="","",INDEX(Assessment!$D:$D,$A39)) | E39: =IF($A39="","",INDEX(Assessment!$E:$E,$A39)) | F39: =IF($A39="","",INDEX(Assessment!$G:$G,$A39)) | G39: =IF($A39="","",INDEX(Assessment!$H:$H,$A39)) | H39: =IF($A39="","",INDEX(Assessment!$I:$I,$A39))
A40: =IFERROR(MATCH(36,Assessment!$N:$N,0),"") | B40: =IF($A40="","",INDEX(Assessment!$K:$K,$A40)) | C40: =IF($A40="","",INDEX(Assessment!$B:$B,$A40)) | D40: =IF($A40="","",INDEX(Assessment!$D:$D,$A40)) | E40: =IF($A40="","",INDEX(Assessment!$E:$E,$A40)) | F40: =IF($A40="","",INDEX(Assessment!$G:$G,$A40)) | G40: =IF($A40="","",INDEX(Assessment!$H:$H,$A40)) | H40: =IF($A40="","",INDEX(Assessment!$I:$I,$A40))
A41: =IFERROR(MATCH(37,Assessment!$N:$N,0),"") | B41: =IF($A41="","",INDEX(Assessment!$K:$K,$A41)) | C41: =IF($A41="","",INDEX(Assessment!$B:$B,$A41)) | D41: =IF($A41="","",INDEX(Assessment!$D:$D,$A41)) | E41: =IF($A41="","",INDEX(Assessment!$E:$E,$A41)) | F41: =IF($A41="","",INDEX(Assessment!$G:$G,$A41)) | G41: =IF($A41="","",INDEX(Assessment!$H:$H,$A41)) | H41: =IF($A41="","",INDEX(Assessment!$I:$I,$A41))
A42: =IFERROR(MATCH(38,Assessment!$N:$N,0),"") | B42: =IF($A42="","",INDEX(Assessment!$K:$K,$A42)) | C42: =IF($A42="","",INDEX(Assessment!$B:$B,$A42)) | D42: =IF($A42="","",INDEX(Assessment!$D:$D,$A42)) | E42: =IF($A42="","",INDEX(Assessment!$E:$E,$A42)) | F42: =IF($A42="","",INDEX(Assessment!$G:$G,$A42)) | G42: =IF($A42="","",INDEX(Assessment!$H:$H,$A42)) | H42: =IF($A42="","",INDEX(Assessment!$I:$I,$A42))
A43: =IFERROR(MATCH(39,Assessment!$N:$N,0),"") | B43: =IF($A43="","",INDEX(Assessment!$K:$K,$A43)) | C43: =IF($A43="","",INDEX(Assessment!$B:$B,$A43)) | D43: =IF($A43="","",INDEX(Assessment!$D:$D,$A43)) | E43: =IF($A43="","",INDEX(Assessment!$E:$E,$A43)) | F43: =IF($A43="","",INDEX(Assessment!$G:$G,$A43)) | G43: =IF($A43="","",INDEX(Assessment!$H:$H,$A43)) | H43: =IF($A43="","",INDEX(Assessment!$I:$I,$A43))
A44: =IFERROR(MATCH(40,Assessment!$N:$N,0),"") | B44: =IF($A44="","",INDEX(Assessment!$K:$K,$A44)) | C44: =IF($A44="","",INDEX(Assessment!$B:$B,$A44)) | D44: =IF($A44="","",INDEX(Assessment!$D:$D,$A44)) | E44: =IF($A44="","",INDEX(Assessment!$E:$E,$A44)) | F44: =IF($A44="","",INDEX(Assessment!$G:$G,$A44)) | G44: =IF($A44="","",INDEX(Assessment!$H:$H,$A44)) | H44: =IF($A44="","",INDEX(Assessment!$I:$I,$A44))
A45: =IFERROR(MATCH(41,Assessment!$N:$N,0),"") | B45: =IF($A45="","",INDEX(Assessment!$K:$K,$A45)) | C45: =IF($A45="","",INDEX(Assessment!$B:$B,$A45)) | D45: =IF($A45="","",INDEX(Assessment!$D:$D,$A45)) | E45: =IF($A45="","",INDEX(Assessment!$E:$E,$A45)) | F45: =IF($A45="","",INDEX(Assessment!$G:$G,$A45)) | G45: =IF($A45="","",INDEX(Assessment!$H:$H,$A45)) | H45: =IF($A45="","",INDEX(Assessment!$I:$I,$A45))
A46: =IFERROR(MATCH(42,Assessment!$N:$N,0),"") | B46: =IF($A46="","",INDEX(Assessment!$K:$K,$A46)) | C46: =IF($A46="","",INDEX(Assessment!$B:$B,$A46)) | D46: =IF($A46="","",INDEX(Assessment!$D:$D,$A46)) | E46: =IF($A46="","",INDEX(Assessment!$E:$E,$A46)) | F46: =IF($A46="","",INDEX(Assessment!$G:$G,$A46)) | G46: =IF($A46="","",INDEX(Assessment!$H:$H,$A46)) | H46: =IF($A46="","",INDEX(Assessment!$I:$I,$A46))
A47: =IFERROR(MATCH(43,Assessment!$N:$N,0),"") | B47: =IF($A47="","",INDEX(Assessment!$K:$K,$A47)) | C47: =IF($A47="","",INDEX(Assessment!$B:$B,$A47)) | D47: =IF($A47="","",INDEX(Assessment!$D:$D,$A47)) | E47: =IF($A47="","",INDEX(Assessment!$E:$E,$A47)) | F47: =IF($A47="","",INDEX(Assessment!$G:$G,$A47)) | G47: =IF($A47="","",INDEX(Assessment!$H:$H,$A47)) | H47: =IF($A47="","",INDEX(Assessment!$I:$I,$A47))
A48: =IFERROR(MATCH(44,Assessment!$N:$N,0),"") | B48: =IF($A48="","",INDEX(Assessment!$K:$K,$A48)) | C48: =IF($A48="","",INDEX(Assessment!$B:$B,$A48)) | D48: =IF($A48="","",INDEX(Assessment!$D:$D,$A48)) | E48: =IF($A48="","",INDEX(Assessment!$E:$E,$A48)) | F48: =IF($A48="","",INDEX(Assessment!$G:$G,$A48)) | G48: =IF($A48="","",INDEX(Assessment!$H:$H,$A48)) | H48: =IF($A48="","",INDEX(Assessment!$I:$I,$A48))
A49: =IFERROR(MATCH(45,Assessment!$N:$N,0),"") | B49: =IF($A49="","",INDEX(Assessment!$K:$K,$A49)) | C49: =IF($A49="","",INDEX(Assessment!$B:$B,$A49)) | D49: =IF($A49="","",INDEX(Assessment!$D:$D,$A49)) | E49: =IF($A49="","",INDEX(Assessment!$E:$E,$A49)) | F49: =IF($A49="","",INDEX(Assessment!$G:$G,$A49)) | G49: =IF($A49="","",INDEX(Assessment!$H:$H,$A49)) | H49: =IF($A49="","",INDEX(Assessment!$I:$I,$A49))
A50: =IFERROR(MATCH(46,Assessment!$N:$N,0),"") | B50: =IF($A50="","",INDEX(Assessment!$K:$K,$A50)) | C50: =IF($A50="","",INDEX(Assessment!$B:$B,$A50)) | D50: =IF($A50="","",INDEX(Assessment!$D:$D,$A50)) | E50: =IF($A50="","",INDEX(Assessment!$E:$E,$A50)) | F50: =IF($A50="","",INDEX(Assessment!$G:$G,$A50)) | G50: =IF($A50="","",INDEX(Assessment!$H:$H,$A50)) | H50: =IF($A50="","",INDEX(Assessment!$I:$I,$A50))
A51: =IFERROR(MATCH(47,Assessment!$N:$N,0),"") | B51: =IF($A51="","",INDEX(Assessment!$K:$K,$A51)) | C51: =IF($A51="","",INDEX(Assessment!$B:$B,$A51)) | D51: =IF($A51="","",INDEX(Assessment!$D:$D,$A51)) | E51: =IF($A51="","",INDEX(Assessment!$E:$E,$A51)) | F51: =IF($A51="","",INDEX(Assessment!$G:$G,$A51)) | G51: =IF($A51="","",INDEX(Assessment!$H:$H,$A51)) | H51: =IF($A51="","",INDEX(Assessment!$I:$I,$A51))
A52: =IFERROR(MATCH(48,Assessment!$N:$N,0),"") | B52: =IF($A52="","",INDEX(Assessment!$K:$K,$A52)) | C52: =IF($A52="","",INDEX(Assessment!$B:$B,$A52)) | D52: =IF($A52="","",INDEX(Assessment!$D:$D,$A52)) | E52: =IF($A52="","",INDEX(Assessment!$E:$E,$A52)) | F52: =IF($A52="","",INDEX(Assessment!$G:$G,$A52)) | G52: =IF($A52="","",INDEX(Assessment!$H:$H,$A52)) | H52: =IF($A52="","",INDEX(Assessment!$I:$I,$A52))
A53: =IFERROR(MATCH(49,Assessment!$N:$N,0),"") | B53: =IF($A53="","",INDEX(Assessment!$K:$K,$A53)) | C53: =IF($A53="","",INDEX(Assessment!$B:$B,$A53)) | D53: =IF($A53="","",INDEX(Assessment!$D:$D,$A53)) | E53: =IF($A53="","",INDEX(Assessment!$E:$E,$A53)) | F53: =IF($A53="","",INDEX(Assessment!$G:$G,$A53)) | G53: =IF($A53="","",INDEX(Assessment!$H:$H,$A53)) | H53: =IF($A53="","",INDEX(Assessment!$I:$I,$A53))
A54: =IFERROR(MATCH(50,Assessment!$N:$N,0),"") | B54: =IF($A54="","",INDEX(Assessment!$K:$K,$A54)) | C54: =IF($A54="","",INDEX(Assessment!$B:$B,$A54)) | D54: =IF($A54="","",INDEX(Assessment!$D:$D,$A54)) | E54: =IF($A54="","",INDEX(Assessment!$E:$E,$A54)) | F54: =IF($A54="","",INDEX(Assessment!$G:$G,$A54)) | G54: =IF($A54="","",INDEX(Assessment!$H:$H,$A54)) | H54: =IF($A54="","",INDEX(Assessment!$I:$I,$A54))
A55: =IFERROR(MATCH(51,Assessment!$N:$N,0),"") | B55: =IF($A55="","",INDEX(Assessment!$K:$K,$A55)) | C55: =IF($A55="","",INDEX(Assessment!$B:$B,$A55)) | D55: =IF($A55="","",INDEX(Assessment!$D:$D,$A55)) | E55: =IF($A55="","",INDEX(Assessment!$E:$E,$A55)) | F55: =IF($A55="","",INDEX(Assessment!$G:$G,$A55)) | G55: =IF($A55="","",INDEX(Assessment!$H:$H,$A55)) | H55: =IF($A55="","",INDEX(Assessment!$I:$I,$A55))
A56: =IFERROR(MATCH(52,Assessment!$N:$N,0),"") | B56: =IF($A56="","",INDEX(Assessment!$K:$K,$A56)) | C56: =IF($A56="","",INDEX(Assessment!$B:$B,$A56)) | D56: =IF($A56="","",INDEX(Assessment!$D:$D,$A56)) | E56: =IF($A56="","",INDEX(Assessment!$E:$E,$A56)) | F56: =IF($A56="","",INDEX(Assessment!$G:$G,$A56)) | G56: =IF($A56="","",INDEX(Assessment!$H:$H,$A56)) | H56: =IF($A56="","",INDEX(Assessment!$I:$I,$A56))
A57: =IFERROR(MATCH(53,Assessment!$N:$N,0),"") | B57: =IF($A57="","",INDEX(Assessment!$K:$K,$A57)) | C57: =IF($A57="","",INDEX(Assessment!$B:$B,$A57)) | D57: =IF($A57="","",INDEX(Assessment!$D:$D,$A57)) | E57: =IF($A57="","",INDEX(Assessment!$E:$E,$A57)) | F57: =IF($A57="","",INDEX(Assessment!$G:$G,$A57)) | G57: =IF($A57="","",INDEX(Assessment!$H:$H,$A57)) | H57: =IF($A57="","",INDEX(Assessment!$I:$I,$A57))
A58: =IFERROR(MATCH(54,Assessment!$N:$N,0),"") | B58: =IF($A58="","",INDEX(Assessment!$K:$K,$A58)) | C58: =IF($A58="","",INDEX(Assessment!$B:$B,$A58)) | D58: =IF($A58="","",INDEX(Assessment!$D:$D,$A58)) | E58: =IF($A58="","",INDEX(Assessment!$E:$E,$A58)) | F58: =IF($A58="","",INDEX(Assessment!$G:$G,$A58)) | G58: =IF($A58="","",INDEX(Assessment!$H:$H,$A58)) | H58: =IF($A58="","",INDEX(Assessment!$I:$I,$A58))
A59: =IFERROR(MATCH(55,Assessment!$N:$N,0),"") | B59: =IF($A59="","",INDEX(Assessment!$K:$K,$A59)) | C59: =IF($A59="","",INDEX(Assessment!$B:$B,$A59)) | D59: =IF($A59="","",INDEX(Assessment!$D:$D,$A59)) | E59: =IF($A59="","",INDEX(Assessment!$E:$E,$A59)) | F59: =IF($A59="","",INDEX(Assessment!$G:$G,$A59)) | G59: =IF($A59="","",INDEX(Assessment!$H:$H,$A59)) | H59: =IF($A59="","",INDEX(Assessment!$I:$I,$A59))
A60: =IFERROR(MATCH(56,Assessment!$N:$N,0),"") | B60: =IF($A60="","",INDEX(Assessment!$K:$K,$A60)) | C60: =IF($A60="","",INDEX(Assessment!$B:$B,$A60)) | D60: =IF($A60="","",INDEX(Assessment!$D:$D,$A60)) | E60: =IF($A60="","",INDEX(Assessment!$E:$E,$A60)) | F60: =IF($A60="","",INDEX(Assessment!$G:$G,$A60)) | G60: =IF($A60="","",INDEX(Assessment!$H:$H,$A60)) | H60: =IF($A60="","",INDEX(Assessment!$I:$I,$A60))
A61: =IFERROR(MATCH(57,Assessment!$N:$N,0),"") | B61: =IF($A61="","",INDEX(Assessment!$K:$K,$A61)) | C61: =IF($A61="","",INDEX(Assessment!$B:$B,$A61)) | D61: =IF($A61="","",INDEX(Assessment!$D:$D,$A61)) | E61: =IF($A61="","",INDEX(Assessment!$E:$E,$A61)) | F61: =IF($A61="","",INDEX(Assessment!$G:$G,$A61)) | G61: =IF($A61="","",INDEX(Assessment!$H:$H,$A61)) | H61: =IF($A61="","",INDEX(Assessment!$I:$I,$A61))
A62: =IFERROR(MATCH(58,Assessment!$N:$N,0),"") | B62: =IF($A62="","",INDEX(Assessment!$K:$K,$A62)) | C62: =IF($A62="","",INDEX(Assessment!$B:$B,$A62)) | D62: =IF($A62="","",INDEX(Assessment!$D:$D,$A62)) | E62: =IF($A62="","",INDEX(Assessment!$E:$E,$A62)) | F62: =IF($A62="","",INDEX(Assessment!$G:$G,$A62)) | G62: =IF($A62="","",INDEX(Assessment!$H:$H,$A62)) | H62: =IF($A62="","",INDEX(Assessment!$I:$I,$A62))
A63: =IFERROR(MATCH(59,Assessment!$N:$N,0),"") | B63: =IF($A63="","",INDEX(Assessment!$K:$K,$A63)) | C63: =IF($A63="","",INDEX(Assessment!$B:$B,$A63)) | D63: =IF($A63="","",INDEX(Assessment!$D:$D,$A63)) | E63: =IF($A63="","",INDEX(Assessment!$E:$E,$A63)) | F63: =IF($A63="","",INDEX(Assessment!$G:$G,$A63)) | G63: =IF($A63="","",INDEX(Assessment!$H:$H,$A63)) | H63: =IF($A63="","",INDEX(Assessment!$I:$I,$A63))
A64: =IFERROR(MATCH(60,Assessment!$N:$N,0),"") | B64: =IF($A64="","",INDEX(Assessment!$K:$K,$A64)) | C64: =IF($A64="","",INDEX(Assessment!$B:$B,$A64)) | D64: =IF($A64="","",INDEX(Assessment!$D:$D,$A64)) | E64: =IF($A64="","",INDEX(Assessment!$E:$E,$A64)) | F64: =IF($A64="","",INDEX(Assessment!$G:$G,$A64)) | G64: =IF($A64="","",INDEX(Assessment!$H:$H,$A64)) | H64: =IF($A64="","",INDEX(Assessment!$I:$I,$A64))
A65: =IFERROR(MATCH(61,Assessment!$N:$N,0),"") | B65: =IF($A65="","",INDEX(Assessment!$K:$K,$A65)) | C65: =IF($A65="","",INDEX(Assessment!$B:$B,$A65)) | D65: =IF($A65="","",INDEX(Assessment!$D:$D,$A65)) | E65: =IF($A65="","",INDEX(Assessment!$E:$E,$A65)) | F65: =IF($A65="","",INDEX(Assessment!$G:$G,$A65)) | G65: =IF($A65="","",INDEX(Assessment!$H:$H,$A65)) | H65: =IF($A65="","",INDEX(Assessment!$I:$I,$A65))
A66: =IFERROR(MATCH(62,Assessment!$N:$N,0),"") | B66: =IF($A66="","",INDEX(Assessment!$K:$K,$A66)) | C66: =IF($A66="","",INDEX(Assessment!$B:$B,$A66)) | D66: =IF($A66="","",INDEX(Assessment!$D:$D,$A66)) | E66: =IF($A66="","",INDEX(Assessment!$E:$E,$A66)) | F66: =IF($A66="","",INDEX(Assessment!$G:$G,$A66)) | G66: =IF($A66="","",INDEX(Assessment!$H:$H,$A66)) | H66: =IF($A66="","",INDEX(Assessment!$I:$I,$A66))
A67: =IFERROR(MATCH(63,Assessment!$N:$N,0),"") | B67: =IF($A67="","",INDEX(Assessment!$K:$K,$A67)) | C67: =IF($A67="","",INDEX(Assessment!$B:$B,$A67)) | D67: =IF($A67="","",INDEX(Assessment!$D:$D,$A67)) | E67: =IF($A67="","",INDEX(Assessment!$E:$E,$A67)) | F67: =IF($A67="","",INDEX(Assessment!$G:$G,$A67)) | G67: =IF($A67="","",INDEX(Assessment!$H:$H,$A67)) | H67: =IF($A67="","",INDEX(Assessment!$I:$I,$A67))
A68: =IFERROR(MATCH(64,Assessment!$N:$N,0),"") | B68: =IF($A68="","",INDEX(Assessment!$K:$K,$A68)) | C68: =IF($A68="","",INDEX(Assessment!$B:$B,$A68)) | D68: =IF($A68="","",INDEX(Assessment!$D:$D,$A68)) | E68: =IF($A68="","",INDEX(Assessment!$E:$E,$A68)) | F68: =IF($A68="","",INDEX(Assessment!$G:$G,$A68)) | G68: =IF($A68="","",INDEX(Assessment!$H:$H,$A68)) | H68: =IF($A68="","",INDEX(Assessment!$I:$I,$A68))
A69: =IFERROR(MATCH(65,Assessment!$N:$N,0),"") | B69: =IF($A69="","",INDEX(Assessment!$K:$K,$A69)) | C69: =IF($A69="","",INDEX(Assessment!$B:$B,$A69)) | D69: =IF($A69="","",INDEX(Assessment!$D:$D,$A69)) | E69: =IF($A69="","",INDEX(Assessment!$E:$E,$A69)) | F69: =IF($A69="","",INDEX(Assessment!$G:$G,$A69)) | G69: =IF($A69="","",INDEX(Assessment!$H:$H,$A69)) | H69: =IF($A69="","",INDEX(Assessment!$I:$I,$A69))
A70: =IFERROR(MATCH(66,Assessment!$N:$N,0),"") | B70: =IF($A70="","",INDEX(Assessment!$K:$K,$A70)) | C70: =IF($A70="","",INDEX(Assessment!$B:$B,$A70)) | D70: =IF($A70="","",INDEX(Assessment!$D:$D,$A70)) | E70: =IF($A70="","",INDEX(Assessment!$E:$E,$A70)) | F70: =IF($A70="","",INDEX(Assessment!$G:$G,$A70)) | G70: =IF($A70="","",INDEX(Assessment!$H:$H,$A70)) | H70: =IF($A70="","",INDEX(Assessment!$I:$I,$A70))
A71: =IFERROR(MATCH(67,Assessment!$N:$N,0),"") | B71: =IF($A71="","",INDEX(Assessment!$K:$K,$A71)) | C71: =IF($A71="","",INDEX(Assessment!$B:$B,$A71)) | D71: =IF($A71="","",INDEX(Assessment!$D:$D,$A71)) | E71: =IF($A71="","",INDEX(Assessment!$E:$E,$A71)) | F71: =IF($A71="","",INDEX(Assessment!$G:$G,$A71)) | G71: =IF($A71="","",INDEX(Assessment!$H:$H,$A71)) | H71: =IF($A71="","",INDEX(Assessment!$I:$I,$A71))
A72: =IFERROR(MATCH(68,Assessment!$N:$N,0),"") | B72: =IF($A72="","",INDEX(Assessment!$K:$K,$A72)) | C72: =IF($A72="","",INDEX(Assessment!$B:$B,$A72)) | D72: =IF($A72="","",INDEX(Assessment!$D:$D,$A72)) | E72: =IF($A72="","",INDEX(Assessment!$E:$E,$A72)) | F72: =IF($A72="","",INDEX(Assessment!$G:$G,$A72)) | G72: =IF($A72="","",INDEX(Assessment!$H:$H,$A72)) | H72: =IF($A72="","",INDEX(Assessment!$I:$I,$A72))
A73: =IFERROR(MATCH(69,Assessment!$N:$N,0),"") | B73: =IF($A73="","",INDEX(Assessment!$K:$K,$A73)) | C73: =IF($A73="","",INDEX(Assessment!$B:$B,$A73)) | D73: =IF($A73="","",INDEX(Assessment!$D:$D,$A73)) | E73: =IF($A73="","",INDEX(Assessment!$E:$E,$A73)) | F73: =IF($A73="","",INDEX(Assessment!$G:$G,$A73)) | G73: =IF($A73="","",INDEX(Assessment!$H:$H,$A73)) | H73: =IF($A73="","",INDEX(Assessment!$I:$I,$A73))
A74: =IFERROR(MATCH(70,Assessment!$N:$N,0),"") | B74: =IF($A74="","",INDEX(Assessment!$K:$K,$A74)) | C74: =IF($A74="","",INDEX(Assessment!$B:$B,$A74)) | D74: =IF($A74="","",INDEX(Assessment!$D:$D,$A74)) | E74: =IF($A74="","",INDEX(Assessment!$E:$E,$A74)) | F74: =IF($A74="","",INDEX(Assessment!$G:$G,$A74)) | G74: =IF($A74="","",INDEX(Assessment!$H:$H,$A74)) | H74: =IF($A74="","",INDEX(Assessment!$I:$I,$A74))
A75: =IFERROR(MATCH(71,Assessment!$N:$N,0),"") | B75: =IF($A75="","",INDEX(Assessment!$K:$K,$A75)) | C75: =IF($A75="","",INDEX(Assessment!$B:$B,$A75)) | D75: =IF($A75="","",INDEX(Assessment!$D:$D,$A75)) | E75: =IF($A75="","",INDEX(Assessment!$E:$E,$A75)) | F75: =IF($A75="","",INDEX(Assessment!$G:$G,$A75)) | G75: =IF($A75="","",INDEX(Assessment!$H:$H,$A75)) | H75: =IF($A75="","",INDEX(Assessment!$I:$I,$A75))
A76: =IFERROR(MATCH(72,Assessment!$N:$N,0),"") | B76: =IF($A76="","",INDEX(Assessment!$K:$K,$A76)) | C76: =IF($A76="","",INDEX(Assessment!$B:$B,$A76)) | D76: =IF($A76="","",INDEX(Assessment!$D:$D,$A76)) | E76: =IF($A76="","",INDEX(Assessment!$E:$E,$A76)) | F76: =IF($A76="","",INDEX(Assessment!$G:$G,$A76)) | G76: =IF($A76="","",INDEX(Assessment!$H:$H,$A76)) | H76: =IF($A76="","",INDEX(Assessment!$I:$I,$A76))
A77: =IFERROR(MATCH(73,Assessment!$N:$N,0),"") | B77: =IF($A77="","",INDEX(Assessment!$K:$K,$A77)) | C77: =IF($A77="","",INDEX(Assessment!$B:$B,$A77)) | D77: =IF($A77="","",INDEX(Assessment!$D:$D,$A77)) | E77: =IF($A77="","",INDEX(Assessment!$E:$E,$A77)) | F77: =IF($A77="","",INDEX(Assessment!$G:$G,$A77)) | G77: =IF($A77="","",INDEX(Assessment!$H:$H,$A77)) | H77: =IF($A77="","",INDEX(Assessment!$I:$I,$A77))
A78: =IFERROR(MATCH(74,Assessment!$N:$N,0),"") | B78: =IF($A78="","",INDEX(Assessment!$K:$K,$A78)) | C78: =IF($A78="","",INDEX(Assessment!$B:$B,$A78)) | D78: =IF($A78="","",INDEX(Assessment!$D:$D,$A78)) | E78: =IF($A78="","",INDEX(Assessment!$E:$E,$A78)) | F78: =IF($A78="","",INDEX(Assessment!$G:$G,$A78)) | G78: =IF($A78="","",INDEX(Assessment!$H:$H,$A78)) | H78: =IF($A78="","",INDEX(Assessment!$I:$I,$A78))
A79: =IFERROR(MATCH(75,Assessment!$N:$N,0),"") | B79: =IF($A79="","",INDEX(Assessment!$K:$K,$A79)) | C79: =IF($A79="","",INDEX(Assessment!$B:$B,$A79)) | D79: =IF($A79="","",INDEX(Assessment!$D:$D,$A79)) | E79: =IF($A79="","",INDEX(Assessment!$E:$E,$A79)) | F79: =IF($A79="","",INDEX(Assessment!$G:$G,$A79)) | G79: =IF($A79="","",INDEX(Assessment!$H:$H,$A79)) | H79: =IF($A79="","",INDEX(Assessment!$I:$I,$A79))
A80: =IFERROR(MATCH(76,Assessment!$N:$N,0),"") | B80: =IF($A80="","",INDEX(Assessment!$K:$K,$A80)) | C80: =IF($A80="","",INDEX(Assessment!$B:$B,$A80)) | D80: =IF($A80="","",INDEX(Assessment!$D:$D,$A80)) | E80: =IF($A80="","",INDEX(Assessment!$E:$E,$A80)) | F80: =IF($A80="","",INDEX(Assessment!$G:$G,$A80)) | G80: =IF($A80="","",INDEX(Assessment!$H:$H,$A80)) | H80: =IF($A80="","",INDEX(Assessment!$I:$I,$A80))
A81: =IFERROR(MATCH(77,Assessment!$N:$N,0),"") | B81: =IF($A81="","",INDEX(Assessment!$K:$K,$A81)) | C81: =IF($A81="","",INDEX(Assessment!$B:$B,$A81)) | D81: =IF($A81="","",INDEX(Assessment!$D:$D,$A81)) | E81: =IF($A81="","",INDEX(Assessment!$E:$E,$A81)) | F81: =IF($A81="","",INDEX(Assessment!$G:$G,$A81)) | G81: =IF($A81="","",INDEX(Assessment!$H:$H,$A81)) | H81: =IF($A81="","",INDEX(Assessment!$I:$I,$A81))
A82: =IFERROR(MATCH(78,Assessment!$N:$N,0),"") | B82: =IF($A82="","",INDEX(Assessment!$K:$K,$A82)) | C82: =IF($A82="","",INDEX(Assessment!$B:$B,$A82)) | D82: =IF($A82="","",INDEX(Assessment!$D:$D,$A82)) | E82: =IF($A82="","",INDEX(Assessment!$E:$E,$A82)) | F82: =IF($A82="","",INDEX(Assessment!$G:$G,$A82)) | G82: =IF($A82="","",INDEX(Assessment!$H:$H,$A82)) | H82: =IF($A82="","",INDEX(Assessment!$I:$I,$A82))
A83: =IFERROR(MATCH(79,Assessment!$N:$N,0),"") | B83: =IF($A83="","",INDEX(Assessment!$K:$K,$A83)) | C83: =IF($A83="","",INDEX(Assessment!$B:$B,$A83)) | D83: =IF($A83="","",INDEX(Assessment!$D:$D,$A83)) | E83: =IF($A83="","",INDEX(Assessment!$E:$E,$A83)) | F83: =IF($A83="","",INDEX(Assessment!$G:$G,$A83)) | G83: =IF($A83="","",INDEX(Assessment!$H:$H,$A83)) | H83: =IF($A83="","",INDEX(Assessment!$I:$I,$A83))
A84: =IFERROR(MATCH(80,Assessment!$N:$N,0),"") | B84: =IF($A84="","",INDEX(Assessment!$K:$K,$A84)) | C84: =IF($A84="","",INDEX(Assessment!$B:$B,$A84)) | D84: =IF($A84="","",INDEX(Assessment!$D:$D,$A84)) | E84: =IF($A84="","",INDEX(Assessment!$E:$E,$A84)) | F84: =IF($A84="","",INDEX(Assessment!$G:$G,$A84)) | G84: =IF($A84="","",INDEX(Assessment!$H:$H,$A84)) | H84: =IF($A84="","",INDEX(Assessment!$I:$I,$A84))
A85: =IFERROR(MATCH(81,Assessment!$N:$N,0),"") | B85: =IF($A85="","",INDEX(Assessment!$K:$K,$A85)) | C85: =IF($A85="","",INDEX(Assessment!$B:$B,$A85)) | D85: =IF($A85="","",INDEX(Assessment!$D:$D,$A85)) | E85: =IF($A85="","",INDEX(Assessment!$E:$E,$A85)) | F85: =IF($A85="","",INDEX(Assessment!$G:$G,$A85)) | G85: =IF($A85="","",INDEX(Assessment!$H:$H,$A85)) | H85: =IF($A85="","",INDEX(Assessment!$I:$I,$A85))
A86: =IFERROR(MATCH(82,Assessment!$N:$N,0),"") | B86: =IF($A86="","",INDEX(Assessment!$K:$K,$A86)) | C86: =IF($A86="","",INDEX(Assessment!$B:$B,$A86)) | D86: =IF($A86="","",INDEX(Assessment!$D:$D,$A86)) | E86: =IF($A86="","",INDEX(Assessment!$E:$E,$A86)) | F86: =IF($A86="","",INDEX(Assessment!$G:$G,$A86)) | G86: =IF($A86="","",INDEX(Assessment!$H:$H,$A86)) | H86: =IF($A86="","",INDEX(Assessment!$I:$I,$A86))
A87: =IFERROR(MATCH(83,Assessment!$N:$N,0),"") | B87: =IF($A87="","",INDEX(Assessment!$K:$K,$A87)) | C87: =IF($A87="","",INDEX(Assessment!$B:$B,$A87)) | D87: =IF($A87="","",INDEX(Assessment!$D:$D,$A87)) | E87: =IF($A87="","",INDEX(Assessment!$E:$E,$A87)) | F87: =IF($A87="","",INDEX(Assessment!$G:$G,$A87)) | G87: =IF($A87="","",INDEX(Assessment!$H:$H,$A87)) | H87: =IF($A87="","",INDEX(Assessment!$I:$I,$A87))
A88: =IFERROR(MATCH(84,Assessment!$N:$N,0),"") | B88: =IF($A88="","",INDEX(Assessment!$K:$K,$A88)) | C88: =IF($A88="","",INDEX(Assessment!$B:$B,$A88)) | D88: =IF($A88="","",INDEX(Assessment!$D:$D,$A88)) | E88: =IF($A88="","",INDEX(Assessment!$E:$E,$A88)) | F88: =IF($A88="","",INDEX(Assessment!$G:$G,$A88)) | G88: =IF($A88="","",INDEX(Assessment!$H:$H,$A88)) | H88: =IF($A88="","",INDEX(Assessment!$I:$I,$A88))
A89: =IFERROR(MATCH(85,Assessment!$N:$N,0),"") | B89: =IF($A89="","",INDEX(Assessment!$K:$K,$A89)) | C89: =IF($A89="","",INDEX(Assessment!$B:$B,$A89)) | D89: =IF($A89="","",INDEX(Assessment!$D:$D,$A89)) | E89: =IF($A89="","",INDEX(Assessment!$E:$E,$A89)) | F89: =IF($A89="","",INDEX(Assessment!$G:$G,$A89)) | G89: =IF($A89="","",INDEX(Assessment!$H:$H,$A89)) | H89: =IF($A89="","",INDEX(Assessment!$I:$I,$A89))
A90: =IFERROR(MATCH(86,Assessment!$N:$N,0),"") | B90: =IF($A90="","",INDEX(Assessment!$K:$K,$A90)) | C90: =IF($A90="","",INDEX(Assessment!$B:$B,$A90)) | D90: =IF($A90="","",INDEX(Assessment!$D:$D,$A90)) | E90: =IF($A90="","",INDEX(Assessment!$E:$E,$A90)) | F90: =IF($A90="","",INDEX(Assessment!$G:$G,$A90)) | G90: =IF($A90="","",INDEX(Assessment!$H:$H,$A90)) | H90: =IF($A90="","",INDEX(Assessment!$I:$I,$A90))
A91: =IFERROR(MATCH(87,Assessment!$N:$N,0),"") | B91: =IF($A91="","",INDEX(Assessment!$K:$K,$A91)) | C91: =IF($A91="","",INDEX(Assessment!$B:$B,$A91)) | D91: =IF($A91="","",INDEX(Assessment!$D:$D,$A91)) | E91: =IF($A91="","",INDEX(Assessment!$E:$E,$A91)) | F91: =IF($A91="","",INDEX(Assessment!$G:$G,$A91)) | G91: =IF($A91="","",INDEX(Assessment!$H:$H,$A91)) | H91: =IF($A91="","",INDEX(Assessment!$I:$I,$A91))
A92: =IFERROR(MATCH(88,Assessment!$N:$N,0),"") | B92: =IF($A92="","",INDEX(Assessment!$K:$K,$A92)) | C92: =IF($A92="","",INDEX(Assessment!$B:$B,$A92)) | D92: =IF($A92="","",INDEX(Assessment!$D:$D,$A92)) | E92: =IF($A92="","",INDEX(Assessment!$E:$E,$A92)) | F92: =IF($A92="","",INDEX(Assessment!$G:$G,$A92)) | G92: =IF($A92="","",INDEX(Assessment!$H:$H,$A92)) | H92: =IF($A92="","",INDEX(Assessment!$I:$I,$A92))
A93: =IFERROR(MATCH(89,Assessment!$N:$N,0),"") | B93: =IF($A93="","",INDEX(Assessment!$K:$K,$A93)) | C93: =IF($A93="","",INDEX(Assessment!$B:$B,$A93)) | D93: =IF($A93="","",INDEX(Assessment!$D:$D,$A93)) | E93: =IF($A93="","",INDEX(Assessment!$E:$E,$A93)) | F93: =IF($A93="","",INDEX(Assessment!$G:$G,$A93)) | G93: =IF($A93="","",INDEX(Assessment!$H:$H,$A93)) | H93: =IF($A93="","",INDEX(Assessment!$I:$I,$A93))
A94: =IFERROR(MATCH(90,Assessment!$N:$N,0),"") | B94: =IF($A94="","",INDEX(Assessment!$K:$K,$A94)) | C94: =IF($A94="","",INDEX(Assessment!$B:$B,$A94)) | D94: =IF($A94="","",INDEX(Assessment!$D:$D,$A94)) | E94: =IF($A94="","",INDEX(Assessment!$E:$E,$A94)) | F94: =IF($A94="","",INDEX(Assessment!$G:$G,$A94)) | G94: =IF($A94="","",INDEX(Assessment!$H:$H,$A94)) | H94: =IF($A94="","",INDEX(Assessment!$I:$I,$A94))
A95: =IFERROR(MATCH(91,Assessment!$N:$N,0),"") | B95: =IF($A95="","",INDEX(Assessment!$K:$K,$A95)) | C95: =IF($A95="","",INDEX(Assessment!$B:$B,$A95)) | D95: =IF($A95="","",INDEX(Assessment!$D:$D,$A95)) | E95: =IF($A95="","",INDEX(Assessment!$E:$E,$A95)) | F95: =IF($A95="","",INDEX(Assessment!$G:$G,$A95)) | G95: =IF($A95="","",INDEX(Assessment!$H:$H,$A95)) | H95: =IF($A95="","",INDEX(Assessment!$I:$I,$A95))
A96: =IFERROR(MATCH(92,Assessment!$N:$N,0),"") | B96: =IF($A96="","",INDEX(Assessment!$K:$K,$A96)) | C96: =IF($A96="","",INDEX(Assessment!$B:$B,$A96)) | D96: =IF($A96="","",INDEX(Assessment!$D:$D,$A96)) | E96: =IF($A96="","",INDEX(Assessment!$E:$E,$A96)) | F96: =IF($A96="","",INDEX(Assessment!$G:$G,$A96)) | G96: =IF($A96="","",INDEX(Assessment!$H:$H,$A96)) | H96: =IF($A96="","",INDEX(Assessment!$I:$I,$A96))
A97: =IFERROR(MATCH(93,Assessment!$N:$N,0),"") | B97: =IF($A97="","",INDEX(Assessment!$K:$K,$A97)) | C97: =IF($A97="","",INDEX(Assessment!$B:$B,$A97)) | D97: =IF($A97="","",INDEX(Assessment!$D:$D,$A97)) | E97: =IF($A97="","",INDEX(Assessment!$E:$E,$A97)) | F97: =IF($A97="","",INDEX(Assessment!$G:$G,$A97)) | G97: =IF($A97="","",INDEX(Assessment!$H:$H,$A97)) | H97: =IF($A97="","",INDEX(Assessment!$I:$I,$A97))
A98: =IFERROR(MATCH(94,Assessment!$N:$N,0),"") | B98: =IF($A98="","",INDEX(Assessment!$K:$K,$A98)) | C98: =IF($A98="","",INDEX(Assessment!$B:$B,$A98)) | D98: =IF($A98="","",INDEX(Assessment!$D:$D,$A98)) | E98: =IF($A98="","",INDEX(Assessment!$E:$E,$A98)) | F98: =IF($A98="","",INDEX(Assessment!$G:$G,$A98)) | G98: =IF($A98="","",INDEX(Assessment!$H:$H,$A98)) | H98: =IF($A98="","",INDEX(Assessment!$I:$I,$A98))
A99: =IFERROR(MATCH(95,Assessment!$N:$N,0),"") | B99: =IF($A99="","",INDEX(Assessment!$K:$K,$A99)) | C99: =IF($A99="","",INDEX(Assessment!$B:$B,$A99)) | D99: =IF($A99="","",INDEX(Assessment!$D:$D,$A99)) | E99: =IF($A99="","",INDEX(Assessment!$E:$E,$A99)) | F99: =IF($A99="","",INDEX(Assessment!$G:$G,$A99)) | G99: =IF($A99="","",INDEX(Assessment!$H:$H,$A99)) | H99: =IF($A99="","",INDEX(Assessment!$I:$I,$A99))
A100: =IFERROR(MATCH(96,Assessment!$N:$N,0),"") | B100: =IF($A100="","",INDEX(Assessment!$K:$K,$A100)) | C100: =IF($A100="","",INDEX(Assessment!$B:$B,$A100)) | D100: =IF($A100="","",INDEX(Assessment!$D:$D,$A100)) | E100: =IF($A100="","",INDEX(Assessment!$E:$E,$A100)) | F100: =IF($A100="","",INDEX(Assessment!$G:$G,$A100)) | G100: =IF($A100="","",INDEX(Assessment!$H:$H,$A100)) | H100: =IF($A100="","",INDEX(Assessment!$I:$I,$A100))
A101: =IFERROR(MATCH(97,Assessment!$N:$N,0),"") | B101: =IF($A101="","",INDEX(Assessment!$K:$K,$A101)) | C101: =IF($A101="","",INDEX(Assessment!$B:$B,$A101)) | D101: =IF($A101="","",INDEX(Assessment!$D:$D,$A101)) | E101: =IF($A101="","",INDEX(Assessment!$E:$E,$A101)) | F101: =IF($A101="","",INDEX(Assessment!$G:$G,$A101)) | G101: =IF($A101="","",INDEX(Assessment!$H:$H,$A101)) | H101: =IF($A101="","",INDEX(Assessment!$I:$I,$A101))
...

Sheet Summary
A1: READINESS SUMMARY
A4: Branch: | B4: =Cover!B5 -> 0 | D4: Date: | E4: =Cover!B6 -> 0 | G4: Assessor: | H4: =Cover!B7 -> 0
A6: # | B6: Domain | C6: # Questions | D6: Branch answered (col H) | E6: TownSq capability (col I) | F6: PC | G6: AC | H6: FB | I6: NA | J6: Not yet classified | K6: Readiness %
A7: 1 | B7: Platform Foundation | C7: =COUNTIF(Assessment!$A$5:$A$730,$A7) -> 13 | D7: =COUNTIFS(Assessment!$A$5:$A$730,$A7,Assessment!$H$5:$H$730,"<>") -> 0 | E7: =COUNTIFS(Assessment!$A$5:$A$730,$A7,Assessment!$I$5:$I$730,"<>") -> 13 | F7: =SUMPRODUCT((Assessment!$A$5:$A$730=$A7)*(Assessment!$J$5:$J$730="PC")) -> 0 | G7: =SUMPRODUCT((Assessment!$A$5:$A$730=$A7)*(Assessment!$J$5:$J$730="AC")) -> 0 | H7: {=SUMPRODUCT((Assessment!$A$5:$A$730=$A7)*(Assessment!$J$5:$J$730="FB"))} -> 0 | I7: =SUMPRODUCT((Assessment!$A$5:$A$730=$A7)*(Assessment!$J$5:$J$730="NA")) -> 0 | J7: =C7-F7-G7-H7-I7 -> 13 | K7: =IF(OR($C7=0,$D7<$C7,$J7>0),"—",IFERROR(($F7+$G7)/($F7+$G7+$H7),"—")) -> —
A8: 2 | B8: Property & Assoc. Mgmt | C8: =COUNTIF(Assessment!$A$5:$A$730,$A8) -> 15 | D8: =COUNTIFS(Assessment!$A$5:$A$730,$A8,Assessment!$H$5:$H$730,"<>") -> 0 | E8: =COUNTIFS(Assessment!$A$5:$A$730,$A8,Assessment!$I$5:$I$730,"<>") -> 15 | F8: =SUMPRODUCT((Assessment!$A$5:$A$730=$A8)*(Assessment!$J$5:$J$730="PC")) -> 0 | G8: =SUMPRODUCT((Assessment!$A$5:$A$730=$A8)*(Assessment!$J$5:$J$730="AC")) -> 0 | H8: {=SUMPRODUCT((Assessment!$A$5:$A$730=$A8)*(Assessment!$J$5:$J$730="FB"))} -> 0 | I8: =SUMPRODUCT((Assessment!$A$5:$A$730=$A8)*(Assessment!$J$5:$J$730="NA")) -> 0 | J8: =C8-F8-G8-H8-I8 -> 15 | K8: =IF(OR($C8=0,$D8<$C8,$J8>0),"—",IFERROR(($F8+$G8)/($F8+$G8+$H8),"—")) -> —
A9: 3 | B9: Communications | C9: =COUNTIF(Assessment!$A$5:$A$730,$A9) -> 18 | D9: =COUNTIFS(Assessment!$A$5:$A$730,$A9,Assessment!$H$5:$H$730,"<>") -> 0 | E9: =COUNTIFS(Assessment!$A$5:$A$730,$A9,Assessment!$I$5:$I$730,"<>") -> 18 | F9: =SUMPRODUCT((Assessment!$A$5:$A$730=$A9)*(Assessment!$J$5:$J$730="PC")) -> 0 | G9: =SUMPRODUCT((Assessment!$A$5:$A$730=$A9)*(Assessment!$J$5:$J$730="AC")) -> 0 | H9: {=SUMPRODUCT((Assessment!$A$5:$A$730=$A9)*(Assessment!$J$5:$J$730="FB"))} -> 0 | I9: =SUMPRODUCT((Assessment!$A$5:$A$730=$A9)*(Assessment!$J$5:$J$730="NA")) -> 0 | J9: =C9-F9-G9-H9-I9 -> 18 | K9: =IF(OR($C9=0,$D9<$C9,$J9>0),"—",IFERROR(($F9+$G9)/($F9+$G9+$H9),"—")) -> —
A10: 4 | B10: Homeowner Management | C10: =COUNTIF(Assessment!$A$5:$A$730,$A10) -> 20 | D10: =COUNTIFS(Assessment!$A$5:$A$730,$A10,Assessment!$H$5:$H$730,"<>") -> 0 | E10: =COUNTIFS(Assessment!$A$5:$A$730,$A10,Assessment!$I$5:$I$730,"<>") -> 20 | F10: =SUMPRODUCT((Assessment!$A$5:$A$730=$A10)*(Assessment!$J$5:$J$730="PC")) -> 0 | G10: =SUMPRODUCT((Assessment!$A$5:$A$730=$A10)*(Assessment!$J$5:$J$730="AC")) -> 0 | H10: {=SUMPRODUCT((Assessment!$A$5:$A$730=$A10)*(Assessment!$J$5:$J$730="FB"))} -> 0 | I10: =SUMPRODUCT((Assessment!$A$5:$A$730=$A10)*(Assessment!$J$5:$J$730="NA")) -> 0 | J10: =C10-F10-G10-H10-I10 -> 20 | K10: =IF(OR($C10=0,$D10<$C10,$J10>0),"—",IFERROR(($F10+$G10)/($F10+$G10+$H10),"—")) -> —
A11: 5 | B11: Operations & Tasks | C11: =COUNTIF(Assessment!$A$5:$A$730,$A11) -> 22 | D11: =COUNTIFS(Assessment!$A$5:$A$730,$A11,Assessment!$H$5:$H$730,"<>") -> 0 | E11: =COUNTIFS(Assessment!$A$5:$A$730,$A11,Assessment!$I$5:$I$730,"<>") -> 22 | F11: =SUMPRODUCT((Assessment!$A$5:$A$730=$A11)*(Assessment!$J$5:$J$730="PC")) -> 0 | G11: =SUMPRODUCT((Assessment!$A$5:$A$730=$A11)*(Assessment!$J$5:$J$730="AC")) -> 0 | H11: {=SUMPRODUCT((Assessment!$A$5:$A$730=$A11)*(Assessment!$J$5:$J$730="FB"))} -> 0 | I11: =SUMPRODUCT((Assessment!$A$5:$A$730=$A11)*(Assessment!$J$5:$J$730="NA")) -> 0 | J11: =C11-F11-G11-H11-I11 -> 22 | K11: =IF(OR($C11=0,$D11<$C11,$J11>0),"—",IFERROR(($F11+$G11)/($F11+$G11+$H11),"—")) -> —
A12: 6 | B12: Financial Operations | C12: =COUNTIF(Assessment!$A$5:$A$730,$A12) -> 428 | D12: =COUNTIFS(Assessment!$A$5:$A$730,$A12,Assessment!$H$5:$H$730,"<>") -> 0 | E12: =COUNTIFS(Assessment!$A$5:$A$730,$A12,Assessment!$I$5:$I$730,"<>") -> 219 | F12: =SUMPRODUCT((Assessment!$A$5:$A$730=$A12)*(Assessment!$J$5:$J$730="PC")) -> 0 | G12: =SUMPRODUCT((Assessment!$A$5:$A$730=$A12)*(Assessment!$J$5:$J$730="AC")) -> 0 | H12: {=SUMPRODUCT((Assessment!$A$5:$A$730=$A12)*(Assessment!$J$5:$J$730="FB"))} -> 0 | I12: =SUMPRODUCT((Assessment!$A$5:$A$730=$A12)*(Assessment!$J$5:$J$730="NA")) -> 0 | J12: =C12-F12-G12-H12-I12 -> 428 | K12: =IF(OR($C12=0,$D12<$C12,$J12>0),"—",IFERROR(($F12+$G12)/($F12+$G12+$H12),"—")) -> —
A13: 7 | B13: Violations & ACC | C13: =COUNTIF(Assessment!$A$5:$A$730,$A13) -> 57 | D13: =COUNTIFS(Assessment!$A$5:$A$730,$A13,Assessment!$H$5:$H$730,"<>") -> 0 | E13: =COUNTIFS(Assessment!$A$5:$A$730,$A13,Assessment!$I$5:$I$730,"<>") -> 3 | F13: =SUMPRODUCT((Assessment!$A$5:$A$730=$A13)*(Assessment!$J$5:$J$730="PC")) -> 0 | G13: =SUMPRODUCT((Assessment!$A$5:$A$730=$A13)*(Assessment!$J$5:$J$730="AC")) -> 0 | H13: {=SUMPRODUCT((Assessment!$A$5:$A$730=$A13)*(Assessment!$J$5:$J$730="FB"))} -> 0 | I13: =SUMPRODUCT((Assessment!$A$5:$A$730=$A13)*(Assessment!$J$5:$J$730="NA")) -> 0 | J13: =C13-F13-G13-H13-I13 -> 57 | K13: =IF(OR($C13=0,$D13<$C13,$J13>0),"—",IFERROR(($F13+$G13)/($F13+$G13+$H13),"—")) -> —
A14: 8 | B14: Board Management | C14: =COUNTIF(Assessment!$A$5:$A$730,$A14) -> 8 | D14: =COUNTIFS(Assessment!$A$5:$A$730,$A14,Assessment!$H$5:$H$730,"<>") -> 0 | E14: =COUNTIFS(Assessment!$A$5:$A$730,$A14,Assessment!$I$5:$I$730,"<>") -> 8 | F14: =SUMPRODUCT((Assessment!$A$5:$A$730=$A14)*(Assessment!$J$5:$J$730="PC")) -> 0 | G14: =SUMPRODUCT((Assessment!$A$5:$A$730=$A14)*(Assessment!$J$5:$J$730="AC")) -> 0 | H14: {=SUMPRODUCT((Assessment!$A$5:$A$730=$A14)*(Assessment!$J$5:$J$730="FB"))} -> 0 | I14: =SUMPRODUCT((Assessment!$A$5:$A$730=$A14)*(Assessment!$J$5:$J$730="NA")) -> 0 | J14: =C14-F14-G14-H14-I14 -> 8 | K14: =IF(OR($C14=0,$D14<$C14,$J14>0),"—",IFERROR(($F14+$G14)/($F14+$G14+$H14),"—")) -> —
A15: 9 | B15: Board Packets & Meetings | C15: =COUNTIF(Assessment!$A$5:$A$730,$A15) -> 6 | D15: =COUNTIFS(Assessment!$A$5:$A$730,$A15,Assessment!$H$5:$H$730,"<>") -> 0 | E15: =COUNTIFS(Assessment!$A$5:$A$730,$A15,Assessment!$I$5:$I$730,"<>") -> 6 | F15: =SUMPRODUCT((Assessment!$A$5:$A$730=$A15)*(Assessment!$J$5:$J$730="PC")) -> 0 | G15: =SUMPRODUCT((Assessment!$A$5:$A$730=$A15)*(Assessment!$J$5:$J$730="AC")) -> 0 | H15: {=SUMPRODUCT((Assessment!$A$5:$A$730=$A15)*(Assessment!$J$5:$J$730="FB"))} -> 0 | I15: =SUMPRODUCT((Assessment!$A$5:$A$730=$A15)*(Assessment!$J$5:$J$730="NA")) -> 0 | J15: =C15-F15-G15-H15-I15 -> 6 | K15: =IF(OR($C15=0,$D15<$C15,$J15>0),"—",IFERROR(($F15+$G15)/($F15+$G15+$H15),"—")) -> —
A16: 10 | B16: Insurance Tracking | C16: =COUNTIF(Assessment!$A$5:$A$730,$A16) -> 6 | D16: =COUNTIFS(Assessment!$A$5:$A$730,$A16,Assessment!$H$5:$H$730,"<>") -> 0 | E16: =COUNTIFS(Assessment!$A$5:$A$730,$A16,Assessment!$I$5:$I$730,"<>") -> 6 | F16: =SUMPRODUCT((Assessment!$A$5:$A$730=$A16)*(Assessment!$J$5:$J$730="PC")) -> 0 | G16: =SUMPRODUCT((Assessment!$A$5:$A$730=$A16)*(Assessment!$J$5:$J$730="AC")) -> 0 | H16: {=SUMPRODUCT((Assessment!$A$5:$A$730=$A16)*(Assessment!$J$5:$J$730="FB"))} -> 0 | I16: =SUMPRODUCT((Assessment!$A$5:$A$730=$A16)*(Assessment!$J$5:$J$730="NA")) -> 0 | J16: =C16-F16-G16-H16-I16 -> 6 | K16: =IF(OR($C16=0,$D16<$C16,$J16>0),"—",IFERROR(($F16+$G16)/($F16+$G16+$H16),"—")) -> —
A17: 11 | B17: Reserve Analysis | C17: =COUNTIF(Assessment!$A$5:$A$730,$A17) -> 7 | D17: =COUNTIFS(Assessment!$A$5:$A$730,$A17,Assessment!$H$5:$H$730,"<>") -> 0 | E17: =COUNTIFS(Assessment!$A$5:$A$730,$A17,Assessment!$I$5:$I$730,"<>") -> 7 | F17: =SUMPRODUCT((Assessment!$A$5:$A$730=$A17)*(Assessment!$J$5:$J$730="PC")) -> 0 | G17: =SUMPRODUCT((Assessment!$A$5:$A$730=$A17)*(Assessment!$J$5:$J$730="AC")) -> 0 | H17: {=SUMPRODUCT((Assessment!$A$5:$A$730=$A17)*(Assessment!$J$5:$J$730="FB"))} -> 0 | I17: =SUMPRODUCT((Assessment!$A$5:$A$730=$A17)*(Assessment!$J$5:$J$730="NA")) -> 0 | J17: =C17-F17-G17-H17-I17 -> 7 | K17: =IF(OR($C17=0,$D17<$C17,$J17>0),"—",IFERROR(($F17+$G17)/($F17+$G17+$H17),"—")) -> —
A18: 12 | B18: Document Management | C18: =COUNTIF(Assessment!$A$5:$A$730,$A18) -> 7 | D18: =COUNTIFS(Assessment!$A$5:$A$730,$A18,Assessment!$H$5:$H$730,"<>") -> 0 | E18: =COUNTIFS(Assessment!$A$5:$A$730,$A18,Assessment!$I$5:$I$730,"<>") -> 7 | F18: =SUMPRODUCT((Assessment!$A$5:$A$730=$A18)*(Assessment!$J$5:$J$730="PC")) -> 0 | G18: =SUMPRODUCT((Assessment!$A$5:$A$730=$A18)*(Assessment!$J$5:$J$730="AC")) -> 0 | H18: {=SUMPRODUCT((Assessment!$A$5:$A$730=$A18)*(Assessment!$J$5:$J$730="FB"))} -> 0 | I18: =SUMPRODUCT((Assessment!$A$5:$A$730=$A18)*(Assessment!$J$5:$J$730="NA")) -> 0 | J18: =C18-F18-G18-H18-I18 -> 7 | K18: =IF(OR($C18=0,$D18<$C18,$J18>0),"—",IFERROR(($F18+$G18)/($F18+$G18+$H18),"—")) -> —
... A22: 16 | B22: Implementation & Transition | C22: =COUNTIF(Assessment!$A$5:$A$730,$A22) -> 9 | D22: =COUNTIFS(Assessment!$A$5:$A$730,$A22,Assessment!$H$5:$H$730,"<>") -> 0 | E22: =COUNTIFS(Assessment!$A$5:$A$730,$A22,Assessment!$I$5:$I$730,"<>") -> 9 | F22: =SUMPRODUCT((Assessment!$A$5:$A$730=$A22)*(Assessment!$J$5:$J$730="PC")) -> 0 | G22: =SUMPRODUCT((Assessment!$A$5:$A$730=$A22)*(Assessment!$J$5:$J$730="AC")) -> 0 | H22: {=SUMPRODUCT((Assessment!$A$5:$A$730=$A22)*(Assessment!$J$5:$J$730="FB"))} -> 0 | I22: =SUMPRODUCT((Assessment!$A$5:$A$730=$A22)*(Assessment!$J$5:$J$730="NA")) -> 0 | J22: =C22-F22-G22-H22-I22 -> 9 | K22: =IF(OR($C22=0,$D22<$C22,$J22>0),"—",IFERROR(($F22+$G22)/($F22+$G22+$H22),"—")) -> —
B23: TOTAL | C23: =SUM(C7:C22) -> 641 | D23: =SUM(D7:D22) -> 0 | E23: =SUM(E7:E22) -> 378 | F23: =SUM(F7:F22) -> 0 | G23: =SUM(G7:G22) -> 0 | H23: =SUM(H7:H22) -> 0 | I23: =SUM(I7:I22) -> 0 | J23: =SUM(J7:J22) -> 641 | K23: =IF(OR($C23=0,$D23<$C23,$J23>0),"—",IFERROR(($F23+$G23)/($F23+$G23+$H23),"—")) -> —
A25: Domains are now numbered 1–16 with no gaps. The rubric previously numbered them 1–6 then 10–19, leaving 7, 8 and 9 empty; those three slots held no rows, no branch answers and no classifications, so they were closed rather than carried. See the Renumber Map sheet to translate any reference written against the old numbers.
A27: READINESS IS DELIBERATELY SUPPRESSED. A readiness figure is only valid once the branch answer (col H) has been compared against the TownSq capability (col I) and recorded as PC / AC / FB / NA in col J. Until then this column shows "—" by design — it is not a broken formula.
A29: The gate: Readiness returns "—" whenever # Questions = 0, Branch answered < # Questions, or Not yet classified > 0.
A31: Not yet classified = # Questions − PC − AC − FB − NA — the assessor work queue.
A33: Counts read Assessment rows 5–730, matched on Dom # in column A, with classification read from column J.

Sheet Renumber Map
A1: UID (unchanged) | B1: Assessment row | C1: Old Dom # | D1: New Dom # | E1: Old Cap # | F1: New Cap # | G1: Old QID | H1: New QID | I1: Domain | J1: Capability | K1: Dimension
A2: Q0001 | B2: 5 | C2: 1 | D2: 1 | E2: 1.1 | F2: 1.1 | G2: 1.1.1 | H2: 1.1.1 | I2: Platform Foundation | J2: General System Access | K2: Multi-system navigation
A3: Q0002 | B3: 6 | C3: 1 | D3: 1 | E3: 1.1 | F3: 1.1 | G3: 1.1.2 | H3: 1.1.2 | I3: Platform Foundation | J3: General System Access | K3: User account management
A4: Q0003 | B4: 7 | C4: 1 | D4: 1 | E4: 1.1 | F4: 1.1 | G4: 1.1.3 | H4: 1.1.3 | I4: Platform Foundation | J4: General System Access | K4: Password reset / access mgmt
A5: Q0004 | B5: 8 | C5: 1 | D5: 1 | E5: 1.1 | F5: 1.1 | G5: 1.1.4 | H5: 1.1.4 | I5: Platform Foundation | J5: General System Access | K5: Issue submission process
A6: Q0005 | B6: 9 | C6: 1 | D6: 1 | E6: 1.2 | F6: 1.2 | G6: 1.2.1 | H6: 1.2.1 | I6: Platform Foundation | J6: User Security / Permissions | K6: Role-based access control
A7: Q0006 | B7: 10 | C7: 1 | D7: 1 | E7: 1.2 | F7: 1.2 | G7: 1.2.2 | H7: 1.2.2 | I7: Platform Foundation | J7: User Security / Permissions | K7: Board member access
A8: Q0007 | B8: 11 | C8: 1 | D8: 1 | E8: 1.2 | F8: 1.2 | G8: 1.2.3 | H8: 1.2.3 | I8: Platform Foundation | J8: User Security / Permissions | K8: Attorney / external access
A9: Q0008 | B9: 12 | C9: 1 | D9: 1 | E9: 1.2 | F9: 1.2 | G9: 1.2.4 | H9: 1.2.4 | I9: Platform Foundation | J9: User Security / Permissions | K9: LOA / temporary access mgmt
A10: Q0009 | B10: 13 | C10: 1 | D10: 1 | E10: 1.3 | F10: 1.3 | G10: 1.3.1 | H10: 1.3.1 | I10: Platform Foundation | J10: Data Management / Master Data | K10: Association record structure
A11: Q0010 | B11: 14 | C11: 1 | D11: 1 | E11: 1.3 | F11: 1.3 | G11: 1.3.2 | H11: 1.3.2 | I11: Platform Foundation | J11: Data Management / Master Data | K11: Unit / lot data completeness
A12: Q0011 | B12: 15 | C12: 1 | D12: 1 | E12: 1.3 | F12: 1.3 | G12: 1.3.3 | H12: 1.3.3 | I12: Platform Foundation | J12: Data Management / Master Data | K12: Tax ID / legal entity data
A13: Q0012 | B13: 16 | C13: 1 | D13: 1 | E13: 1.3 | F13: 1.3 | G13: 1.3.4 | H13: 1.3.4 | I13: Platform Foundation | J13: Data Management / Master Data | K13: Transition-in / out process
... A642: Q0641 | B642: 645 | C642: 19 | D642: 16 | E642: 19.3 | F642: 16.3 | G642: 19.3.3 | H642: 16.3.3 | I642: Implementation & Transition | J642: Post Go-Live | K642: User adoption measurement
